Workbook

Sheet Inicio
B1: CONTROL DE BOLETOS — TDS · PIN · PKS
B2: Un solo libro para los tres buses, dividido por meses. Se cargaron los viajes de octubre de TDS y PIN; PKS empieza vacío.
B4: MENÚ — haz clic en una opción para ir a esa hoja
B5: ✎ REGISTRO — anotar un viaje nuevo o corregir uno
B6: 🔎 CONSULTA — ver los viajes de un bus en un mes
B7: 📅 RESUMEN — totales de cada mes del año
B8: 📊 RESUMEN DIARIO — cada día del mes de un bus
B9: 🧾 FACTURAS — registrar facturas y calcular el IVA del mes
B10: Las celdas amarillas son las que tú escribes o eliges; todo lo demás se calcula solo.
B12: 1. REGISTRAR UN VIAJE (ventana emergente)
B13: Primera vez (una sola vez): clic derecho en la barra de acceso rápido (arriba a la izquierda) → Personalizar barra de herramientas de acceso rápido → en «Comandos disponibles en» elige «Comandos que no están en la cinta de opciones» → busca «Formulario…» → Agregar → Aceptar. En Excel para Mac: pestaña Datos → Formulario.
B14: Cada vez: ve a la hoja Registro, haz clic en cualquier celda con datos y pulsa el botón Formulario. Se abre una ventana con un campo por cada columna.
... B30: Cálculo: hoja automática; no escribas ahí. Capacidad: 1000 viajes, unos 12 meses para los tres buses (filas 2 a 1001 de Registro).

Sheet Registro
A1: Bus | B1: Fecha | C1: Destino | D1: Hora salida - llegada | E1: Boletos de ida (detalle) | F1: Descuento ida (monto) | G1: Boletos de llegada (detalle) | H1: Monto registrado que trajeron | I1: Gastos (concepto y monto) | J1: Otros gastos (concepto y monto) | K1: Observaciones | M1: ⌂ Inicio
A2: TDS | B2: 46296 | C2: Lp | D2: 08:30 - 15:30 | E2: 25x40; 3x50 | G2: 1x3300 | H2: 3300 | I2: Peaje 50; Veatico 50
A3: TDS | B3: 46297 | C3: Cbba | D3: 6:30 - 17:30 | E3: 15x40; 15x50; 5x60 | G3: 1x4060 | H3: 4060 | I3: Peaje 50; Veatico 50; Gasto 100
A4: TDS | B4: 46298 | C4: Cbba | D4: 5:30 - 15:30 | E4: 43x50; 2x80; 10x70 | G4: 1x3599 | H4: 3599 | I4: Peaje 50; Veatico 50 | J4: Diesel 8400
A5: TDS | B5: 46299 | C5: Lp | D5: 4:00 | E5: 43x40; 4x50; 7x60 | G5: 1x2080 | H5: 2080 | I5: Peaje 50; Veatico 50; Engrase 40
A6: TDS | B6: 46300 | C6: Cbba | D6: 9:30-17:00 | E6: 37x40; 2x50; 2x70; 8x60 | G6: 1x3300 | H6: 3300 | I6: Peaje 50; Diesel 400; Veatico 50 | J6: Diesel 7500
A7: TDS | B7: 46301 | C7: Lp | D7: 15:30-4:00 | E7: 9x60; 2x70; 45x50 | G7: 1x2350 | H7: 2350 | I7: Peaje 50; Veatico 50
A8: TDS | B8: 46302 | C8: Lp | D8: 6:30-14:30 | E8: 24x40; 4x60; 5x50 | G8: 1x2455 | H8: 2455 | I8: Peaje 50; Veatico 50
A9: TDS | B9: 46303 | C9: Lp | D9: 19:30-8:00 | E9: 35x40; 11x60 | G9: 1x2365 | H9: 2365 | I9: Peaje 50
A10: TDS | B10: 46304 | C10: Lp | D10: 4:00-11:00 | E10: 14x40; 31x50; 1x60; 4x70; 7x60 | G10: 1x2395 | H10: 2395
A11: TDS | B11: 46305 | C11: Cbba | D11: 7:00-14:30 | E11: 30x40; 12x35; 1x70 | G11: 1x3670 | H11: 3670 | I11: Peaje 50; Veatico 50 | J11: Diesel 8380
A12: TDS | B12: 46305 | C12: Lp | D12: 17:30-4:30 | E12: 19x40; 10x60; 5x50; 11x35 | G12: 1x2100 | H12: 2100
A13: TDS | B13: 46306 | C13: Cbba | D13: 12:00-19:00 | E13: 46x50; 4x70 | G13: 1x5280 | H13: 5280 | I13: Peaje 50; Veatico 50; Engrase 30
A14: TDS | B14: 46307 | C14: Lp | D14: 4:30-16:30 | E14: 38x40; 5x60; 8x50 | G14: 1x2855 | H14: 2855 | I14: Peaje 50; Veatico 50; Ayudante 120 | J14: Diesel 8190
A15: TDS | B15: 46308 | C15: Cbba | D15: 4:30-19:00 | E15: 36x40; 3x60; 2x50 | G15: 1x2960 | H15: 2960 | I15: Peaje 50; Veatico 50; Engrase 20
A16: TDS | B16: 46309 | C16: Lp | D16: 3:30-16:00 | E16: 29x40; 3x50; 10x60 | G16: 1x2070 | H16: 2070 | I16: Peaje 50; Veatico 50; Diesel 500
A17: TDS | B17: 46310 | C17: Lp | D17: 3:30-14:30 | E17: Sin boleto | G17: Sin boleto | H17: 2870 | I17: Peaje 50; Veatico 50; Extra 20 | J17: Diesel 8370
A18: TDS | B18: 46311 | C18: Lp | D18: 5:00-19:00 | E18: Sin boleto | G18: 1x3250 | H18: 3250 | I18: Peaje 50; Veatico 50; Engrase 40
A19: TDS | B19: 46312 | C19: Cbba | D19: 05:00-12:00 | E19: 29x50; 18x60; 11x80 | G19: 1x3360 | H19: 3360 | I19: Peaje 60; Veatico 50; Taxi 20 | J19: Diesel 5550
A20: TDS | B20: 46313 | C20: Lp | D20: 7:00-15:30 | E20: 37x40; 5x60 | G20: 1x3275 | H20: 3275 | I20: Peaje 45; Veatico 50
A21: TDS | B21: 46314 | C21: Cbba | D21: 3:30-12:00 | E21: 41x50; 7x40; 4x80 | G21: 1x3275 | H21: 3275 | I21: Peaje 45; Veatico 50; Ayudante 120
A22: TDS | B22: 46315 | C22: Lp | D22: 3:30-10:00 | E22: 42x50; 5x70; 2x60 | G22: 1x2340 | H22: 2340 | I22: Peaje 50; Veatico 50 | J22: Diesel 8500
A23: TDS | B23: 46316 | C23: Lp | D23: 4:30-17:00 | E23: 7x70; 35x50 | G23: Sin boleto | H23: 0
A24: TDS | B24: 46317 | C24: Cbba | D24: 6:30-15:30 | E24: 19x50; 6x40; 4x70; 4x60 | G24: Sin boleto | H24: 3760 | I24: Peaje 50; Veatico 50; Engrase 30
A25: TDS | B25: 46318 | C25: Lp | D25: 4:30-11:00 | E25: 47x50; 12x70 | G25: 1x2335 | H25: 2335 | I25: Peaje 45; Veatico 50 | J25: Diesel 8400
A26: PIN | B26: 46296 | C26: Lp | D26: 17:30-5:30 | E26: 31x40; 5x50; 7X60 | G26: 1X1925 | H26: 1925 | I26: Peaje 50; Veatico 50
A27: PIN | B27: 46297 | C27: Lp | D27: 17:30-5:30 | E27: 29x40; 13x50; 6x60; 4x70 | G27: 1x2520 | H27: 2520 | K27: Bultos 180
A28: PIN | B28: 46298 | C28: Lp | D28: 16:00-5:30 | E28: 32x40; 8x70; 4x60 | G28: 1x2215 | H28: 2215 | K28: Bultos 300
A29: PIN | B29: 46299 | C29: Cbba | D29: 15:30-5:00 | E29: 18x40; 15x50; 4x70; 8x60 | G29: 1x3860 | H29: 3860 | I29: Peaje 50; Veatico 50
A30: PIN | B30: 46300 | C30: Lp | D30: 13:30-20:30 | E30: 38x40; 10x60; 1x70 | G30: 1x2685 | H30: 2685 | I30: Peaje 50; Veatico 50; Engrase-Llantas 100; Gastos 65
A31: PIN | B31: 46302 | C31: Lp | D31: 04:30-12:00 | E31: 3x70; 5x60; 42x50 | G31: 1x2235 | H31: 2235 | I31: Peaje 52; Veatico 50; Gastos 70
A32: PIN | B32: 46303 | C32: Cbba | D32: 3:30-12:00 | E32: 1x80; 4x70; 7x60; 20x50 | G32: 1x3300 | H32: 3300 | I32: Peaje 50; Veatico 50; Gasto 80
A33: PIN | B33: 46304 | C33: Lp | D33: 4:30-13:30 | E33: 29x40; 18x50; 3x70; 8x60 | G33: 1x2855 | H33: 2855 | I33: Peaje 50; Veatico 50; engrase 45
A34: PIN | B34: 46305 | C34: Lp | D34: 5:30-14:30 | E34: 37x40; 10x60 | G34: 1x3015 | H34: 3015 | I34: Peaje 55; Veatico 50
A35: PIN | B35: 46306 | C35: Lp | D35: 4:30-13:00 | E35: 47x50; 2x70 | G35: 1x2825 | H35: 2825 | I35: Peaje 55; Veatico 50
A36: PIN | B36: 46306 | C36: Lp | D36: 16:00-7:30 | E36: 7x70; 14x40; 22x50; 5x60 | G36: 1x1425 | H36: 1425 | I36: Peaje 55; Veatico 50
A37: PIN | B37: 46307 | C37: Lp | D37: 18:00-12:30 | E37: 49x50; 12x70 | G37: 1x2795 | H37: 2795 | I37: Peaje 55; Veatico 50
A38: PIN | B38: 46308 | C38: Lp | D38: 3:30-10:00 | E38: 30x50; 2x70; 2x90; 1x60 | G38: 1x1415 | H38: 1415 | I38: Peaje 55; Veatico 50
A39: PIN | B39: 46309 | C39: Lp | D39: 19:30-8:30 | E39: 44x40; 11x60 | G39: 1x2115 | H39: 2115 | I39: Peaje 55; Veatico 50
A40: PIN | B40: 46310 | C40: Lp | D40: 19:30-7:30 | E40: 49x40; 1x50; 11x60 | G40: 1x1905 | H40: 1905 | I40: Peaje 55; Veatico 50
... A46: PIN | B46: 46318 | C46: Cbba | D46: 3:30-14:30 | E46: 40x50; 2x60; 12x70 | G46: 43x60; 2x80; 5x50; 10x70 | H46: 3750 | I46: Engrase 40; gastos 90
A47: TDS | B47: 46319 | C47: Lp | D47: 4:00-13:30 | E47: 43x50; 6x70; 2x80; 1x60 | G47: 1x2815 | H47: 2815 | I47: Veatico 92 | J47: Diesel 2700
A48: TDS | B48: 46320 | C48: Lp | D48: 4:30-13:30 | E48: 13x50; 18x40; 2x60; 1x70 | G48: 1x200 | H48: 200
A49: PIN | B49: 46319 | C49: Lp | D49: 5:00-12:00 | E49: 40x50; 8x70; 3x60 | G49: 3x80; 1x70; 7x40; 4x60; 8x55; 20x50 | H49: 2415 | I49: veatico 50; Peaje 40 | J49: Diesel 2500 | K49: Aumento 200 rudy
A50: PIN | B50: 46320 | C50: Cbba | D50: 5:00-14:30 | E50: 32x50; 5x70; 1x60 | G50: 26x50; 7x70; 2x80; 2x90; 13x60 | H50: 3560 | I50: veatico 50; peaje 40; llantero 350 | J50: Diesel 3000; devolviorRudy 200

Sheet Consulta
A1: ="CONSULTA — "&$B$3&" · "&$F$3&" "&$D$3 -> CONSULTA — TDS · Octubre 2026
A2: Elige el bus, el año y el mes (celdas amarillas). Se muestran los viajes de ese bus y mes con todos los cálculos. «Fila en Registro» indica dónde corregir un dato.
A3: Bus: | B3: TDS | C3: Año: | D3: 2026 | E3: Mes: | F3: Octubre | G3: Clave: | H3: =$D$3*100+MATCH($F$3,{"Enero","Febrero","Marzo","Abril","Mayo","Junio","Julio","Agosto","Septiembre","Octubre","Noviembre","Diciembre"},0) -> 202610 | I3: ⌂ Inicio | J3: MONTO IDA (normal) | L3: DESCUENTO | N3: IDA NETO | P3: MONTO LLEGADA | R3: GASTOS + OTROS | T3: NETO FINAL
J4: =G7 -> 53675 | L4: =H7 -> 0 | N4: =I7 -> 53675 | P4: =N7 -> 72319 | R4: =P7+S7 -> 69567 | T4: =T7 -> 2752
A5: INFORMACIÓN DEL VIAJE | E5: IDA | J5: LLEGADA | O5: GASTOS Y NETO | R5: OTROS GASTOS | U5: NOTAS
A6: Fila en Registro | B6: Fecha | C6: Destino | D6: Hora salida - llegada | E6: Boletos de ida (detalle) | F6: Total boletos ida (cant.) | G6: Monto total de ida | H6: Descuento ida | I6: Monto ida neto | J6: Boletos de llegada (detalle) | K6: Total boletos llegada (cant.) | L6: Monto calculado | M6: Verificación | N6: Monto registrado que trajeron | O6: Gastos (detalle) | P6: Total gastos | Q6: Total menos gastos | R6: Otros gastos (detalle) | S6: Total otros gastos | T6: Neto final | U6: Observaciones
B7: TOTALES | C7: =COUNT(B8:B69) -> 26 | F7: =SUM(F8:F69) -> 1106 | G7: =SUM(G8:G69) -> 53675 | H7: =SUM(H8:H69) -> 0 | I7: =SUM(I8:I69) -> 53675 | K7: =SUM(K8:K69) -> 23 | L7: =SUM(L8:L69) -> 72319 | N7: =SUM(N8:N69) -> 72319 | P7: =SUM(P8:P69) -> 3577 | Q7: =SUM(Q8:Q69) -> 68742 | S7: =SUM(S8:S69) -> 65990 | T7: =SUM(T8:T69) -> 2752
A8: =IFERROR(MOD(SMALL(Cálculo!$O$2:$O$1001,ROWS(A$8:A8)),10000),"") -> 2 | B8: =IF($A8="","",IF(INDEX(Registro!$B$1:$B$1001,$A8)="","",INDEX(Registro!$B$1:$B$1001,$A8))) -> 46296 | C8: =IF($A8="","",IF(INDEX(Registro!$C$1:$C$1001,$A8)="","",INDEX(Registro!$C$1:$C$1001,$A8))) -> Lp | D8: =IF($A8="","",IF(INDEX(Registro!$D$1:$D$1001,$A8)="","",INDEX(Registro!$D$1:$D$1001,$A8))) -> 08:30 - 15:30 | E8: =IF($A8="","",IF(INDEX(Registro!$E$1:$E$1001,$A8)="","",INDEX(Registro!$E$1:$E$1001,$A8))) -> 25x40; 3x50 | F8: =IF($A8="","",IF(INDEX(Cálculo!$D$1:$D$1001,$A8)="","",INDEX(Cálculo!$D$1:$D$1001,$A8))) -> 28 | G8: =IF($A8="","",IF(INDEX(Cálculo!$E$1:$E$1001,$A8)="","",INDEX(Cálculo!$E$1:$E$1001,$A8))) -> 1150 | H8: =IF($A8="","",IF(INDEX(Cálculo!$F$1:$F$1001,$A8)="","",INDEX(Cálculo!$F$1:$F$1001,$A8))) | I8: =IF($A8="","",IF(INDEX(Cálculo!$G$1:$G$1001,$A8)="","",INDEX(Cálculo!$G$1:$G$1001,$A8))) -> 1150 | J8: =IF($A8="","",IF(INDEX(Registro!$G$1:$G$1001,$A8)="","",INDEX(Registro!$G$1:$G$1001,$A8))) -> 1x3300 | K8: =IF($A8="","",IF(INDEX(Cálculo!$H$1:$H$1001,$A8)="","",INDEX(Cálculo!$H$1:$H$1001,$A8))) -> 1 | L8: =IF($A8="","",IF(INDEX(Cálculo!$I$1:$I$1001,$A8)="","",INDEX(Cálculo!$I$1:$I$1001,$A8))) -> 3300 | M8: =IF($A8="","",IF(INDEX(Cálculo!$J$1:$J$1001,$A8)="","",INDEX(Cálculo!$J$1:$J$1001,$A8))) -> CONFORME | N8: =IF($A8="","",IF(INDEX(Registro!$H$1:$H$1001,$A8)="","",INDEX(Registro!$H$1:$H$1001,$A8))) -> 3300 | O8: =IF($A8="","",IF(INDEX(Registro!$I$1:$I$1001,$A8)="","",INDEX(Registro!$I$1:$I$1001,$A8))) -> Peaje 50; Veatico 50 | P8: =IF($A8="","",IF(INDEX(Cálculo!$K$1:$K$1001,$A8)="","",INDEX(Cálculo!$K$1:$K$1001,$A8))) -> 100 | Q8: =IF($A8="","",IF(INDEX(Cálculo!$M$1:$M$1001,$A8)="","",INDEX(Cálculo!$M$1:$M$1001,$A8))) -> 3200 | R8: =IF($A8="","",IF(INDEX(Registro!$J$1:$J$1001,$A8)="","",INDEX(Registro!$J$1:$J$1001,$A8))) | S8: =IF($A8="","",IF(INDEX(Cálculo!$L$1:$L$1001,$A8)="","",INDEX(Cálculo!$L$1:$L$1001,$A8))) | T8: =IF($A8="","",IF(INDEX(Cálculo!$N$1:$N$1001,$A8)="","",INDEX(Cálculo!$N$1:$N$1001,$A8))) -> 3200 | U8: =IF($A8="","",IF(INDEX(Registro!$K$1:$K$1001,$A8)="","",INDEX(Registro!$K$1:$K$1001,$A8)))
A9: =IFERROR(MOD(SMALL(Cálculo!$O$2:$O$1001,ROWS(A$8:A9)),10000),"") -> 3 | B9: =IF($A9="","",IF(INDEX(Registro!$B$1:$B$1001,$A9)="","",INDEX(Registro!$B$1:$B$1001,$A9))) -> 46297 | C9: =IF($A9="","",IF(INDEX(Registro!$C$1:$C$1001,$A9)="","",INDEX(Registro!$C$1:$C$1001,$A9))) -> Cbba | D9: =IF($A9="","",IF(INDEX(Registro!$D$1:$D$1001,$A9)="","",INDEX(Registro!$D$1:$D$1001,$A9))) -> 6:30 - 17:30 | E9: =IF($A9="","",IF(INDEX(Registro!$E$1:$E$1001,$A9)="","",INDEX(Registro!$E$1:$E$1001,$A9))) -> 15x40; 15x50; 5x60 | F9: =IF($A9="","",IF(INDEX(Cálculo!$D$1:$D$1001,$A9)="","",INDEX(Cálculo!$D$1:$D$1001,$A9))) -> 35 | G9: =IF($A9="","",IF(INDEX(Cálculo!$E$1:$E$1001,$A9)="","",INDEX(Cálculo!$E$1:$E$1001,$A9))) -> 1650 | H9: =IF($A9="","",IF(INDEX(Cálculo!$F$1:$F$1001,$A9)="","",INDEX(Cálculo!$F$1:$F$1001,$A9))) | I9: =IF($A9="","",IF(INDEX(Cálculo!$G$1:$G$1001,$A9)="","",INDEX(Cálculo!$G$1:$G$1001,$A9))) -> 1650 | J9: =IF($A9="","",IF(INDEX(Registro!$G$1:$G$1001,$A9)="","",INDEX(Registro!$G$1:$G$1001,$A9))) -> 1x4060 | K9: =IF($A9="","",IF(INDEX(Cálculo!$H$1:$H$1001,$A9)="","",INDEX(Cálculo!$H$1:$H$1001,$A9))) -> 1 | L9: =IF($A9="","",IF(INDEX(Cálculo!$I$1:$I$1001,$A9)="","",INDEX(Cálculo!$I$1:$I$1001,$A9))) -> 4060 | M9: =IF($A9="","",IF(INDEX(Cálculo!$J$1:$J$1001,$A9)="","",INDEX(Cálculo!$J$1:$J$1001,$A9))) -> CONFORME | N9: =IF($A9="","",IF(INDEX(Registro!$H$1:$H$1001,$A9)="","",INDEX(Registro!$H$1:$H$1001,$A9))) -> 4060 | O9: =IF($A9="","",IF(INDEX(Registro!$I$1:$I$1001,$A9)="","",INDEX(Registro!$I$1:$I$1001,$A9))) -> Peaje 50; Veatico 50; Gasto 100 | P9: =IF($A9="","",IF(INDEX(Cálculo!$K$1:$K$1001,$A9)="","",INDEX(Cálculo!$K$1:$K$1001,$A9))) -> 200 | Q9: =IF($A9="","",IF(INDEX(Cálculo!$M$1:$M$1001,$A9)="","",INDEX(Cálculo!$M$1:$M$1001,$A9))) -> 3860 | R9: =IF($A9="","",IF(INDEX(Registro!$J$1:$J$1001,$A9)="","",INDEX(Registro!$J$1:$J$1001,$A9))) | S9: =IF($A9="","",IF(INDEX(Cálculo!$L$1:$L$1001,$A9)="","",INDEX(Cálculo!$L$1:$L$1001,$A9))) | T9: =IF($A9="","",IF(INDEX(Cálculo!$N$1:$N$1001,$A9)="","",INDEX(Cálculo!$N$1:$N$1001,$A9))) -> 3860 | U9: =IF($A9="","",IF(INDEX(Registro!$K$1:$K$1001,$A9)="","",INDEX(Registro!$K$1:$K$1001,$A9)))
A10: =IFERROR(MOD(SMALL(Cálculo!$O$2:$O$1001,ROWS(A$8:A10)),10000),"") -> 4 | B10: =IF($A10="","",IF(INDEX(Registro!$B$1:$B$1001,$A10)="","",INDEX(Registro!$B$1:$B$1001,$A10))) -> 46298 | C10: =IF($A10="","",IF(INDEX(Registro!$C$1:$C$1001,$A10)="","",INDEX(Registro!$C$1:$C$1001,$A10))) -> Cbba | D10: =IF($A10="","",IF(INDEX(Registro!$D$1:$D$1001,$A10)="","",INDEX(Registro!$D$1:$D$1001,$A10))) -> 5:30 - 15:30 | E10: =IF($A10="","",IF(INDEX(Registro!$E$1:$E$1001,$A10)="","",INDEX(Registro!$E$1:$E$1001,$A10))) -> 43x50; 2x80; 10x70 | F10: =IF($A10="","",IF(INDEX(Cálculo!$D$1:$D$1001,$A10)="","",INDEX(Cálculo!$D$1:$D$1001,$A10))) -> 55 | G10: =IF($A10="","",IF(INDEX(Cálculo!$E$1:$E$1001,$A10)="","",INDEX(Cálculo!$E$1:$E$1001,$A10))) -> 3010 | H10: =IF($A10="","",IF(INDEX(Cálculo!$F$1:$F$1001,$A10)="","",INDEX(Cálculo!$F$1:$F$1001,$A10))) | I10: =IF($A10="","",IF(INDEX(Cálculo!$G$1:$G$1001,$A10)="","",INDEX(Cálculo!$G$1:$G$1001,$A10))) -> 3010 | J10: =IF($A10="","",IF(INDEX(Registro!$G$1:$G$1001,$A10)="","",INDEX(Registro!$G$1:$G$1001,$A10))) -> 1x3599 | K10: =IF($A10="","",IF(INDEX(Cálculo!$H$1:$H$1001,$A10)="","",INDEX(Cálculo!$H$1:$H$1001,$A10))) -> 1 | L10: =IF($A10="","",IF(INDEX(Cálculo!$I$1:$I$1001,$A10)="","",INDEX(Cálculo!$I$1:$I$1001,$A10))) -> 3599 | M10: =IF($A10="","",IF(INDEX(Cálculo!$J$1:$J$1001,$A10)="","",INDEX(Cálculo!$J$1:$J$1001,$A10))) -> CONFORME | N10: =IF($A10="","",IF(INDEX(Registro!$H$1:$H$1001,$A10)="","",INDEX(Registro!$H$1:$H$1001,$A10))) -> 3599 | O10: =IF($A10="","",IF(INDEX(Registro!$I$1:$I$1001,$A10)="","",INDEX(Registro!$I$1:$I$1001,$A10))) -> Peaje 50; Veatico 50 | P10: =IF($A10="","",IF(INDEX(Cálculo!$K$1:$K$1001,$A10)="","",INDEX(Cálculo!$K$1:$K$1001,$A10))) -> 100 | Q10: =IF($A10="","",IF(INDEX(Cálculo!$M$1:$M$1001,$A10)="","",INDEX(Cálculo!$M$1:$M$1001,$A10))) -> 3499 | R10: =IF($A10="","",IF(INDEX(Registro!$J$1:$J$1001,$A10)="","",INDEX(Registro!$J$1:$J$1001,$A10))) -> Diesel 8400 | S10: =IF($A10="","",IF(INDEX(Cálculo!$L$1:$L$1001,$A10)="","",INDEX(Cálculo!$L$1:$L$1001,$A10))) -> 8400 | T10: =IF($A10="","",IF(INDEX(Cálculo!$N$1:$N$1001,$A10)="","",INDEX(Cálculo!$N$1:$N$1001,$A10))) -> -4901 | U10: =IF($A10="","",IF(INDEX(Registro!$K$1:$K$1001,$A10)="","",INDEX(Registro!$K$1:$K$1001,$A10)))
A11: =IFERROR(MOD(SMALL(Cálculo!$O$2:$O$1001,ROWS(A$8:A11)),10000),"") -> 5 | B11: =IF($A11="","",IF(INDEX(Registro!$B$1:$B$1001,$A11)="","",INDEX(Registro!$B$1:$B$1001,$A11))) -> 46299 | C11: =IF($A11="","",IF(INDEX(Registro!$C$1:$C$1001,$A11)="","",INDEX(Registro!$C$1:$C$1001,$A11))) -> Lp | D11: =IF($A11="","",IF(INDEX(Registro!$D$1:$D$1001,$A11)="","",INDEX(Registro!$D$1:$D$1001,$A11))) -> 4:00 | E11: =IF($A11="","",IF(INDEX(Registro!$E$1:$E$1001,$A11)="","",INDEX(Registro!$E$1:$E$1001,$A11))) -> 43x40; 4x50; 7x60 | F11: =IF($A11="","",IF(INDEX(Cálculo!$D$1:$D$1001,$A11)="","",INDEX(Cálculo!$D$1:$D$1001,$A11))) -> 54 | G11: =IF($A11="","",IF(INDEX(Cálculo!$E$1:$E$1001,$A11)="","",INDEX(Cálculo!$E$1:$E$1001,$A11))) -> 2340 | H11: =IF($A11="","",IF(INDEX(Cálculo!$F$1:$F$1001,$A11)="","",INDEX(Cálculo!$F$1:$F$1001,$A11))) | I11: =IF($A11="","",IF(INDEX(Cálculo!$G$1:$G$1001,$A11)="","",INDEX(Cálculo!$G$1:$G$1001,$A11))) -> 2340 | J11: =IF($A11="","",IF(INDEX(Registro!$G$1:$G$1001,$A11)="","",INDEX(Registro!$G$1:$G$1001,$A11))) -> 1x2080 | K11: =IF($A11="","",IF(INDEX(Cálculo!$H$1:$H$1001,$A11)="","",INDEX(Cálculo!$H$1:$H$1001,$A11))) -> 1 | L11: =IF($A11="","",IF(INDEX(Cálculo!$I$1:$I$1001,$A11)="","",INDEX(Cálculo!$I$1:$I$1001,$A11))) -> 2080 | M11: =IF($A11="","",IF(INDEX(Cálculo!$J$1:$J$1001,$A11)="","",INDEX(Cálculo!$J$1:$J$1001,$A11))) -> CONFORME | N11: =IF($A11="","",IF(INDEX(Registro!$H$1:$H$1001,$A11)="","",INDEX(Registro!$H$1:$H$1001,$A11))) -> 2080 | O11: =IF($A11="","",IF(INDEX(Registro!$I$1:$I$1001,$A11)="","",INDEX(Registro!$I$1:$I$1001,$A11))) -> Peaje 50; Veatico 50; Engrase 40 | P11: =IF($A11="","",IF(INDEX(Cálculo!$K$1:$K$1001,$A11)="","",INDEX(Cálculo!$K$1:$K$1001,$A11))) -> 140 | Q11: =IF($A11="","",IF(INDEX(Cálculo!$M$1:$M$1001,$A11)="","",INDEX(Cálculo!$M$1:$M$1001,$A11))) -> 1940 | R11: =IF($A11="","",IF(INDEX(Registro!$J$1:$J$1001,$A11)="","",INDEX(Registro!$J$1:$J$1001,$A11))) | S11: =IF($A11="","",IF(INDEX(Cálculo!$L$1:$L$1001,$A11)="","",INDEX(Cálculo!$L$1:$L$1001,$A11))) | T11: =IF($A11="","",IF(INDEX(Cálculo!$N$1:$N$1001,$A11)="","",INDEX(Cálculo!$N$1:$N$1001,$A11))) -> 1940 | U11: =IF($A11="","",IF(INDEX(Registro!$K$1:$K$1001,$A11)="","",INDEX(Registro!$K$1:$K$1001,$A11)))
A12: =IFERROR(MOD(SMALL(Cálculo!$O$2:$O$1001,ROWS(A$8:A12)),10000),"") -> 6 | B12: =IF($A12="","",IF(INDEX(Registro!$B$1:$B$1001,$A12)="","",INDEX(Registro!$B$1:$B$1001,$A12))) -> 46300 | C12: =IF($A12="","",IF(INDEX(Registro!$C$1:$C$1001,$A12)="","",INDEX(Registro!$C$1:$C$1001,$A12))) -> Cbba | D12: =IF($A12="","",IF(INDEX(Registro!$D$1:$D$1001,$A12)="","",INDEX(Registro!$D$1:$D$1001,$A12))) -> 9:30-17:00 | E12: =IF($A12="","",IF(INDEX(Registro!$E$1:$E$1001,$A12)="","",INDEX(Registro!$E$1:$E$1001,$A12))) -> 37x40; 2x50; 2x70; 8x60 | F12: =IF($A12="","",IF(INDEX(Cálculo!$D$1:$D$1001,$A12)="","",INDEX(Cálculo!$D$1:$D$1001,$A12))) -> 49 | G12: =IF($A12="","",IF(INDEX(Cálculo!$E$1:$E$1001,$A12)="","",INDEX(Cálculo!$E$1:$E$1001,$A12))) -> 2200 | H12: =IF($A12="","",IF(INDEX(Cálculo!$F$1:$F$1001,$A12)="","",INDEX(Cálculo!$F$1:$F$1001,$A12))) | I12: =IF($A12="","",IF(INDEX(Cálculo!$G$1:$G$1001,$A12)="","",INDEX(Cálculo!$G$1:$G$1001,$A12))) -> 2200 | J12: =IF($A12="","",IF(INDEX(Registro!$G$1:$G$1001,$A12)="","",INDEX(Registro!$G$1:$G$1001,$A12))) -> 1x3300 | K12: =IF($A12="","",IF(INDEX(Cálculo!$H$1:$H$1001,$A12)="","",INDEX(Cálculo!$H$1:$H$1001,$A12))) -> 1 | L12: =IF($A12="","",IF(INDEX(Cálculo!$I$1:$I$1001,$A12)="","",INDEX(Cálculo!$I$1:$I$1001,$A12))) -> 3300 | M12: =IF($A12="","",IF(INDEX(Cálculo!$J$1:$J$1001,$A12)="","",INDEX(Cálculo!$J$1:$J$1001,$A12))) -> CONFORME | N12: =IF($A12="","",IF(INDEX(Registro!$H$1:$H$1001,$A12)="","",INDEX(Registro!$H$1:$H$1001,$A12))) -> 3300 | O12: =IF($A12="","",IF(INDEX(Registro!$I$1:$I$1001,$A12)="","",INDEX(Registro!$I$1:$I$1001,$A12))) -> Peaje 50; Diesel 400; Veatico 50 | P12: =IF($A12="","",IF(INDEX(Cálculo!$K$1:$K$1001,$A12)="","",INDEX(Cálculo!$K$1:$K$1001,$A12))) -> 500 | Q12: =IF($A12="","",IF(INDEX(Cálculo!$M$1:$M$1001,$A12)="","",INDEX(Cálculo!$M$1:$M$1001,$A12))) -> 2800 | R12: =IF($A12="","",IF(INDEX(Registro!$J$1:$J$1001,$A12)="","",INDEX(Registro!$J$1:$J$1001,$A12))) -> Diesel 7500 | S12: =IF($A12="","",IF(INDEX(Cálculo!$L$1:$L$1001,$A12)="","",INDEX(Cálculo!$L$1:$L$1001,$A12))) -> 7500 | T12: =IF($A12="","",IF(INDEX(Cálculo!$N$1:$N$1001,$A12)="","",INDEX(Cálculo!$N$1:$N$1001,$A12))) -> -4700 | U12: =IF($A12="","",IF(INDEX(Registro!$K$1:$K$1001,$A12)="","",INDEX(Registro!$K$1:$K$1001,$A12)))
A13: =IFERROR(MOD(SMALL(Cálculo!$O$2:$O$1001,ROWS(A$8:A13)),10000),"") -> 7 | B13: =IF($A13="","",IF(INDEX(Registro!$B$1:$B$1001,$A13)="","",INDEX(Registro!$B$1:$B$1001,$A13))) -> 46301 | C13: =IF($A13="","",IF(INDEX(Registro!$C$1:$C$1001,$A13)="","",INDEX(Registro!$C$1:$C$1001,$A13))) -> Lp | D13: =IF($A13="","",IF(INDEX(Registro!$D$1:$D$1001,$A13)="","",INDEX(Registro!$D$1:$D$1001,$A13))) -> 15:30-4:00 | E13: =IF($A13="","",IF(INDEX(Registro!$E$1:$E$1001,$A13)="","",INDEX(Registro!$E$1:$E$1001,$A13))) -> 9x60; 2x70; 45x50 | F13: =IF($A13="","",IF(INDEX(Cálculo!$D$1:$D$1001,$A13)="","",INDEX(Cálculo!$D$1:$D$1001,$A13))) -> 56 | G13: =IF($A13="","",IF(INDEX(Cálculo!$E$1:$E$1001,$A13)="","",INDEX(Cálculo!$E$1:$E$1001,$A13))) -> 2930 | H13: =IF($A13="","",IF(INDEX(Cálculo!$F$1:$F$1001,$A13)="","",INDEX(Cálculo!$F$1:$F$1001,$A13))) | I13: =IF($A13="","",IF(INDEX(Cálculo!$G$1:$G$1001,$A13)="","",INDEX(Cálculo!$G$1:$G$1001,$A13))) -> 2930 | J13: =IF($A13="","",IF(INDEX(Registro!$G$1:$G$1001,$A13)="","",INDEX(Registro!$G$1:$G$1001,$A13))) -> 1x2350 | K13: =IF($A13="","",IF(INDEX(Cálculo!$H$1:$H$1001,$A13)="","",INDEX(Cálculo!$H$1:$H$1001,$A13))) -> 1 | L13: =IF($A13="","",IF(INDEX(Cálculo!$I$1:$I$1001,$A13)="","",INDEX(Cálculo!$I$1:$I$1001,$A13))) -> 2350 | M13: =IF($A13="","",IF(INDEX(Cálculo!$J$1:$J$1001,$A13)="","",INDEX(Cálculo!$J$1:$J$1001,$A13))) -> CONFORME | N13: =IF($A13="","",IF(INDEX(Registro!$H$1:$H$1001,$A13)="","",INDEX(Registro!$H$1:$H$1001,$A13))) -> 2350 | O13: =IF($A13="","",IF(INDEX(Registro!$I$1:$I$1001,$A13)="","",INDEX(Registro!$I$1:$I$1001,$A13))) -> Peaje 50; Veatico 50 | P13: =IF($A13="","",IF(INDEX(Cálculo!$K$1:$K$1001,$A13)="","",INDEX(Cálculo!$K$1:$K$1001,$A13))) -> 100 | Q13: =IF($A13="","",IF(INDEX(Cálculo!$M$1:$M$1001,$A13)="","",INDEX(Cálculo!$M$1:$M$1001,$A13))) -> 2250 | R13: =IF($A13="","",IF(INDEX(Registro!$J$1:$J$1001,$A13)="","",INDEX(Registro!$J$1:$J$1001,$A13))) | S13: =IF($A13="","",IF(INDEX(Cálculo!$L$1:$L$1001,$A13)="","",INDEX(Cálculo!$L$1:$L$1001,$A13))) | T13: =IF($A13="","",IF(INDEX(Cálculo!$N$1:$N$1001,$A13)="","",INDEX(Cálculo!$N$1:$N$1001,$A13))) -> 2250 | U13: =IF($A13="","",IF(INDEX(Registro!$K$1:$K$1001,$A13)="","",INDEX(Registro!$K$1:$K$1001,$A13)))
A14: =IFERROR(MOD(SMALL(Cálculo!$O$2:$O$1001,ROWS(A$8:A14)),10000),"") -> 8 | B14: =IF($A14="","",IF(INDEX(Registro!$B$1:$B$1001,$A14)="","",INDEX(Registro!$B$1:$B$1001,$A14))) -> 46302 | C14: =IF($A14="","",IF(INDEX(Registro!$C$1:$C$1001,$A14)="","",INDEX(Registro!$C$1:$C$1001,$A14))) -> Lp | D14: =IF($A14="","",IF(INDEX(Registro!$D$1:$D$1001,$A14)="","",INDEX(Registro!$D$1:$D$1001,$A14))) -> 6:30-14:30 | E14: =IF($A14="","",IF(INDEX(Registro!$E$1:$E$1001,$A14)="","",INDEX(Registro!$E$1:$E$1001,$A14))) -> 24x40; 4x60; 5x50 | F14: =IF($A14="","",IF(INDEX(Cálculo!$D$1:$D$1001,$A14)="","",INDEX(Cálculo!$D$1:$D$1001,$A14))) -> 33 | G14: =IF($A14="","",IF(INDEX(Cálculo!$E$1:$E$1001,$A14)="","",INDEX(Cálculo!$E$1:$E$1001,$A14))) -> 1450 | H14: =IF($A14="","",IF(INDEX(Cálculo!$F$1:$F$1001,$A14)="","",INDEX(Cálculo!$F$1:$F$1001,$A14))) | I14: =IF($A14="","",IF(INDEX(Cálculo!$G$1:$G$1001,$A14)="","",INDEX(Cálculo!$G$1:$G$1001,$A14))) -> 1450 | J14: =IF($A14="","",IF(INDEX(Registro!$G$1:$G$1001,$A14)="","",INDEX(Registro!$G$1:$G$1001,$A14))) -> 1x2455 | K14: =IF($A14="","",IF(INDEX(Cálculo!$H$1:$H$1001,$A14)="","",INDEX(Cálculo!$H$1:$H$1001,$A14))) -> 1 | L14: =IF($A14="","",IF(INDEX(Cálculo!$I$1:$I$1001,$A14)="","",INDEX(Cálculo!$I$1:$I$1001,$A14))) -> 2455 | M14: =IF($A14="","",IF(INDEX(Cálculo!$J$1:$J$1001,$A14)="","",INDEX(Cálculo!$J$1:$J$1001,$A14))) -> CONFORME | N14: =IF($A14="","",IF(INDEX(Registro!$H$1:$H$1001,$A14)="","",INDEX(Registro!$H$1:$H$1001,$A14))) -> 2455 | O14: =IF($A14="","",IF(INDEX(Registro!$I$1:$I$1001,$A14)="","",INDEX(Registro!$I$1:$I$1001,$A14))) -> Peaje 50; Veatico 50 | P14: =IF($A14="","",IF(INDEX(Cálculo!$K$1:$K$1001,$A14)="","",INDEX(Cálculo!$K$1:$K$1001,$A14))) -> 100 | Q14: =IF($A14="","",IF(INDEX(Cálculo!$M$1:$M$1001,$A14)="","",INDEX(Cálculo!$M$1:$M$1001,$A14))) -> 2355 | R14: =IF($A14="","",IF(INDEX(Registro!$J$1:$J$1001,$A14)="","",INDEX(Registro!$J$1:$J$1001,$A14))) | S14: =IF($A14="","",IF(INDEX(Cálculo!$L$1:$L$1001,$A14)="","",INDEX(Cálculo!$L$1:$L$1001,$A14))) | T14: =IF($A14="","",IF(INDEX(Cálculo!$N$1:$N$1001,$A14)="","",INDEX(Cálculo!$N$1:$N$1001,$A14))) -> 2355 | U14: =IF($A14="","",IF(INDEX(Registro!$K$1:$K$1001,$A14)="","",INDEX(Registro!$K$1:$K$1001,$A14)))
A15: =IFERROR(MOD(SMALL(Cálculo!$O$2:$O$1001,ROWS(A$8:A15)),10000),"") -> 9 | B15: =IF($A15="","",IF(INDEX(Registro!$B$1:$B$1001,$A15)="","",INDEX(Registro!$B$1:$B$1001,$A15))) -> 46303 | C15: =IF($A15="","",IF(INDEX(Registro!$C$1:$C$1001,$A15)="","",INDEX(Registro!$C$1:$C$1001,$A15))) -> Lp | D15: =IF($A15="","",IF(INDEX(Registro!$D$1:$D$1001,$A15)="","",INDEX(Registro!$D$1:$D$1001,$A15))) -> 19:30-8:00 | E15: =IF($A15="","",IF(INDEX(Registro!$E$1:$E$1001,$A15)="","",INDEX(Registro!$E$1:$E$1001,$A15))) -> 35x40; 11x60 | F15: =IF($A15="","",IF(INDEX(Cálculo!$D$1:$D$1001,$A15)="","",INDEX(Cálculo!$D$1:$D$1001,$A15))) -> 46 | G15: =IF($A15="","",IF(INDEX(Cálculo!$E$1:$E$1001,$A15)="","",INDEX(Cálculo!$E$1:$E$1001,$A15))) -> 2060 | H15: =IF($A15="","",IF(INDEX(Cálculo!$F$1:$F$1001,$A15)="","",INDEX(Cálculo!$F$1:$F$1001,$A15))) | I15: =IF($A15="","",IF(INDEX(Cálculo!$G$1:$G$1001,$A15)="","",INDEX(Cálculo!$G$1:$G$1001,$A15))) -> 2060 | J15: =IF($A15="","",IF(INDEX(Registro!$G$1:$G$1001,$A15)="","",INDEX(Registro!$G$1:$G$1001,$A15))) -> 1x2365 | K15: =IF($A15="","",IF(INDEX(Cálculo!$H$1:$H$1001,$A15)="","",INDEX(Cálculo!$H$1:$H$1001,$A15))) -> 1 | L15: =IF($A15="","",IF(INDEX(Cálculo!$I$1:$I$1001,$A15)="","",INDEX(Cálculo!$I$1:$I$1001,$A15))) -> 2365 | M15: =IF($A15="","",IF(INDEX(Cálculo!$J$1:$J$1001,$A15)="","",INDEX(Cálculo!$J$1:$J$1001,$A15))) -> CONFORME | N15: =IF($A15="","",IF(INDEX(Registro!$H$1:$H$1001,$A15)="","",INDEX(Registro!$H$1:$H$1001,$A15))) -> 2365 | O15: =IF($A15="","",IF(INDEX(Registro!$I$1:$I$1001,$A15)="","",INDEX(Registro!$I$1:$I$1001,$A15))) -> Peaje 50 | P15: =IF($A15="","",IF(INDEX(Cálculo!$K$1:$K$1001,$A15)="","",INDEX(Cálculo!$K$1:$K$1001,$A15))) -> 50 | Q15: =IF($A15="","",IF(INDEX(Cálculo!$M$1:$M$1001,$A15)="","",INDEX(Cálculo!$M$1:$M$1001,$A15))) -> 2315 | R15: =IF($A15="","",IF(INDEX(Registro!$J$1:$J$1001,$A15)="","",INDEX(Registro!$J$1:$J$1001,$A15))) | S15: =IF($A15="","",IF(INDEX(Cálculo!$L$1:$L$1001,$A15)="","",INDEX(Cálculo!$L$1:$L$1001,$A15))) | T15: =IF($A15="","",IF(INDEX(Cálculo!$N$1:$N$1001,$A15)="","",INDEX(Cálculo!$N$1:$N$1001,$A15))) -> 2315 | U15: =IF($A15="","",IF(INDEX(Registro!$K$1:$K$1001,$A15)="","",INDEX(Registro!$K$1:$K$1001,$A15)))
A16: =IFERROR(MOD(SMALL(Cálculo!$O$2:$O$1001,ROWS(A$8:A16)),10000),"") -> 10 | B16: =IF($A16="","",IF(INDEX(Registro!$B$1:$B$1001,$A16)="","",INDEX(Registro!$B$1:$B$1001,$A16))) -> 46304 | C16: =IF($A16="","",IF(INDEX(Registro!$C$1:$C$1001,$A16)="","",INDEX(Registro!$C$1:$C$1001,$A16))) -> Lp | D16: =IF($A16="","",IF(INDEX(Registro!$D$1:$D$1001,$A16)="","",INDEX(Registro!$D$1:$D$1001,$A16))) -> 4:00-11:00 | E16: =IF($A16="","",IF(INDEX(Registro!$E$1:$E$1001,$A16)="","",INDEX(Registro!$E$1:$E$1001,$A16))) -> 14x40; 31x50; 1x60; 4x70; 7x60 | F16: =IF($A16="","",IF(INDEX(Cálculo!$D$1:$D$1001,$A16)="","",INDEX(Cálculo!$D$1:$D$1001,$A16))) -> 57 | G16: =IF($A16="","",IF(INDEX(Cálculo!$E$1:$E$1001,$A16)="","",INDEX(Cálculo!$E$1:$E$1001,$A16))) -> 2870 | H16: =IF($A16="","",IF(INDEX(Cálculo!$F$1:$F$1001,$A16)="","",INDEX(Cálculo!$F$1:$F$1001,$A16))) | I16: =IF($A16="","",IF(INDEX(Cálculo!$G$1:$G$1001,$A16)="","",INDEX(Cálculo!$G$1:$G$1001,$A16))) -> 2870 | J16: =IF($A16="","",IF(INDEX(Registro!$G$1:$G$1001,$A16)="","",INDEX(Registro!$G$1:$G$1001,$A16))) -> 1x2395 | K16: =IF($A16="","",IF(INDEX(Cálculo!$H$1:$H$1001,$A16)="","",INDEX(Cálculo!$H$1:$H$1001,$A16))) -> 1 | L16: =IF($A16="","",IF(INDEX(Cálculo!$I$1:$I$1001,$A16)="","",INDEX(Cálculo!$I$1:$I$1001,$A16))) -> 2395 | M16: =IF($A16="","",IF(INDEX(Cálculo!$J$1:$J$1001,$A16)="","",INDEX(Cálculo!$J$1:$J$1001,$A16))) -> CONFORME | N16: =IF($A16="","",IF(INDEX(Registro!$H$1:$H$1001,$A16)="","",INDEX(Registro!$H$1:$H$1001,$A16))) -> 2395 | O16: =IF($A16="","",IF(INDEX(Registro!$I$1:$I$1001,$A16)="","",INDEX(Registro!$I$1:$I$1001,$A16))) | P16: =IF($A16="","",IF(INDEX(Cálculo!$K$1:$K$1001,$A16)="","",INDEX(Cálculo!$K$1:$K$1001,$A16))) | Q16: =IF($A16="","",IF(INDEX(Cálculo!$M$1:$M$1001,$A16)="","",INDEX(Cálculo!$M$1:$M$1001,$A16))) -> 2395 | R16: =IF($A16="","",IF(INDEX(Registro!$J$1:$J$1001,$A16)="","",INDEX(Registro!$J$1:$J$1001,$A16))) | S16: =IF($A16="","",IF(INDEX(Cálculo!$L$1:$L$1001,$A16)="","",INDEX(Cálculo!$L$1:$L$1001,$A16))) | T16: =IF($A16="","",IF(INDEX(Cálculo!$N$1:$N$1001,$A16)="","",INDEX(Cálculo!$N$1:$N$1001,$A16))) -> 2395 | U16: =IF($A16="","",IF(INDEX(Registro!$K$1:$K$1001,$A16)="","",INDEX(Registro!$K$1:$K$1001,$A16)))
A17: =IFERROR(MOD(SMALL(Cálculo!$O$2:$O$1001,ROWS(A$8:A17)),10000),"") -> 11 | B17: =IF($A17="","",IF(INDEX(Registro!$B$1:$B$1001,$A17)="","",INDEX(Registro!$B$1:$B$1001,$A17))) -> 46305 | C17: =IF($A17="","",IF(INDEX(Registro!$C$1:$C$1001,$A17)="","",INDEX(Registro!$C$1:$C$1001,$A17))) -> Cbba | D17: =IF($A17="","",IF(INDEX(Registro!$D$1:$D$1001,$A17)="","",INDEX(Registro!$D$1:$D$1001,$A17))) -> 7:00-14:30 | E17: =IF($A17="","",IF(INDEX(Registro!$E$1:$E$1001,$A17)="","",INDEX(Registro!$E$1:$E$1001,$A17))) -> 30x40; 12x35; 1x70 | F17: =IF($A17="","",IF(INDEX(Cálculo!$D$1:$D$1001,$A17)="","",INDEX(Cálculo!$D$1:$D$1001,$A17))) -> 43 | G17: =IF($A17="","",IF(INDEX(Cálculo!$E$1:$E$1001,$A17)="","",INDEX(Cálculo!$E$1:$E$1001,$A17))) -> 1690 | H17: =IF($A17="","",IF(INDEX(Cálculo!$F$1:$F$1001,$A17)="","",INDEX(Cálculo!$F$1:$F$1001,$A17))) | I17: =IF($A17="","",IF(INDEX(Cálculo!$G$1:$G$1001,$A17)="","",INDEX(Cálculo!$G$1:$G$1001,$A17))) -> 1690 | J17: =IF($A17="","",IF(INDEX(Registro!$G$1:$G$1001,$A17)="","",INDEX(Registro!$G$1:$G$1001,$A17))) -> 1x3670 | K17: =IF($A17="","",IF(INDEX(Cálculo!$H$1:$H$1001,$A17)="","",INDEX(Cálculo!$H$1:$H$1001,$A17))) -> 1 | L17: =IF($A17="","",IF(INDEX(Cálculo!$I$1:$I$1001,$A17)="","",INDEX(Cálculo!$I$1:$I$1001,$A17))) -> 3670 | M17: =IF($A17="","",IF(INDEX(Cálculo!$J$1:$J$1001,$A17)="","",INDEX(Cálculo!$J$1:$J$1001,$A17))) -> CONFORME | N17: =IF($A17="","",IF(INDEX(Registro!$H$1:$H$1001,$A17)="","",INDEX(Registro!$H$1:$H$1001,$A17))) -> 3670 | O17: =IF($A17="","",IF(INDEX(Registro!$I$1:$I$1001,$A17)="","",INDEX(Registro!$I$1:$I$1001,$A17))) -> Peaje 50; Veatico 50 | P17: =IF($A17="","",IF(INDEX(Cálculo!$K$1:$K$1001,$A17)="","",INDEX(Cálculo!$K$1:$K$1001,$A17))) -> 100 | Q17: =IF($A17="","",IF(INDEX(Cálculo!$M$1:$M$1001,$A17)="","",INDEX(Cálculo!$M$1:$M$1001,$A17))) -> 3570 | R17: =IF($A17="","",IF(INDEX(Registro!$J$1:$J$1001,$A17)="","",INDEX(Registro!$J$1:$J$1001,$A17))) -> Diesel 8380 | S17: =IF($A17="","",IF(INDEX(Cálculo!$L$1:$L$1001,$A17)="","",INDEX(Cálculo!$L$1:$L$1001,$A17))) -> 8380 | T17: =IF($A17="","",IF(INDEX(Cálculo!$N$1:$N$1001,$A17)="","",INDEX(Cálculo!$N$1:$N$1001,$A17))) -> -4810 | U17: =IF($A17="","",IF(INDEX(Registro!$K$1:$K$1001,$A17)="","",INDEX(Registro!$K$1:$K$1001,$A17)))
A18: =IFERROR(MOD(SMALL(Cálculo!$O$2:$O$1001,ROWS(A$8:A18)),10000),"") -> 12 | B18: =IF($A18="","",IF(INDEX(Registro!$B$1:$B$1001,$A18)="","",INDEX(Registro!$B$1:$B$1001,$A18))) -> 46305 | C18: =IF($A18="","",IF(INDEX(Registro!$C$1:$C$1001,$A18)="","",INDEX(Registro!$C$1:$C$1001,$A18))) -> Lp | D18: =IF($A18="","",IF(INDEX(Registro!$D$1:$D$1001,$A18)="","",INDEX(Registro!$D$1:$D$1001,$A18))) -> 17:30-4:30 | E18: =IF($A18="","",IF(INDEX(Registro!$E$1:$E$1001,$A18)="","",INDEX(Registro!$E$1:$E$1001,$A18))) -> 19x40; 10x60; 5x50; 11x35 | F18: =IF($A18="","",IF(INDEX(Cálculo!$D$1:$D$1001,$A18)="","",INDEX(Cálculo!$D$1:$D$1001,$A18))) -> 45 | G18: =IF($A18="","",IF(INDEX(Cálculo!$E$1:$E$1001,$A18)="","",INDEX(Cálculo!$E$1:$E$1001,$A18))) -> 1995 | H18: =IF($A18="","",IF(INDEX(Cálculo!$F$1:$F$1001,$A18)="","",INDEX(Cálculo!$F$1:$F$1001,$A18))) | I18: =IF($A18="","",IF(INDEX(Cálculo!$G$1:$G$1001,$A18)="","",INDEX(Cálculo!$G$1:$G$1001,$A18))) -> 1995 | J18: =IF($A18="","",IF(INDEX(Registro!$G$1:$G$1001,$A18)="","",INDEX(Registro!$G$1:$G$1001,$A18))) -> 1x2100 | K18: =IF($A18="","",IF(INDEX(Cálculo!$H$1:$H$1001,$A18)="","",INDEX(Cálculo!$H$1:$H$1001,$A18))) -> 1 | L18: =IF($A18="","",IF(INDEX(Cálculo!$I$1:$I$1001,$A18)="","",INDEX(Cálculo!$I$1:$I$1001,$A18))) -> 2100 | M18: =IF($A18="","",IF(INDEX(Cálculo!$J$1:$J$1001,$A18)="","",INDEX(Cálculo!$J$1:$J$1001,$A18))) -> CONFORME | N18: =IF($A18="","",IF(INDEX(Registro!$H$1:$H$1001,$A18)="","",INDEX(Registro!$H$1:$H$1001,$A18))) -> 2100 | O18: =IF($A18="","",IF(INDEX(Registro!$I$1:$I$1001,$A18)="","",INDEX(Registro!$I$1:$I$1001,$A18))) | P18: =IF($A18="","",IF(INDEX(Cálculo!$K$1:$K$1001,$A18)="","",INDEX(Cálculo!$K$1:$K$1001,$A18))) | Q18: =IF($A18="","",IF(INDEX(Cálculo!$M$1:$M$1001,$A18)="","",INDEX(Cálculo!$M$1:$M$1001,$A18))) -> 2100 | R18: =IF($A18="","",IF(INDEX(Registro!$J$1:$J$1001,$A18)="","",INDEX(Registro!$J$1:$J$1001,$A18))) | S18: =IF($A18="","",IF(INDEX(Cálculo!$L$1:$L$1001,$A18)="","",INDEX(Cálculo!$L$1:$L$1001,$A18))) | T18: =IF($A18="","",IF(INDEX(Cálculo!$N$1:$N$1001,$A18)="","",INDEX(Cálculo!$N$1:$N$1001,$A18))) -> 2100 | U18: =IF($A18="","",IF(INDEX(Registro!$K$1:$K$1001,$A18)="","",INDEX(Registro!$K$1:$K$1001,$A18)))
A19: =IFERROR(MOD(SMALL(Cálculo!$O$2:$O$1001,ROWS(A$8:A19)),10000),"") -> 13 | B19: =IF($A19="","",IF(INDEX(Registro!$B$1:$B$1001,$A19)="","",INDEX(Registro!$B$1:$B$1001,$A19))) -> 46306 | C19: =IF($A19="","",IF(INDEX(Registro!$C$1:$C$1001,$A19)="","",INDEX(Registro!$C$1:$C$1001,$A19))) -> Cbba | D19: =IF($A19="","",IF(INDEX(Registro!$D$1:$D$1001,$A19)="","",INDEX(Registro!$D$1:$D$1001,$A19))) -> 12:00-19:00 | E19: =IF($A19="","",IF(INDEX(Registro!$E$1:$E$1001,$A19)="","",INDEX(Registro!$E$1:$E$1001,$A19))) -> 46x50; 4x70 | F19: =IF($A19="","",IF(INDEX(Cálculo!$D$1:$D$1001,$A19)="","",INDEX(Cálculo!$D$1:$D$1001,$A19))) -> 50 | G19: =IF($A19="","",IF(INDEX(Cálculo!$E$1:$E$1001,$A19)="","",INDEX(Cálculo!$E$1:$E$1001,$A19))) -> 2580 | H19: =IF($A19="","",IF(INDEX(Cálculo!$F$1:$F$1001,$A19)="","",INDEX(Cálculo!$F$1:$F$1001,$A19))) | I19: =IF($A19="","",IF(INDEX(Cálculo!$G$1:$G$1001,$A19)="","",INDEX(Cálculo!$G$1:$G$1001,$A19))) -> 2580 | J19: =IF($A19="","",IF(INDEX(Registro!$G$1:$G$1001,$A19)="","",INDEX(Registro!$G$1:$G$1001,$A19))) -> 1x5280 | K19: =IF($A19="","",IF(INDEX(Cálculo!$H$1:$H$1001,$A19)="","",INDEX(Cálculo!$H$1:$H$1001,$A19))) -> 1 | L19: =IF($A19="","",IF(INDEX(Cálculo!$I$1:$I$1001,$A19)="","",INDEX(Cálculo!$I$1:$I$1001,$A19))) -> 5280 | M19: =IF($A19="","",IF(INDEX(Cálculo!$J$1:$J$1001,$A19)="","",INDEX(Cálculo!$J$1:$J$1001,$A19))) -> CONFORME | N19: =IF($A19="","",IF(INDEX(Registro!$H$1:$H$1001,$A19)="","",INDEX(Registro!$H$1:$H$1001,$A19))) -> 5280 | O19: =IF($A19="","",IF(INDEX(Registro!$I$1:$I$1001,$A19)="","",INDEX(Registro!$I$1:$I$1001,$A19))) -> Peaje 50; Veatico 50; Engrase 30 | P19: =IF($A19="","",IF(INDEX(Cálculo!$K$1:$K$1001,$A19)="","",INDEX(Cálculo!$K$1:$K$1001,$A19))) -> 130 | Q19: =IF($A19="","",IF(INDEX(Cálculo!$M$1:$M$1001,$A19)="","",INDEX(Cálculo!$M$1:$M$1001,$A19))) -> 5150 | R19: =IF($A19="","",IF(INDEX(Registro!$J$1:$J$1001,$A19)="","",INDEX(Registro!$J$1:$J$1001,$A19))) | S19: =IF($A19="","",IF(INDEX(Cálculo!$L$1:$L$1001,$A19)="","",INDEX(Cálculo!$L$1:$L$1001,$A19))) | T19: =IF($A19="","",IF(INDEX(Cálculo!$N$1:$N$1001,$A19)="","",INDEX(Cálculo!$N$1:$N$1001,$A19))) -> 5150 | U19: =IF($A19="","",IF(INDEX(Registro!$K$1:$K$1001,$A19)="","",INDEX(Registro!$K$1:$K$1001,$A19)))
... A69: =IFERROR(MOD(SMALL(Cálculo!$O$2:$O$1001,ROWS(A$8:A69)),10000),"") | B69: =IF($A69="","",IF(INDEX(Registro!$B$1:$B$1001,$A69)="","",INDEX(Registro!$B$1:$B$1001,$A69))) | C69: =IF($A69="","",IF(INDEX(Registro!$C$1:$C$1001,$A69)="","",INDEX(Registro!$C$1:$C$1001,$A69))) | D69: =IF($A69="","",IF(INDEX(Registro!$D$1:$D$1001,$A69)="","",INDEX(Registro!$D$1:$D$1001,$A69))) | E69: =IF($A69="","",IF(INDEX(Registro!$E$1:$E$1001,$A69)="","",INDEX(Registro!$E$1:$E$1001,$A69))) | F69: =IF($A69="","",IF(INDEX(Cálculo!$D$1:$D$1001,$A69)="","",INDEX(Cálculo!$D$1:$D$1001,$A69))) | G69: =IF($A69="","",IF(INDEX(Cálculo!$E$1:$E$1001,$A69)="","",INDEX(Cálculo!$E$1:$E$1001,$A69))) | H69: =IF($A69="","",IF(INDEX(Cálculo!$F$1:$F$1001,$A69)="","",INDEX(Cálculo!$F$1:$F$1001,$A69))) | I69: =IF($A69="","",IF(INDEX(Cálculo!$G$1:$G$1001,$A69)="","",INDEX(Cálculo!$G$1:$G$1001,$A69))) | J69: =IF($A69="","",IF(INDEX(Registro!$G$1:$G$1001,$A69)="","",INDEX(Registro!$G$1:$G$1001,$A69))) | K69: =IF($A69="","",IF(INDEX(Cálculo!$H$1:$H$1001,$A69)="","",INDEX(Cálculo!$H$1:$H$1001,$A69))) | L69: =IF($A69="","",IF(INDEX(Cálculo!$I$1:$I$1001,$A69)="","",INDEX(Cálculo!$I$1:$I$1001,$A69))) | M69: =IF($A69="","",IF(INDEX(Cálculo!$J$1:$J$1001,$A69)="","",INDEX(Cálculo!$J$1:$J$1001,$A69))) | N69: =IF($A69="","",IF(INDEX(Registro!$H$1:$H$1001,$A69)="","",INDEX(Registro!$H$1:$H$1001,$A69))) | O69: =IF($A69="","",IF(INDEX(Registro!$I$1:$I$1001,$A69)="","",INDEX(Registro!$I$1:$I$1001,$A69))) | P69: =IF($A69="","",IF(INDEX(Cálculo!$K$1:$K$1001,$A69)="","",INDEX(Cálculo!$K$1:$K$1001,$A69))) | Q69: =IF($A69="","",IF(INDEX(Cálculo!$M$1:$M$1001,$A69)="","",INDEX(Cálculo!$M$1:$M$1001,$A69))) | R69: =IF($A69="","",IF(INDEX(Registro!$J$1:$J$1001,$A69)="","",INDEX(Registro!$J$1:$J$1001,$A69))) | S69: =IF($A69="","",IF(INDEX(Cálculo!$L$1:$L$1001,$A69)="","",INDEX(Cálculo!$L$1:$L$1001,$A69))) | T69: =IF($A69="","",IF(INDEX(Cálculo!$N$1:$N$1001,$A69)="","",INDEX(Cálculo!$N$1:$N$1001,$A69))) | U69: =IF($A69="","",IF(INDEX(Registro!$K$1:$K$1001,$A69)="","",INDEX(Registro!$K$1:$K$1001,$A69)))

Sheet Resumen
A1: ="RESUMEN DEL AÑO "&$B$3&" — POR MES Y BUS" -> RESUMEN DEL AÑO 2026 — POR MES Y BUS
A2: Cambia el año en la celda amarilla. Todo se calcula solo a partir de la hoja Registro. Monto ida = total de los boletos de ida. Descuento = descuentos registrados (solo afectan a la ida). Ida neto = Monto ida − Descuento. Monto llegada = monto registrado que trajeron. Neto final = monto llegada − gastos − otros gastos. Ida y llegada van separados.
A3: Año: | B3: 2026 | D3: ⌂ Inicio
C5: TDS | K5: PIN | S5: PKS | AA5: TODOS LOS BUSES
A6: N° | B6: Mes | C6: Viajes | D6: Boletos | E6: Monto ida | F6: Descuento | G6: Ida neto | H6: Monto llegada | I6: Gastos | J6: Neto final | K6: Viajes | L6: Boletos | M6: Monto ida | N6: Descuento | O6: Ida neto | P6: Monto llegada | Q6: Gastos | R6: Neto final | S6: Viajes | T6: Boletos | U6: Monto ida | V6: Descuento | W6: Ida neto | X6: Monto llegada | Y6: Gastos | Z6: Neto final | AA6: Viajes | AB6: Monto ida | AC6: Descuento | AD6: Ida neto | AE6: Monto llegada | AF6: Neto final
A7: 1 | B7: Enero | C7: =COUNTIFS(Cálculo!$A$2:$A$1001,C$5,Cálculo!$C$2:$C$1001,$B$3*100+$A7) -> 0 | D7: =SUMIFS(Cálculo!$D$2:$D$1001,Cálculo!$A$2:$A$1001,C$5,Cálculo!$C$2:$C$1001,$B$3*100+$A7)+SUMIFS(Cálculo!$H$2:$H$1001,Cálculo!$A$2:$A$1001,C$5,Cálculo!$C$2:$C$1001,$B$3*100+$A7) -> 0 | E7: =SUMIFS(Cálculo!$E$2:$E$1001,Cálculo!$A$2:$A$1001,C$5,Cálculo!$C$2:$C$1001,$B$3*100+$A7) -> 0 | F7: =SUMIFS(Cálculo!$F$2:$F$1001,Cálculo!$A$2:$A$1001,C$5,Cálculo!$C$2:$C$1001,$B$3*100+$A7) -> 0 | G7: =E7-F7 -> 0 | H7: =SUMIFS(Registro!$H$2:$H$1001,Cálculo!$A$2:$A$1001,C$5,Cálculo!$C$2:$C$1001,$B$3*100+$A7) -> 0 | I7: =SUMIFS(Cálculo!$K$2:$K$1001,Cálculo!$A$2:$A$1001,C$5,Cálculo!$C$2:$C$1001,$B$3*100+$A7)+SUMIFS(Cálculo!$L$2:$L$1001,Cálculo!$A$2:$A$1001,C$5,Cálculo!$C$2:$C$1001,$B$3*100+$A7) -> 0 | J7: =SUMIFS(Cálculo!$N$2:$N$1001,Cálculo!$A$2:$A$1001,C$5,Cálculo!$C$2:$C$1001,$B$3*100+$A7) -> 0 | K7: =COUNTIFS(Cálculo!$A$2:$A$1001,K$5,Cálculo!$C$2:$C$1001,$B$3*100+$A7) -> 0 | L7: =SUMIFS(Cálculo!$D$2:$D$1001,Cálculo!$A$2:$A$1001,K$5,Cálculo!$C$2:$C$1001,$B$3*100+$A7)+SUMIFS(Cálculo!$H$2:$H$1001,Cálculo!$A$2:$A$1001,K$5,Cálculo!$C$2:$C$1001,$B$3*100+$A7) -> 0 | M7: =SUMIFS(Cálculo!$E$2:$E$1001,Cálculo!$A$2:$A$1001,K$5,Cálculo!$C$2:$C$1001,$B$3*100+$A7) -> 0 | N7: =SUMIFS(Cálculo!$F$2:$F$1001,Cálculo!$A$2:$A$1001,K$5,Cálculo!$C$2:$C$1001,$B$3*100+$A7) -> 0 | O7: =M7-N7 -> 0 | P7: =SUMIFS(Registro!$H$2:$H$1001,Cálculo!$A$2:$A$1001,K$5,Cálculo!$C$2:$C$1001,$B$3*100+$A7) -> 0 | Q7: =SUMIFS(Cálculo!$K$2:$K$1001,Cálculo!$A$2:$A$1001,K$5,Cálculo!$C$2:$C$1001,$B$3*100+$A7)+SUMIFS(Cálculo!$L$2:$L$1001,Cálculo!$A$2:$A$1001,K$5,Cálculo!$C$2:$C$1001,$B$3*100+$A7) -> 0 | R7: =SUMIFS(Cálculo!$N$2:$N$1001,Cálculo!$A$2:$A$1001,K$5,Cálculo!$C$2:$C$1001,$B$3*100+$A7) -> 0 | S7: =COUNTIFS(Cálculo!$A$2:$A$1001,S$5,Cálculo!$C$2:$C$1001,$B$3*100+$A7) -> 0 | T7: =SUMIFS(Cálculo!$D$2:$D$1001,Cálculo!$A$2:$A$1001,S$5,Cálculo!$C$2:$C$1001,$B$3*100+$A7)+SUMIFS(Cálculo!$H$2:$H$1001,Cálculo!$A$2:$A$1001,S$5,Cálculo!$C$2:$C$1001,$B$3*100+$A7) -> 0 | U7: =SUMIFS(Cálculo!$E$2:$E$1001,Cálculo!$A$2:$A$1001,S$5,Cálculo!$C$2:$C$1001,$B$3*100+$A7) -> 0 | V7: =SUMIFS(Cálculo!$F$2:$F$1001,Cálculo!$A$2:$A$1001,S$5,Cálculo!$C$2:$C$1001,$B$3*100+$A7) -> 0 | W7: =U7-V7 -> 0 | X7: =SUMIFS(Registro!$H$2:$H$1001,Cálculo!$A$2:$A$1001,S$5,Cálculo!$C$2:$C$1001,$B$3*100+$A7) -> 0 | Y7: =SUMIFS(Cálculo!$K$2:$K$1001,Cálculo!$A$2:$A$1001,S$5,Cálculo!$C$2:$C$1001,$B$3*100+$A7)+SUMIFS(Cálculo!$L$2:$L$1001,Cálculo!$A$2:$A$1001,S$5,Cálculo!$C$2:$C$1001,$B$3*100+$A7) -> 0 | Z7: =SUMIFS(Cálculo!$N$2:$N$1001,Cálculo!$A$2:$A$1001,S$5,Cálculo!$C$2:$C$1001,$B$3*100+$A7) -> 0 | AA7: =C7+K7+S7 -> 0 | AB7: =E7+M7+U7 -> 0 | AC7: =F7+N7+V7 -> 0 | AD7: =G7+O7+W7 -> 0 | AE7: =H7+P7+X7 -> 0 | AF7: =J7+R7+Z7 -> 0
A8: 2 | B8: Febrero | C8: =COUNTIFS(Cálculo!$A$2:$A$1001,C$5,Cálculo!$C$2:$C$1001,$B$3*100+$A8) -> 0 | D8: =SUMIFS(Cálculo!$D$2:$D$1001,Cálculo!$A$2:$A$1001,C$5,Cálculo!$C$2:$C$1001,$B$3*100+$A8)+SUMIFS(Cálculo!$H$2:$H$1001,Cálculo!$A$2:$A$1001,C$5,Cálculo!$C$2:$C$1001,$B$3*100+$A8) -> 0 | E8: =SUMIFS(Cálculo!$E$2:$E$1001,Cálculo!$A$2:$A$1001,C$5,Cálculo!$C$2:$C$1001,$B$3*100+$A8) -> 0 | F8: =SUMIFS(Cálculo!$F$2:$F$1001,Cálculo!$A$2:$A$1001,C$5,Cálculo!$C$2:$C$1001,$B$3*100+$A8) -> 0 | G8: =E8-F8 -> 0 | H8: =SUMIFS(Registro!$H$2:$H$1001,Cálculo!$A$2:$A$1001,C$5,Cálculo!$C$2:$C$1001,$B$3*100+$A8) -> 0 | I8: =SUMIFS(Cálculo!$K$2:$K$1001,Cálculo!$A$2:$A$1001,C$5,Cálculo!$C$2:$C$1001,$B$3*100+$A8)+SUMIFS(Cálculo!$L$2:$L$1001,Cálculo!$A$2:$A$1001,C$5,Cálculo!$C$2:$C$1001,$B$3*100+$A8) -> 0 | J8: =SUMIFS(Cálculo!$N$2:$N$1001,Cálculo!$A$2:$A$1001,C$5,Cálculo!$C$2:$C$1001,$B$3*100+$A8) -> 0 | K8: =COUNTIFS(Cálculo!$A$2:$A$1001,K$5,Cálculo!$C$2:$C$1001,$B$3*100+$A8) -> 0 | L8: =SUMIFS(Cálculo!$D$2:$D$1001,Cálculo!$A$2:$A$1001,K$5,Cálculo!$C$2:$C$1001,$B$3*100+$A8)+SUMIFS(Cálculo!$H$2:$H$1001,Cálculo!$A$2:$A$1001,K$5,Cálculo!$C$2:$C$1001,$B$3*100+$A8) -> 0 | M8: =SUMIFS(Cálculo!$E$2:$E$1001,Cálculo!$A$2:$A$1001,K$5,Cálculo!$C$2:$C$1001,$B$3*100+$A8) -> 0 | N8: =SUMIFS(Cálculo!$F$2:$F$1001,Cálculo!$A$2:$A$1001,K$5,Cálculo!$C$2:$C$1001,$B$3*100+$A8) -> 0 | O8: =M8-N8 -> 0 | P8: =SUMIFS(Registro!$H$2:$H$1001,Cálculo!$A$2:$A$1001,K$5,Cálculo!$C$2:$C$1001,$B$3*100+$A8) -> 0 | Q8: =SUMIFS(Cálculo!$K$2:$K$1001,Cálculo!$A$2:$A$1001,K$5,Cálculo!$C$2:$C$1001,$B$3*100+$A8)+SUMIFS(Cálculo!$L$2:$L$1001,Cálculo!$A$2:$A$1001,K$5,Cálculo!$C$2:$C$1001,$B$3*100+$A8) -> 0 | R8: =SUMIFS(Cálculo!$N$2:$N$1001,Cálculo!$A$2:$A$1001,K$5,Cálculo!$C$2:$C$1001,$B$3*100+$A8) -> 0 | S8: =COUNTIFS(Cálculo!$A$2:$A$1001,S$5,Cálculo!$C$2:$C$1001,$B$3*100+$A8) -> 0 | T8: =SUMIFS(Cálculo!$D$2:$D$1001,Cálculo!$A$2:$A$1001,S$5,Cálculo!$C$2:$C$1001,$B$3*100+$A8)+SUMIFS(Cálculo!$H$2:$H$1001,Cálculo!$A$2:$A$1001,S$5,Cálculo!$C$2:$C$1001,$B$3*100+$A8) -> 0 | U8: =SUMIFS(Cálculo!$E$2:$E$1001,Cálculo!$A$2:$A$1001,S$5,Cálculo!$C$2:$C$1001,$B$3*100+$A8) -> 0 | V8: =SUMIFS(Cálculo!$F$2:$F$1001,Cálculo!$A$2:$A$1001,S$5,Cálculo!$C$2:$C$1001,$B$3*100+$A8) -> 0 | W8: =U8-V8 -> 0 | X8: =SUMIFS(Registro!$H$2:$H$1001,Cálculo!$A$2:$A$1001,S$5,Cálculo!$C$2:$C$1001,$B$3*100+$A8) -> 0 | Y8: =SUMIFS(Cálculo!$K$2:$K$1001,Cálculo!$A$2:$A$1001,S$5,Cálculo!$C$2:$C$1001,$B$3*100+$A8)+SUMIFS(Cálculo!$L$2:$L$1001,Cálculo!$A$2:$A$1001,S$5,Cálculo!$C$2:$C$1001,$B$3*100+$A8) -> 0 | Z8: =SUMIFS(Cálculo!$N$2:$N$1001,Cálculo!$A$2:$A$1001,S$5,Cálculo!$C$2:$C$1001,$B$3*100+$A8) -> 0 | AA8: =C8+K8+S8 -> 0 | AB8: =E8+M8+U8 -> 0 | AC8: =F8+N8+V8 -> 0 | AD8: =G8+O8+W8 -> 0 | AE8: =H8+P8+X8 -> 0 | AF8: =J8+R8+Z8 -> 0
A9: 3 | B9: Marzo | C9: =COUNTIFS(Cálculo!$A$2:$A$1001,C$5,Cálculo!$C$2:$C$1001,$B$3*100+$A9) -> 0 | D9: =SUMIFS(Cálculo!$D$2:$D$1001,Cálculo!$A$2:$A$1001,C$5,Cálculo!$C$2:$C$1001,$B$3*100+$A9)+SUMIFS(Cálculo!$H$2:$H$1001,Cálculo!$A$2:$A$1001,C$5,Cálculo!$C$2:$C$1001,$B$3*100+$A9) -> 0 | E9: =SUMIFS(Cálculo!$E$2:$E$1001,Cálculo!$A$2:$A$1001,C$5,Cálculo!$C$2:$C$1001,$B$3*100+$A9) -> 0 | F9: =SUMIFS(Cálculo!$F$2:$F$1001,Cálculo!$A$2:$A$1001,C$5,Cálculo!$C$2:$C$1001,$B$3*100+$A9) -> 0 | G9: =E9-F9 -> 0 | H9: =SUMIFS(Registro!$H$2:$H$1001,Cálculo!$A$2:$A$1001,C$5,Cálculo!$C$2:$C$1001,$B$3*100+$A9) -> 0 | I9: =SUMIFS(Cálculo!$K$2:$K$1001,Cálculo!$A$2:$A$1001,C$5,Cálculo!$C$2:$C$1001,$B$3*100+$A9)+SUMIFS(Cálculo!$L$2:$L$1001,Cálculo!$A$2:$A$1001,C$5,Cálculo!$C$2:$C$1001,$B$3*100+$A9) -> 0 | J9: =SUMIFS(Cálculo!$N$2:$N$1001,Cálculo!$A$2:$A$1001,C$5,Cálculo!$C$2:$C$1001,$B$3*100+$A9) -> 0 | K9: =COUNTIFS(Cálculo!$A$2:$A$1001,K$5,Cálculo!$C$2:$C$1001,$B$3*100+$A9) -> 0 | L9: =SUMIFS(Cálculo!$D$2:$D$1001,Cálculo!$A$2:$A$1001,K$5,Cálculo!$C$2:$C$1001,$B$3*100+$A9)+SUMIFS(Cálculo!$H$2:$H$1001,Cálculo!$A$2:$A$1001,K$5,Cálculo!$C$2:$C$1001,$B$3*100+$A9) -> 0 | M9: =SUMIFS(Cálculo!$E$2:$E$1001,Cálculo!$A$2:$A$1001,K$5,Cálculo!$C$2:$C$1001,$B$3*100+$A9) -> 0 | N9: =SUMIFS(Cálculo!$F$2:$F$1001,Cálculo!$A$2:$A$1001,K$5,Cálculo!$C$2:$C$1001,$B$3*100+$A9) -> 0 | O9: =M9-N9 -> 0 | P9: =SUMIFS(Registro!$H$2:$H$1001,Cálculo!$A$2:$A$1001,K$5,Cálculo!$C$2:$C$1001,$B$3*100+$A9) -> 0 | Q9: =SUMIFS(Cálculo!$K$2:$K$1001,Cálculo!$A$2:$A$1001,K$5,Cálculo!$C$2:$C$1001,$B$3*100+$A9)+SUMIFS(Cálculo!$L$2:$L$1001,Cálculo!$A$2:$A$1001,K$5,Cálculo!$C$2:$C$1001,$B$3*100+$A9) -> 0 | R9: =SUMIFS(Cálculo!$N$2:$N$1001,Cálculo!$A$2:$A$1001,K$5,Cálculo!$C$2:$C$1001,$B$3*100+$A9) -> 0 | S9: =COUNTIFS(Cálculo!$A$2:$A$1001,S$5,Cálculo!$C$2:$C$1001,$B$3*100+$A9) -> 0 | T9: =SUMIFS(Cálculo!$D$2:$D$1001,Cálculo!$A$2:$A$1001,S$5,Cálculo!$C$2:$C$1001,$B$3*100+$A9)+SUMIFS(Cálculo!$H$2:$H$1001,Cálculo!$A$2:$A$1001,S$5,Cálculo!$C$2:$C$1001,$B$3*100+$A9) -> 0 | U9: =SUMIFS(Cálculo!$E$2:$E$1001,Cálculo!$A$2:$A$1001,S$5,Cálculo!$C$2:$C$1001,$B$3*100+$A9) -> 0 | V9: =SUMIFS(Cálculo!$F$2:$F$1001,Cálculo!$A$2:$A$1001,S$5,Cálculo!$C$2:$C$1001,$B$3*100+$A9) -> 0 | W9: =U9-V9 -> 0 | X9: =SUMIFS(Registro!$H$2:$H$1001,Cálculo!$A$2:$A$1001,S$5,Cálculo!$C$2:$C$1001,$B$3*100+$A9) -> 0 | Y9: =SUMIFS(Cálculo!$K$2:$K$1001,Cálculo!$A$2:$A$1001,S$5,Cálculo!$C$2:$C$1001,$B$3*100+$A9)+SUMIFS(Cálculo!$L$2:$L$1001,Cálculo!$A$2:$A$1001,S$5,Cálculo!$C$2:$C$1001,$B$3*100+$A9) -> 0 | Z9: =SUMIFS(Cálculo!$N$2:$N$1001,Cálculo!$A$2:$A$1001,S$5,Cálculo!$C$2:$C$1001,$B$3*100+$A9) -> 0 | AA9: =C9+K9+S9 -> 0 | AB9: =E9+M9+U9 -> 0 | AC9: =F9+N9+V9 -> 0 | AD9: =G9+O9+W9 -> 0 | AE9: =H9+P9+X9 -> 0 | AF9: =J9+R9+Z9 -> 0
A10: 4 | B10: Abril | C10: =COUNTIFS(Cálculo!$A$2:$A$1001,C$5,Cálculo!$C$2:$C$1001,$B$3*100+$A10) -> 0 | D10: =SUMIFS(Cálculo!$D$2:$D$1001,Cálculo!$A$2:$A$1001,C$5,Cálculo!$C$2:$C$1001,$B$3*100+$A10)+SUMIFS(Cálculo!$H$2:$H$1001,Cálculo!$A$2:$A$1001,C$5,Cálculo!$C$2:$C$1001,$B$3*100+$A10) -> 0 | E10: =SUMIFS(Cálculo!$E$2:$E$1001,Cálculo!$A$2:$A$1001,C$5,Cálculo!$C$2:$C$1001,$B$3*100+$A10) -> 0 | F10: =SUMIFS(Cálculo!$F$2:$F$1001,Cálculo!$A$2:$A$1001,C$5,Cálculo!$C$2:$C$1001,$B$3*100+$A10) -> 0 | G10: =E10-F10 -> 0 | H10: =SUMIFS(Registro!$H$2:$H$1001,Cálculo!$A$2:$A$1001,C$5,Cálculo!$C$2:$C$1001,$B$3*100+$A10) -> 0 | I10: =SUMIFS(Cálculo!$K$2:$K$1001,Cálculo!$A$2:$A$1001,C$5,Cálculo!$C$2:$C$1001,$B$3*100+$A10)+SUMIFS(Cálculo!$L$2:$L$1001,Cálculo!$A$2:$A$1001,C$5,Cálculo!$C$2:$C$1001,$B$3*100+$A10) -> 0 | J10: =SUMIFS(Cálculo!$N$2:$N$1001,Cálculo!$A$2:$A$1001,C$5,Cálculo!$C$2:$C$1001,$B$3*100+$A10) -> 0 | K10: =COUNTIFS(Cálculo!$A$2:$A$1001,K$5,Cálculo!$C$2:$C$1001,$B$3*100+$A10) -> 0 | L10: =SUMIFS(Cálculo!$D$2:$D$1001,Cálculo!$A$2:$A$1001,K$5,Cálculo!$C$2:$C$1001,$B$3*100+$A10)+SUMIFS(Cálculo!$H$2:$H$1001,Cálculo!$A$2:$A$1001,K$5,Cálculo!$C$2:$C$1001,$B$3*100+$A10) -> 0 | M10: =SUMIFS(Cálculo!$E$2:$E$1001,Cálculo!$A$2:$A$1001,K$5,Cálculo!$C$2:$C$1001,$B$3*100+$A10) -> 0 | N10: =SUMIFS(Cálculo!$F$2:$F$1001,Cálculo!$A$2:$A$1001,K$5,Cálculo!$C$2:$C$1001,$B$3*100+$A10) -> 0 | O10: =M10-N10 -> 0 | P10: =SUMIFS(Registro!$H$2:$H$1001,Cálculo!$A$2:$A$1001,K$5,Cálculo!$C$2:$C$1001,$B$3*100+$A10) -> 0 | Q10: =SUMIFS(Cálculo!$K$2:$K$1001,Cálculo!$A$2:$A$1001,K$5,Cálculo!$C$2:$C$1001,$B$3*100+$A10)+SUMIFS(Cálculo!$L$2:$L$1001,Cálculo!$A$2:$A$1001,K$5,Cálculo!$C$2:$C$1001,$B$3*100+$A10) -> 0 | R10: =SUMIFS(Cálculo!$N$2:$N$1001,Cálculo!$A$2:$A$1001,K$5,Cálculo!$C$2:$C$1001,$B$3*100+$A10) -> 0 | S10: =COUNTIFS(Cálculo!$A$2:$A$1001,S$5,Cálculo!$C$2:$C$1001,$B$3*100+$A10) -> 0 | T10: =SUMIFS(Cálculo!$D$2:$D$1001,Cálculo!$A$2:$A$1001,S$5,Cálculo!$C$2:$C$1001,$B$3*100+$A10)+SUMIFS(Cálculo!$H$2:$H$1001,Cálculo!$A$2:$A$1001,S$5,Cálculo!$C$2:$C$1001,$B$3*100+$A10) -> 0 | U10: =SUMIFS(Cálculo!$E$2:$E$1001,Cálculo!$A$2:$A$1001,S$5,Cálculo!$C$2:$C$1001,$B$3*100+$A10) -> 0 | V10: =SUMIFS(Cálculo!$F$2:$F$1001,Cálculo!$A$2:$A$1001,S$5,Cálculo!$C$2:$C$1001,$B$3*100+$A10) -> 0 | W10: =U10-V10 -> 0 | X10: =SUMIFS(Registro!$H$2:$H$1001,Cálculo!$A$2:$A$1001,S$5,Cálculo!$C$2:$C$1001,$B$3*100+$A10) -> 0 | Y10: =SUMIFS(Cálculo!$K$2:$K$1001,Cálculo!$A$2:$A$1001,S$5,Cálculo!$C$2:$C$1001,$B$3*100+$A10)+SUMIFS(Cálculo!$L$2:$L$1001,Cálculo!$A$2:$A$1001,S$5,Cálculo!$C$2:$C$1001,$B$3*100+$A10) -> 0 | Z10: =SUMIFS(Cálculo!$N$2:$N$1001,Cálculo!$A$2:$A$1001,S$5,Cálculo!$C$2:$C$1001,$B$3*100+$A10) -> 0 | AA10: =C10+K10+S10 -> 0 | AB10: =E10+M10+U10 -> 0 | AC10: =F10+N10+V10 -> 0 | AD10: =G10+O10+W10 -> 0 | AE10: =H10+P10+X10 -> 0 | AF10: =J10+R10+Z10 -> 0
A11: 5 | B11: Mayo | C11: =COUNTIFS(Cálculo!$A$2:$A$1001,C$5,Cálculo!$C$2:$C$1001,$B$3*100+$A11) -> 0 | D11: =SUMIFS(Cálculo!$D$2:$D$1001,Cálculo!$A$2:$A$1001,C$5,Cálculo!$C$2:$C$1001,$B$3*100+$A11)+SUMIFS(Cálculo!$H$2:$H$1001,Cálculo!$A$2:$A$1001,C$5,Cálculo!$C$2:$C$1001,$B$3*100+$A11) -> 0 | E11: =SUMIFS(Cálculo!$E$2:$E$1001,Cálculo!$A$2:$A$1001,C$5,Cálculo!$C$2:$C$1001,$B$3*100+$A11) -> 0 | F11: =SUMIFS(Cálculo!$F$2:$F$1001,Cálculo!$A$2:$A$1001,C$5,Cálculo!$C$2:$C$1001,$B$3*100+$A11) -> 0 | G11: =E11-F11 -> 0 | H11: =SUMIFS(Registro!$H$2:$H$1001,Cálculo!$A$2:$A$1001,C$5,Cálculo!$C$2:$C$1001,$B$3*100+$A11) -> 0 | I11: =SUMIFS(Cálculo!$K$2:$K$1001,Cálculo!$A$2:$A$1001,C$5,Cálculo!$C$2:$C$1001,$B$3*100+$A11)+SUMIFS(Cálculo!$L$2:$L$1001,Cálculo!$A$2:$A$1001,C$5,Cálculo!$C$2:$C$1001,$B$3*100+$A11) -> 0 | J11: =SUMIFS(Cálculo!$N$2:$N$1001,Cálculo!$A$2:$A$1001,C$5,Cálculo!$C$2:$C$1001,$B$3*100+$A11) -> 0 | K11: =COUNTIFS(Cálculo!$A$2:$A$1001,K$5,Cálculo!$C$2:$C$1001,$B$3*100+$A11) -> 0 | L11: =SUMIFS(Cálculo!$D$2:$D$1001,Cálculo!$A$2:$A$1001,K$5,Cálculo!$C$2:$C$1001,$B$3*100+$A11)+SUMIFS(Cálculo!$H$2:$H$1001,Cálculo!$A$2:$A$1001,K$5,Cálculo!$C$2:$C$1001,$B$3*100+$A11) -> 0 | M11: =SUMIFS(Cálculo!$E$2:$E$1001,Cálculo!$A$2:$A$1001,K$5,Cálculo!$C$2:$C$1001,$B$3*100+$A11) -> 0 | N11: =SUMIFS(Cálculo!$F$2:$F$1001,Cálculo!$A$2:$A$1001,K$5,Cálculo!$C$2:$C$1001,$B$3*100+$A11) -> 0 | O11: =M11-N11 -> 0 | P11: =SUMIFS(Registro!$H$2:$H$1001,Cálculo!$A$2:$A$1001,K$5,Cálculo!$C$2:$C$1001,$B$3*100+$A11) -> 0 | Q11: =SUMIFS(Cálculo!$K$2:$K$1001,Cálculo!$A$2:$A$1001,K$5,Cálculo!$C$2:$C$1001,$B$3*100+$A11)+SUMIFS(Cálculo!$L$2:$L$1001,Cálculo!$A$2:$A$1001,K$5,Cálculo!$C$2:$C$1001,$B$3*100+$A11) -> 0 | R11: =SUMIFS(Cálculo!$N$2:$N$1001,Cálculo!$A$2:$A$1001,K$5,Cálculo!$C$2:$C$1001,$B$3*100+$A11) -> 0 | S11: =COUNTIFS(Cálculo!$A$2:$A$1001,S$5,Cálculo!$C$2:$C$1001,$B$3*100+$A11) -> 0 | T11: =SUMIFS(Cálculo!$D$2:$D$1001,Cálculo!$A$2:$A$1001,S$5,Cálculo!$C$2:$C$1001,$B$3*100+$A11)+SUMIFS(Cálculo!$H$2:$H$1001,Cálculo!$A$2:$A$1001,S$5,Cálculo!$C$2:$C$1001,$B$3*100+$A11) -> 0 | U11: =SUMIFS(Cálculo!$E$2:$E$1001,Cálculo!$A$2:$A$1001,S$5,Cálculo!$C$2:$C$1001,$B$3*100+$A11) -> 0 | V11: =SUMIFS(Cálculo!$F$2:$F$1001,Cálculo!$A$2:$A$1001,S$5,Cálculo!$C$2:$C$1001,$B$3*100+$A11) -> 0 | W11: =U11-V11 -> 0 | X11: =SUMIFS(Registro!$H$2:$H$1001,Cálculo!$A$2:$A$1001,S$5,Cálculo!$C$2:$C$1001,$B$3*100+$A11) -> 0 | Y11: =SUMIFS(Cálculo!$K$2:$K$1001,Cálculo!$A$2:$A$1001,S$5,Cálculo!$C$2:$C$1001,$B$3*100+$A11)+SUMIFS(Cálculo!$L$2:$L$1001,Cálculo!$A$2:$A$1001,S$5,Cálculo!$C$2:$C$1001,$B$3*100+$A11) -> 0 | Z11: =SUMIFS(Cálculo!$N$2:$N$1001,Cálculo!$A$2:$A$1001,S$5,Cálculo!$C$2:$C$1001,$B$3*100+$A11) -> 0 | AA11: =C11+K11+S11 -> 0 | AB11: =E11+M11+U11 -> 0 | AC11: =F11+N11+V11 -> 0 | AD11: =G11+O11+W11 -> 0 | AE11: =H11+P11+X11 -> 0 | AF11: =J11+R11+Z11 -> 0
A12: 6 | B12: Junio | C12: =COUNTIFS(Cálculo!$A$2:$A$1001,C$5,Cálculo!$C$2:$C$1001,$B$3*100+$A12) -> 0 | D12: =SUMIFS(Cálculo!$D$2:$D$1001,Cálculo!$A$2:$A$1001,C$5,Cálculo!$C$2:$C$1001,$B$3*100+$A12)+SUMIFS(Cálculo!$H$2:$H$1001,Cálculo!$A$2:$A$1001,C$5,Cálculo!$C$2:$C$1001,$B$3*100+$A12) -> 0 | E12: =SUMIFS(Cálculo!$E$2:$E$1001,Cálculo!$A$2:$A$1001,C$5,Cálculo!$C$2:$C$1001,$B$3*100+$A12) -> 0 | F12: =SUMIFS(Cálculo!$F$2:$F$1001,Cálculo!$A$2:$A$1001,C$5,Cálculo!$C$2:$C$1001,$B$3*100+$A12) -> 0 | G12: =E12-F12 -> 0 | H12: =SUMIFS(Registro!$H$2:$H$1001,Cálculo!$A$2:$A$1001,C$5,Cálculo!$C$2:$C$1001,$B$3*100+$A12) -> 0 | I12: =SUMIFS(Cálculo!$K$2:$K$1001,Cálculo!$A$2:$A$1001,C$5,Cálculo!$C$2:$C$1001,$B$3*100+$A12)+SUMIFS(Cálculo!$L$2:$L$1001,Cálculo!$A$2:$A$1001,C$5,Cálculo!$C$2:$C$1001,$B$3*100+$A12) -> 0 | J12: =SUMIFS(Cálculo!$N$2:$N$1001,Cálculo!$A$2:$A$1001,C$5,Cálculo!$C$2:$C$1001,$B$3*100+$A12) -> 0 | K12: =COUNTIFS(Cálculo!$A$2:$A$1001,K$5,Cálculo!$C$2:$C$1001,$B$3*100+$A12) -> 0 | L12: =SUMIFS(Cálculo!$D$2:$D$1001,Cálculo!$A$2:$A$1001,K$5,Cálculo!$C$2:$C$1001,$B$3*100+$A12)+SUMIFS(Cálculo!$H$2:$H$1001,Cálculo!$A$2:$A$1001,K$5,Cálculo!$C$2:$C$1001,$B$3*100+$A12) -> 0 | M12: =SUMIFS(Cálculo!$E$2:$E$1001,Cálculo!$A$2:$A$1001,K$5,Cálculo!$C$2:$C$1001,$B$3*100+$A12) -> 0 | N12: =SUMIFS(Cálculo!$F$2:$F$1001,Cálculo!$A$2:$A$1001,K$5,Cálculo!$C$2:$C$1001,$B$3*100+$A12) -> 0 | O12: =M12-N12 -> 0 | P12: =SUMIFS(Registro!$H$2:$H$1001,Cálculo!$A$2:$A$1001,K$5,Cálculo!$C$2:$C$1001,$B$3*100+$A12) -> 0 | Q12: =SUMIFS(Cálculo!$K$2:$K$1001,Cálculo!$A$2:$A$1001,K$5,Cálculo!$C$2:$C$1001,$B$3*100+$A12)+SUMIFS(Cálculo!$L$2:$L$1001,Cálculo!$A$2:$A$1001,K$5,Cálculo!$C$2:$C$1001,$B$3*100+$A12) -> 0 | R12: =SUMIFS(Cálculo!$N$2:$N$1001,Cálculo!$A$2:$A$1001,K$5,Cálculo!$C$2:$C$1001,$B$3*100+$A12) -> 0 | S12: =COUNTIFS(Cálculo!$A$2:$A$1001,S$5,Cálculo!$C$2:$C$1001,$B$3*100+$A12) -> 0 | T12: =SUMIFS(Cálculo!$D$2:$D$1001,Cálculo!$A$2:$A$1001,S$5,Cálculo!$C$2:$C$1001,$B$3*100+$A12)+SUMIFS(Cálculo!$H$2:$H$1001,Cálculo!$A$2:$A$1001,S$5,Cálculo!$C$2:$C$1001,$B$3*100+$A12) -> 0 | U12: =SUMIFS(Cálculo!$E$2:$E$1001,Cálculo!$A$2:$A$1001,S$5,Cálculo!$C$2:$C$1001,$B$3*100+$A12) -> 0 | V12: =SUMIFS(Cálculo!$F$2:$F$1001,Cálculo!$A$2:$A$1001,S$5,Cálculo!$C$2:$C$1001,$B$3*100+$A12) -> 0 | W12: =U12-V12 -> 0 | X12: =SUMIFS(Registro!$H$2:$H$1001,Cálculo!$A$2:$A$1001,S$5,Cálculo!$C$2:$C$1001,$B$3*100+$A12) -> 0 | Y12: =SUMIFS(Cálculo!$K$2:$K$1001,Cálculo!$A$2:$A$1001,S$5,Cálculo!$C$2:$C$1001,$B$3*100+$A12)+SUMIFS(Cálculo!$L$2:$L$1001,Cálculo!$A$2:$A$1001,S$5,Cálculo!$C$2:$C$1001,$B$3*100+$A12) -> 0 | Z12: =SUMIFS(Cálculo!$N$2:$N$1001,Cálculo!$A$2:$A$1001,S$5,Cálculo!$C$2:$C$1001,$B$3*100+$A12) -> 0 | AA12: =C12+K12+S12 -> 0 | AB12: =E12+M12+U12 -> 0 | AC12: =F12+N12+V12 -> 0 | AD12: =G12+O12+W12 -> 0 | AE12: =H12+P12+X12 -> 0 | AF12: =J12+R12+Z12 -> 0
A13: 7 | B13: Julio | C13: =COUNTIFS(Cálculo!$A$2:$A$1001,C$5,Cálculo!$C$2:$C$1001,$B$3*100+$A13) -> 0 | D13: =SUMIFS(Cálculo!$D$2:$D$1001,Cálculo!$A$2:$A$1001,C$5,Cálculo!$C$2:$C$1001,$B$3*100+$A13)+SUMIFS(Cálculo!$H$2:$H$1001,Cálculo!$A$2:$A$1001,C$5,Cálculo!$C$2:$C$1001,$B$3*100+$A13) -> 0 | E13: =SUMIFS(Cálculo!$E$2:$E$1001,Cálculo!$A$2:$A$1001,C$5,Cálculo!$C$2:$C$1001,$B$3*100+$A13) -> 0 | F13: =SUMIFS(Cálculo!$F$2:$F$1001,Cálculo!$A$2:$A$1001,C$5,Cálculo!$C$2:$C$1001,$B$3*100+$A13) -> 0 | G13: =E13-F13 -> 0 | H13: =SUMIFS(Registro!$H$2:$H$1001,Cálculo!$A$2:$A$1001,C$5,Cálculo!$C$2:$C$1001,$B$3*100+$A13) -> 0 | I13: =SUMIFS(Cálculo!$K$2:$K$1001,Cálculo!$A$2:$A$1001,C$5,Cálculo!$C$2:$C$1001,$B$3*100+$A13)+SUMIFS(Cálculo!$L$2:$L$1001,Cálculo!$A$2:$A$1001,C$5,Cálculo!$C$2:$C$1001,$B$3*100+$A13) -> 0 | J13: =SUMIFS(Cálculo!$N$2:$N$1001,Cálculo!$A$2:$A$1001,C$5,Cálculo!$C$2:$C$1001,$B$3*100+$A13) -> 0 | K13: =COUNTIFS(Cálculo!$A$2:$A$1001,K$5,Cálculo!$C$2:$C$1001,$B$3*100+$A13) -> 0 | L13: =SUMIFS(Cálculo!$D$2:$D$1001,Cálculo!$A$2:$A$1001,K$5,Cálculo!$C$2:$C$1001,$B$3*100+$A13)+SUMIFS(Cálculo!$H$2:$H$1001,Cálculo!$A$2:$A$1001,K$5,Cálculo!$C$2:$C$1001,$B$3*100+$A13) -> 0 | M13: =SUMIFS(Cálculo!$E$2:$E$1001,Cálculo!$A$2:$A$1001,K$5,Cálculo!$C$2:$C$1001,$B$3*100+$A13) -> 0 | N13: =SUMIFS(Cálculo!$F$2:$F$1001,Cálculo!$A$2:$A$1001,K$5,Cálculo!$C$2:$C$1001,$B$3*100+$A13) -> 0 | O13: =M13-N13 -> 0 | P13: =SUMIFS(Registro!$H$2:$H$1001,Cálculo!$A$2:$A$1001,K$5,Cálculo!$C$2:$C$1001,$B$3*100+$A13) -> 0 | Q13: =SUMIFS(Cálculo!$K$2:$K$1001,Cálculo!$A$2:$A$1001,K$5,Cálculo!$C$2:$C$1001,$B$3*100+$A13)+SUMIFS(Cálculo!$L$2:$L$1001,Cálculo!$A$2:$A$1001,K$5,Cálculo!$C$2:$C$1001,$B$3*100+$A13) -> 0 | R13: =SUMIFS(Cálculo!$N$2:$N$1001,Cálculo!$A$2:$A$1001,K$5,Cálculo!$C$2:$C$1001,$B$3*100+$A13) -> 0 | S13: =COUNTIFS(Cálculo!$A$2:$A$1001,S$5,Cálculo!$C$2:$C$1001,$B$3*100+$A13) -> 0 | T13: =SUMIFS(Cálculo!$D$2:$D$1001,Cálculo!$A$2:$A$1001,S$5,Cálculo!$C$2:$C$1001,$B$3*100+$A13)+SUMIFS(Cálculo!$H$2:$H$1001,Cálculo!$A$2:$A$1001,S$5,Cálculo!$C$2:$C$1001,$B$3*100+$A13) -> 0 | U13: =SUMIFS(Cálculo!$E$2:$E$1001,Cálculo!$A$2:$A$1001,S$5,Cálculo!$C$2:$C$1001,$B$3*100+$A13) -> 0 | V13: =SUMIFS(Cálculo!$F$2:$F$1001,Cálculo!$A$2:$A$1001,S$5,Cálculo!$C$2:$C$1001,$B$3*100+$A13) -> 0 | W13: =U13-V13 -> 0 | X13: =SUMIFS(Registro!$H$2:$H$1001,Cálculo!$A$2:$A$1001,S$5,Cálculo!$C$2:$C$1001,$B$3*100+$A13) -> 0 | Y13: =SUMIFS(Cálculo!$K$2:$K$1001,Cálculo!$A$2:$A$1001,S$5,Cálculo!$C$2:$C$1001,$B$3*100+$A13)+SUMIFS(Cálculo!$L$2:$L$1001,Cálculo!$A$2:$A$1001,S$5,Cálculo!$C$2:$C$1001,$B$3*100+$A13) -> 0 | Z13: =SUMIFS(Cálculo!$N$2:$N$1001,Cálculo!$A$2:$A$1001,S$5,Cálculo!$C$2:$C$1001,$B$3*100+$A13) -> 0 | AA13: =C13+K13+S13 -> 0 | AB13: =E13+M13+U13 -> 0 | AC13: =F13+N13+V13 -> 0 | AD13: =G13+O13+W13 -> 0 | AE13: =H13+P13+X13 -> 0 | AF13: =J13+R13+Z13 -> 0
A14: 8 | B14: Agosto | C14: =COUNTIFS(Cálculo!$A$2:$A$1001,C$5,Cálculo!$C$2:$C$1001,$B$3*100+$A14) -> 0 | D14: =SUMIFS(Cálculo!$D$2:$D$1001,Cálculo!$A$2:$A$1001,C$5,Cálculo!$C$2:$C$1001,$B$3*100+$A14)+SUMIFS(Cálculo!$H$2:$H$1001,Cálculo!$A$2:$A$1001,C$5,Cálculo!$C$2:$C$1001,$B$3*100+$A14) -> 0 | E14: =SUMIFS(Cálculo!$E$2:$E$1001,Cálculo!$A$2:$A$1001,C$5,Cálculo!$C$2:$C$1001,$B$3*100+$A14) -> 0 | F14: =SUMIFS(Cálculo!$F$2:$F$1001,Cálculo!$A$2:$A$1001,C$5,Cálculo!$C$2:$C$1001,$B$3*100+$A14) -> 0 | G14: =E14-F14 -> 0 | H14: =SUMIFS(Registro!$H$2:$H$1001,Cálculo!$A$2:$A$1001,C$5,Cálculo!$C$2:$C$1001,$B$3*100+$A14) -> 0 | I14: =SUMIFS(Cálculo!$K$2:$K$1001,Cálculo!$A$2:$A$1001,C$5,Cálculo!$C$2:$C$1001,$B$3*100+$A14)+SUMIFS(Cálculo!$L$2:$L$1001,Cálculo!$A$2:$A$1001,C$5,Cálculo!$C$2:$C$1001,$B$3*100+$A14) -> 0 | J14: =SUMIFS(Cálculo!$N$2:$N$1001,Cálculo!$A$2:$A$1001,C$5,Cálculo!$C$2:$C$1001,$B$3*100+$A14) -> 0 | K14: =COUNTIFS(Cálculo!$A$2:$A$1001,K$5,Cálculo!$C$2:$C$1001,$B$3*100+$A14) -> 0 | L14: =SUMIFS(Cálculo!$D$2:$D$1001,Cálculo!$A$2:$A$1001,K$5,Cálculo!$C$2:$C$1001,$B$3*100+$A14)+SUMIFS(Cálculo!$H$2:$H$1001,Cálculo!$A$2:$A$1001,K$5,Cálculo!$C$2:$C$1001,$B$3*100+$A14) -> 0 | M14: =SUMIFS(Cálculo!$E$2:$E$1001,Cálculo!$A$2:$A$1001,K$5,Cálculo!$C$2:$C$1001,$B$3*100+$A14) -> 0 | N14: =SUMIFS(Cálculo!$F$2:$F$1001,Cálculo!$A$2:$A$1001,K$5,Cálculo!$C$2:$C$1001,$B$3*100+$A14) -> 0 | O14: =M14-N14 -> 0 | P14: =SUMIFS(Registro!$H$2:$H$1001,Cálculo!$A$2:$A$1001,K$5,Cálculo!$C$2:$C$1001,$B$3*100+$A14) -> 0 | Q14: =SUMIFS(Cálculo!$K$2:$K$1001,Cálculo!$A$2:$A$1001,K$5,Cálculo!$C$2:$C$1001,$B$3*100+$A14)+SUMIFS(Cálculo!$L$2:$L$1001,Cálculo!$A$2:$A$1001,K$5,Cálculo!$C$2:$C$1001,$B$3*100+$A14) -> 0 | R14: =SUMIFS(Cálculo!$N$2:$N$1001,Cálculo!$A$2:$A$1001,K$5,Cálculo!$C$2:$C$1001,$B$3*100+$A14) -> 0 | S14: =COUNTIFS(Cálculo!$A$2:$A$1001,S$5,Cálculo!$C$2:$C$1001,$B$3*100+$A14) -> 0 | T14: =SUMIFS(Cálculo!$D$2:$D$1001,Cálculo!$A$2:$A$1001,S$5,Cálculo!$C$2:$C$1001,$B$3*100+$A14)+SUMIFS(Cálculo!$H$2:$H$1001,Cálculo!$A$2:$A$1001,S$5,Cálculo!$C$2:$C$1001,$B$3*100+$A14) -> 0 | U14: =SUMIFS(Cálculo!$E$2:$E$1001,Cálculo!$A$2:$A$1001,S$5,Cálculo!$C$2:$C$1001,$B$3*100+$A14) -> 0 | V14: =SUMIFS(Cálculo!$F$2:$F$1001,Cálculo!$A$2:$A$1001,S$5,Cálculo!$C$2:$C$1001,$B$3*100+$A14) -> 0 | W14: =U14-V14 -> 0 | X14: =SUMIFS(Registro!$H$2:$H$1001,Cálculo!$A$2:$A$1001,S$5,Cálculo!$C$2:$C$1001,$B$3*100+$A14) -> 0 | Y14: =SUMIFS(Cálculo!$K$2:$K$1001,Cálculo!$A$2:$A$1001,S$5,Cálculo!$C$2:$C$1001,$B$3*100+$A14)+SUMIFS(Cálculo!$L$2:$L$1001,Cálculo!$A$2:$A$1001,S$5,Cálculo!$C$2:$C$1001,$B$3*100+$A14) -> 0 | Z14: =SUMIFS(Cálculo!$N$2:$N$1001,Cálculo!$A$2:$A$1001,S$5,Cálculo!$C$2:$C$1001,$B$3*100+$A14) -> 0 | AA14: =C14+K14+S14 -> 0 | AB14: =E14+M14+U14 -> 0 | AC14: =F14+N14+V14 -> 0 | AD14: =G14+O14+W14 -> 0 | AE14: =H14+P14+X14 -> 0 | AF14: =J14+R14+Z14 -> 0
A15: 9 | B15: Septiembre | C15: =COUNTIFS(Cálculo!$A$2:$A$1001,C$5,Cálculo!$C$2:$C$1001,$B$3*100+$A15) -> 0 | D15: =SUMIFS(Cálculo!$D$2:$D$1001,Cálculo!$A$2:$A$1001,C$5,Cálculo!$C$2:$C$1001,$B$3*100+$A15)+SUMIFS(Cálculo!$H$2:$H$1001,Cálculo!$A$2:$A$1001,C$5,Cálculo!$C$2:$C$1001,$B$3*100+$A15) -> 0 | E15: =SUMIFS(Cálculo!$E$2:$E$1001,Cálculo!$A$2:$A$1001,C$5,Cálculo!$C$2:$C$1001,$B$3*100+$A15) -> 0 | F15: =SUMIFS(Cálculo!$F$2:$F$1001,Cálculo!$A$2:$A$1001,C$5,Cálculo!$C$2:$C$1001,$B$3*100+$A15) -> 0 | G15: =E15-F15 -> 0 | H15: =SUMIFS(Registro!$H$2:$H$1001,Cálculo!$A$2:$A$1001,C$5,Cálculo!$C$2:$C$1001,$B$3*100+$A15) -> 0 | I15: =SUMIFS(Cálculo!$K$2:$K$1001,Cálculo!$A$2:$A$1001,C$5,Cálculo!$C$2:$C$1001,$B$3*100+$A15)+SUMIFS(Cálculo!$L$2:$L$1001,Cálculo!$A$2:$A$1001,C$5,Cálculo!$C$2:$C$1001,$B$3*100+$A15) -> 0 | J15: =SUMIFS(Cálculo!$N$2:$N$1001,Cálculo!$A$2:$A$1001,C$5,Cálculo!$C$2:$C$1001,$B$3*100+$A15) -> 0 | K15: =COUNTIFS(Cálculo!$A$2:$A$1001,K$5,Cálculo!$C$2:$C$1001,$B$3*100+$A15) -> 0 | L15: =SUMIFS(Cálculo!$D$2:$D$1001,Cálculo!$A$2:$A$1001,K$5,Cálculo!$C$2:$C$1001,$B$3*100+$A15)+SUMIFS(Cálculo!$H$2:$H$1001,Cálculo!$A$2:$A$1001,K$5,Cálculo!$C$2:$C$1001,$B$3*100+$A15) -> 0 | M15: =SUMIFS(Cálculo!$E$2:$E$1001,Cálculo!$A$2:$A$1001,K$5,Cálculo!$C$2:$C$1001,$B$3*100+$A15) -> 0 | N15: =SUMIFS(Cálculo!$F$2:$F$1001,Cálculo!$A$2:$A$1001,K$5,Cálculo!$C$2:$C$1001,$B$3*100+$A15) -> 0 | O15: =M15-N15 -> 0 | P15: =SUMIFS(Registro!$H$2:$H$1001,Cálculo!$A$2:$A$1001,K$5,Cálculo!$C$2:$C$1001,$B$3*100+$A15) -> 0 | Q15: =SUMIFS(Cálculo!$K$2:$K$1001,Cálculo!$A$2:$A$1001,K$5,Cálculo!$C$2:$C$1001,$B$3*100+$A15)+SUMIFS(Cálculo!$L$2:$L$1001,Cálculo!$A$2:$A$1001,K$5,Cálculo!$C$2:$C$1001,$B$3*100+$A15) -> 0 | R15: =SUMIFS(Cálculo!$N$2:$N$1001,Cálculo!$A$2:$A$1001,K$5,Cálculo!$C$2:$C$1001,$B$3*100+$A15) -> 0 | S15: =COUNTIFS(Cálculo!$A$2:$A$1001,S$5,Cálculo!$C$2:$C$1001,$B$3*100+$A15) -> 0 | T15: =SUMIFS(Cálculo!$D$2:$D$1001,Cálculo!$A$2:$A$1001,S$5,Cálculo!$C$2:$C$1001,$B$3*100+$A15)+SUMIFS(Cálculo!$H$2:$H$1001,Cálculo!$A$2:$A$1001,S$5,Cálculo!$C$2:$C$1001,$B$3*100+$A15) -> 0 | U15: =SUMIFS(Cálculo!$E$2:$E$1001,Cálculo!$A$2:$A$1001,S$5,Cálculo!$C$2:$C$1001,$B$3*100+$A15) -> 0 | V15: =SUMIFS(Cálculo!$F$2:$F$1001,Cálculo!$A$2:$A$1001,S$5,Cálculo!$C$2:$C$1001,$B$3*100+$A15) -> 0 | W15: =U15-V15 -> 0 | X15: =SUMIFS(Registro!$H$2:$H$1001,Cálculo!$A$2:$A$1001,S$5,Cálculo!$C$2:$C$1001,$B$3*100+$A15) -> 0 | Y15: =SUMIFS(Cálculo!$K$2:$K$1001,Cálculo!$A$2:$A$1001,S$5,Cálculo!$C$2:$C$1001,$B$3*100+$A15)+SUMIFS(Cálculo!$L$2:$L$1001,Cálculo!$A$2:$A$1001,S$5,Cálculo!$C$2:$C$1001,$B$3*100+$A15) -> 0 | Z15: =SUMIFS(Cálculo!$N$2:$N$1001,Cálculo!$A$2:$A$1001,S$5,Cálculo!$C$2:$C$1001,$B$3*100+$A15) -> 0 | AA15: =C15+K15+S15 -> 0 | AB15: =E15+M15+U15 -> 0 | AC15: =F15+N15+V15 -> 0 | AD15: =G15+O15+W15 -> 0 | AE15: =H15+P15+X15 -> 0 | AF15: =J15+R15+Z15 -> 0
A16: 10 | B16: Octubre | C16: =COUNTIFS(Cálculo!$A$2:$A$1001,C$5,Cálculo!$C$2:$C$1001,$B$3*100+$A16) -> 26 | D16: =SUMIFS(Cálculo!$D$2:$D$1001,Cálculo!$A$2:$A$1001,C$5,Cálculo!$C$2:$C$1001,$B$3*100+$A16)+SUMIFS(Cálculo!$H$2:$H$1001,Cálculo!$A$2:$A$1001,C$5,Cálculo!$C$2:$C$1001,$B$3*100+$A16) -> 1129 | E16: =SUMIFS(Cálculo!$E$2:$E$1001,Cálculo!$A$2:$A$1001,C$5,Cálculo!$C$2:$C$1001,$B$3*100+$A16) -> 53675 | F16: =SUMIFS(Cálculo!$F$2:$F$1001,Cálculo!$A$2:$A$1001,C$5,Cálculo!$C$2:$C$1001,$B$3*100+$A16) -> 0 | G16: =E16-F16 -> 53675 | H16: =SUMIFS(Registro!$H$2:$H$1001,Cálculo!$A$2:$A$1001,C$5,Cálculo!$C$2:$C$1001,$B$3*100+$A16) -> 72319 | I16: =SUMIFS(Cálculo!$K$2:$K$1001,Cálculo!$A$2:$A$1001,C$5,Cálculo!$C$2:$C$1001,$B$3*100+$A16)+SUMIFS(Cálculo!$L$2:$L$1001,Cálculo!$A$2:$A$1001,C$5,Cálculo!$C$2:$C$1001,$B$3*100+$A16) -> 69567 | J16: =SUMIFS(Cálculo!$N$2:$N$1001,Cálculo!$A$2:$A$1001,C$5,Cálculo!$C$2:$C$1001,$B$3*100+$A16) -> 2752 | K16: =COUNTIFS(Cálculo!$A$2:$A$1001,K$5,Cálculo!$C$2:$C$1001,$B$3*100+$A16) -> 23 | L16: =SUMIFS(Cálculo!$D$2:$D$1001,Cálculo!$A$2:$A$1001,K$5,Cálculo!$C$2:$C$1001,$B$3*100+$A16)+SUMIFS(Cálculo!$H$2:$H$1001,Cálculo!$A$2:$A$1001,K$5,Cálculo!$C$2:$C$1001,$B$3*100+$A16) -> 1253 | M16: =SUMIFS(Cálculo!$E$2:$E$1001,Cálculo!$A$2:$A$1001,K$5,Cálculo!$C$2:$C$1001,$B$3*100+$A16) -> 52980 | N16: =SUMIFS(Cálculo!$F$2:$F$1001,Cálculo!$A$2:$A$1001,K$5,Cálculo!$C$2:$C$1001,$B$3*100+$A16) -> 0 | O16: =M16-N16 -> 52980 | P16: =SUMIFS(Registro!$H$2:$H$1001,Cálculo!$A$2:$A$1001,K$5,Cálculo!$C$2:$C$1001,$B$3*100+$A16) -> 58695 | Q16: =SUMIFS(Cálculo!$K$2:$K$1001,Cálculo!$A$2:$A$1001,K$5,Cálculo!$C$2:$C$1001,$B$3*100+$A16)+SUMIFS(Cálculo!$L$2:$L$1001,Cálculo!$A$2:$A$1001,K$5,Cálculo!$C$2:$C$1001,$B$3*100+$A16) -> 8647 | R16: =SUMIFS(Cálculo!$N$2:$N$1001,Cálculo!$A$2:$A$1001,K$5,Cálculo!$C$2:$C$1001,$B$3*100+$A16) -> 50048 | S16: =COUNTIFS(Cálculo!$A$2:$A$1001,S$5,Cálculo!$C$2:$C$1001,$B$3*100+$A16) -> 0 | T16: =SUMIFS(Cálculo!$D$2:$D$1001,Cálculo!$A$2:$A$1001,S$5,Cálculo!$C$2:$C$1001,$B$3*100+$A16)+SUMIFS(Cálculo!$H$2:$H$1001,Cálculo!$A$2:$A$1001,S$5,Cálculo!$C$2:$C$1001,$B$3*100+$A16) -> 0 | U16: =SUMIFS(Cálculo!$E$2:$E$1001,Cálculo!$A$2:$A$1001,S$5,Cálculo!$C$2:$C$1001,$B$3*100+$A16) -> 0 | V16: =SUMIFS(Cálculo!$F$2:$F$1001,Cálculo!$A$2:$A$1001,S$5,Cálculo!$C$2:$C$1001,$B$3*100+$A16) -> 0 | W16: =U16-V16 -> 0 | X16: =SUMIFS(Registro!$H$2:$H$1001,Cálculo!$A$2:$A$1001,S$5,Cálculo!$C$2:$C$1001,$B$3*100+$A16) -> 0 | Y16: =SUMIFS(Cálculo!$K$2:$K$1001,Cálculo!$A$2:$A$1001,S$5,Cálculo!$C$2:$C$1001,$B$3*100+$A16)+SUMIFS(Cálculo!$L$2:$L$1001,Cálculo!$A$2:$A$1001,S$5,Cálculo!$C$2:$C$1001,$B$3*100+$A16) -> 0 | Z16: =SUMIFS(Cálculo!$N$2:$N$1001,Cálculo!$A$2:$A$1001,S$5,Cálculo!$C$2:$C$1001,$B$3*100+$A16) -> 0 | AA16: =C16+K16+S16 -> 49 | AB16: =E16+M16+U16 -> 106655 | AC16: =F16+N16+V16 -> 0 | AD16: =G16+O16+W16 -> 106655 | AE16: =H16+P16+X16 -> 131014 | AF16: =J16+R16+Z16 -> 52800
A17: 11 | B17: Noviembre | C17: =COUNTIFS(Cálculo!$A$2:$A$1001,C$5,Cálculo!$C$2:$C$1001,$B$3*100+$A17) -> 0 | D17: =SUMIFS(Cálculo!$D$2:$D$1001,Cálculo!$A$2:$A$1001,C$5,Cálculo!$C$2:$C$1001,$B$3*100+$A17)+SUMIFS(Cálculo!$H$2:$H$1001,Cálculo!$A$2:$A$1001,C$5,Cálculo!$C$2:$C$1001,$B$3*100+$A17) -> 0 | E17: =SUMIFS(Cálculo!$E$2:$E$1001,Cálculo!$A$2:$A$1001,C$5,Cálculo!$C$2:$C$1001,$B$3*100+$A17) -> 0 | F17: =SUMIFS(Cálculo!$F$2:$F$1001,Cálculo!$A$2:$A$1001,C$5,Cálculo!$C$2:$C$1001,$B$3*100+$A17) -> 0 | G17: =E17-F17 -> 0 | H17: =SUMIFS(Registro!$H$2:$H$1001,Cálculo!$A$2:$A$1001,C$5,Cálculo!$C$2:$C$1001,$B$3*100+$A17) -> 0 | I17: =SUMIFS(Cálculo!$K$2:$K$1001,Cálculo!$A$2:$A$1001,C$5,Cálculo!$C$2:$C$1001,$B$3*100+$A17)+SUMIFS(Cálculo!$L$2:$L$1001,Cálculo!$A$2:$A$1001,C$5,Cálculo!$C$2:$C$1001,$B$3*100+$A17) -> 0 | J17: =SUMIFS(Cálculo!$N$2:$N$1001,Cálculo!$A$2:$A$1001,C$5,Cálculo!$C$2:$C$1001,$B$3*100+$A17) -> 0 | K17: =COUNTIFS(Cálculo!$A$2:$A$1001,K$5,Cálculo!$C$2:$C$1001,$B$3*100+$A17) -> 0 | L17: =SUMIFS(Cálculo!$D$2:$D$1001,Cálculo!$A$2:$A$1001,K$5,Cálculo!$C$2:$C$1001,$B$3*100+$A17)+SUMIFS(Cálculo!$H$2:$H$1001,Cálculo!$A$2:$A$1001,K$5,Cálculo!$C$2:$C$1001,$B$3*100+$A17) -> 0 | M17: =SUMIFS(Cálculo!$E$2:$E$1001,Cálculo!$A$2:$A$1001,K$5,Cálculo!$C$2:$C$1001,$B$3*100+$A17) -> 0 | N17: =SUMIFS(Cálculo!$F$2:$F$1001,Cálculo!$A$2:$A$1001,K$5,Cálculo!$C$2:$C$1001,$B$3*100+$A17) -> 0 | O17: =M17-N17 -> 0 | P17: =SUMIFS(Registro!$H$2:$H$1001,Cálculo!$A$2:$A$1001,K$5,Cálculo!$C$2:$C$1001,$B$3*100+$A17) -> 0 | Q17: =SUMIFS(Cálculo!$K$2:$K$1001,Cálculo!$A$2:$A$1001,K$5,Cálculo!$C$2:$C$1001,$B$3*100+$A17)+SUMIFS(Cálculo!$L$2:$L$1001,Cálculo!$A$2:$A$1001,K$5,Cálculo!$C$2:$C$1001,$B$3*100+$A17) -> 0 | R17: =SUMIFS(Cálculo!$N$2:$N$1001,Cálculo!$A$2:$A$1001,K$5,Cálculo!$C$2:$C$1001,$B$3*100+$A17) -> 0 | S17: =COUNTIFS(Cálculo!$A$2:$A$1001,S$5,Cálculo!$C$2:$C$1001,$B$3*100+$A17) -> 0 | T17: =SUMIFS(Cálculo!$D$2:$D$1001,Cálculo!$A$2:$A$1001,S$5,Cálculo!$C$2:$C$1001,$B$3*100+$A17)+SUMIFS(Cálculo!$H$2:$H$1001,Cálculo!$A$2:$A$1001,S$5,Cálculo!$C$2:$C$1001,$B$3*100+$A17) -> 0 | U17: =SUMIFS(Cálculo!$E$2:$E$1001,Cálculo!$A$2:$A$1001,S$5,Cálculo!$C$2:$C$1001,$B$3*100+$A17) -> 0 | V17: =SUMIFS(Cálculo!$F$2:$F$1001,Cálculo!$A$2:$A$1001,S$5,Cálculo!$C$2:$C$1001,$B$3*100+$A17) -> 0 | W17: =U17-V17 -> 0 | X17: =SUMIFS(Registro!$H$2:$H$1001,Cálculo!$A$2:$A$1001,S$5,Cálculo!$C$2:$C$1001,$B$3*100+$A17) -> 0 | Y17: =SUMIFS(Cálculo!$K$2:$K$1001,Cálculo!$A$2:$A$1001,S$5,Cálculo!$C$2:$C$1001,$B$3*100+$A17)+SUMIFS(Cálculo!$L$2:$L$1001,Cálculo!$A$2:$A$1001,S$5,Cálculo!$C$2:$C$1001,$B$3*100+$A17) -> 0 | Z17: =SUMIFS(Cálculo!$N$2:$N$1001,Cálculo!$A$2:$A$1001,S$5,Cálculo!$C$2:$C$1001,$B$3*100+$A17) -> 0 | AA17: =C17+K17+S17 -> 0 | AB17: =E17+M17+U17 -> 0 | AC17: =F17+N17+V17 -> 0 | AD17: =G17+O17+W17 -> 0 | AE17: =H17+P17+X17 -> 0 | AF17: =J17+R17+Z17 -> 0
A18: 12 | B18: Diciembre | C18: =COUNTIFS(Cálculo!$A$2:$A$1001,C$5,Cálculo!$C$2:$C$1001,$B$3*100+$A18) -> 0 | D18: =SUMIFS(Cálculo!$D$2:$D$1001,Cálculo!$A$2:$A$1001,C$5,Cálculo!$C$2:$C$1001,$B$3*100+$A18)+SUMIFS(Cálculo!$H$2:$H$1001,Cálculo!$A$2:$A$1001,C$5,Cálculo!$C$2:$C$1001,$B$3*100+$A18) -> 0 | E18: =SUMIFS(Cálculo!$E$2:$E$1001,Cálculo!$A$2:$A$1001,C$5,Cálculo!$C$2:$C$1001,$B$3*100+$A18) -> 0 | F18: =SUMIFS(Cálculo!$F$2:$F$1001,Cálculo!$A$2:$A$1001,C$5,Cálculo!$C$2:$C$1001,$B$3*100+$A18) -> 0 | G18: =E18-F18 -> 0 | H18: =SUMIFS(Registro!$H$2:$H$1001,Cálculo!$A$2:$A$1001,C$5,Cálculo!$C$2:$C$1001,$B$3*100+$A18) -> 0 | I18: =SUMIFS(Cálculo!$K$2:$K$1001,Cálculo!$A$2:$A$1001,C$5,Cálculo!$C$2:$C$1001,$B$3*100+$A18)+SUMIFS(Cálculo!$L$2:$L$1001,Cálculo!$A$2:$A$1001,C$5,Cálculo!$C$2:$C$1001,$B$3*100+$A18) -> 0 | J18: =SUMIFS(Cálculo!$N$2:$N$1001,Cálculo!$A$2:$A$1001,C$5,Cálculo!$C$2:$C$1001,$B$3*100+$A18) -> 0 | K18: =COUNTIFS(Cálculo!$A$2:$A$1001,K$5,Cálculo!$C$2:$C$1001,$B$3*100+$A18) -> 0 | L18: =SUMIFS(Cálculo!$D$2:$D$1001,Cálculo!$A$2:$A$1001,K$5,Cálculo!$C$2:$C$1001,$B$3*100+$A18)+SUMIFS(Cálculo!$H$2:$H$1001,Cálculo!$A$2:$A$1001,K$5,Cálculo!$C$2:$C$1001,$B$3*100+$A18) -> 0 | M18: =SUMIFS(Cálculo!$E$2:$E$1001,Cálculo!$A$2:$A$1001,K$5,Cálculo!$C$2:$C$1001,$B$3*100+$A18) -> 0 | N18: =SUMIFS(Cálculo!$F$2:$F$1001,Cálculo!$A$2:$A$1001,K$5,Cálculo!$C$2:$C$1001,$B$3*100+$A18) -> 0 | O18: =M18-N18 -> 0 | P18: =SUMIFS(Registro!$H$2:$H$1001,Cálculo!$A$2:$A$1001,K$5,Cálculo!$C$2:$C$1001,$B$3*100+$A18) -> 0 | Q18: =SUMIFS(Cálculo!$K$2:$K$1001,Cálculo!$A$2:$A$1001,K$5,Cálculo!$C$2:$C$1001,$B$3*100+$A18)+SUMIFS(Cálculo!$L$2:$L$1001,Cálculo!$A$2:$A$1001,K$5,Cálculo!$C$2:$C$1001,$B$3*100+$A18) -> 0 | R18: =SUMIFS(Cálculo!$N$2:$N$1001,Cálculo!$A$2:$A$1001,K$5,Cálculo!$C$2:$C$1001,$B$3*100+$A18) -> 0 | S18: =COUNTIFS(Cálculo!$A$2:$A$1001,S$5,Cálculo!$C$2:$C$1001,$B$3*100+$A18) -> 0 | T18: =SUMIFS(Cálculo!$D$2:$D$1001,Cálculo!$A$2:$A$1001,S$5,Cálculo!$C$2:$C$1001,$B$3*100+$A18)+SUMIFS(Cálculo!$H$2:$H$1001,Cálculo!$A$2:$A$1001,S$5,Cálculo!$C$2:$C$1001,$B$3*100+$A18) -> 0 | U18: =SUMIFS(Cálculo!$E$2:$E$1001,Cálculo!$A$2:$A$1001,S$5,Cálculo!$C$2:$C$1001,$B$3*100+$A18) -> 0 | V18: =SUMIFS(Cálculo!$F$2:$F$1001,Cálculo!$A$2:$A$1001,S$5,Cálculo!$C$2:$C$1001,$B$3*100+$A18) -> 0 | W18: =U18-V18 -> 0 | X18: =SUMIFS(Registro!$H$2:$H$1001,Cálculo!$A$2:$A$1001,S$5,Cálculo!$C$2:$C$1001,$B$3*100+$A18) -> 0 | Y18: =SUMIFS(Cálculo!$K$2:$K$1001,Cálculo!$A$2:$A$1001,S$5,Cálculo!$C$2:$C$1001,$B$3*100+$A18)+SUMIFS(Cálculo!$L$2:$L$1001,Cálculo!$A$2:$A$1001,S$5,Cálculo!$C$2:$C$1001,$B$3*100+$A18) -> 0 | Z18: =SUMIFS(Cálculo!$N$2:$N$1001,Cálculo!$A$2:$A$1001,S$5,Cálculo!$C$2:$C$1001,$B$3*100+$A18) -> 0 | AA18: =C18+K18+S18 -> 0 | AB18: =E18+M18+U18 -> 0 | AC18: =F18+N18+V18 -> 0 | AD18: =G18+O18+W18 -> 0 | AE18: =H18+P18+X18 -> 0 | AF18: =J18+R18+Z18 -> 0
B19: TOTAL AÑO | C19: =SUM(C7:C18) -> 26 | D19: =SUM(D7:D18) -> 1129 | E19: =SUM(E7:E18) -> 53675 | F19: =SUM(F7:F18) -> 0 | G19: =SUM(G7:G18) -> 53675 | H19: =SUM(H7:H18) -> 72319 | I19: =SUM(I7:I18) -> 69567 | J19: =SUM(J7:J18) -> 2752 | ... AF19: =SUM(AF7:AF18) -> 52800
B21: GRÁFICOS DEL AÑO

Sheet Resumen diario
A1: ="RESUMEN DIARIO — "&$B$3&" · "&$F$3&" "&$D$3 -> RESUMEN DIARIO — TDS · Octubre 2026
A2: Elige el bus, el año y el mes (celdas amarillas). Se muestra cada día del mes con los montos de ida (normal y neto) y de llegada (normal y neto). Ida neto = Monto ida − Descuento. Llegada neta = Monto llegada − Gastos − Otros gastos.
A3: Bus: | B3: TDS | C3: Año: | D3: 2026 | E3: Mes: | F3: Octubre | G3: Mes n°: | H3: =MATCH($F$3,{"Enero","Febrero","Marzo","Abril","Mayo","Junio","Julio","Agosto","Septiembre","Octubre","Noviembre","Diciembre"},0) -> 10 | J3: ⌂ Inicio
A5: VIAJES DEL MES | D5: IDA NORMAL | E5: DESCUENTO | F5: IDA NETO | G5: LLEGADA NORMAL | H5: GASTOS | I5: OTROS GASTOS | J5: LLEGADA NETA
A6: =C10 -> 26 | D6: =D10 -> 53675 | E6: =E10 -> 0 | F6: =F10 -> 53675 | G6: =G10 -> 72319 | H6: =H10 -> 3577 | I6: =I10 -> 65990 | J6: =J10 -> 2752
A8: DÍA | D8: IDA | G8: LLEGADA
A9: Fecha | B9: Día | C9: Viajes | D9: Monto ida (normal) | E9: Descuento | F9: Monto ida neto | G9: Monto llegada (normal) | H9: Gastos | I9: Otros gastos | J9: Monto llegada neto
A10: TOTAL MES | C10: =SUM(C11:C41) -> 26 | D10: =SUM(D11:D41) -> 53675 | E10: =SUM(E11:E41) -> 0 | F10: =SUM(F11:F41) -> 53675 | G10: =SUM(G11:G41) -> 72319 | H10: =SUM(H11:H41) -> 3577 | I10: =SUM(I11:I41) -> 65990 | J10: =SUM(J11:J41) -> 2752
A11: =IF(ROWS($A$11:$A11)<=DAY(EOMONTH(DATE($D$3,$H$3,1),0)),DATE($D$3,$H$3,ROWS($A$11:$A11)),"") -> 46296 | B11: =IF($A11="","",CHOOSE(WEEKDAY($A11,2),"Lunes","Martes","Miércoles","Jueves","Viernes","Sábado","Domingo")) -> Jueves | C11: =IF($A11="","",COUNTIFS(Cálculo!$A$2:$A$1001,$B$3,Cálculo!$B$2:$B$1001,$A11)) -> 1 | D11: =IF($A11="","",SUMIFS(Cálculo!$E$2:$E$1001,Cálculo!$A$2:$A$1001,$B$3,Cálculo!$B$2:$B$1001,$A11)) -> 1150 | E11: =IF($A11="","",SUMIFS(Cálculo!$F$2:$F$1001,Cálculo!$A$2:$A$1001,$B$3,Cálculo!$B$2:$B$1001,$A11)) -> 0 | F11: =IF($A11="","",D11-E11) -> 1150 | G11: =IF($A11="","",SUMIFS(Registro!$H$2:$H$1001,Cálculo!$A$2:$A$1001,$B$3,Cálculo!$B$2:$B$1001,$A11)) -> 3300 | H11: =IF($A11="","",SUMIFS(Cálculo!$K$2:$K$1001,Cálculo!$A$2:$A$1001,$B$3,Cálculo!$B$2:$B$1001,$A11)) -> 100 | I11: =IF($A11="","",SUMIFS(Cálculo!$L$2:$L$1001,Cálculo!$A$2:$A$1001,$B$3,Cálculo!$B$2:$B$1001,$A11)) -> 0 | J11: =IF($A11="","",SUMIFS(Cálculo!$N$2:$N$1001,Cálculo!$A$2:$A$1001,$B$3,Cálculo!$B$2:$B$1001,$A11)) -> 3200
A12: =IF(ROWS($A$11:$A12)<=DAY(EOMONTH(DATE($D$3,$H$3,1),0)),DATE($D$3,$H$3,ROWS($A$11:$A12)),"") -> 46297 | B12: =IF($A12="","",CHOOSE(WEEKDAY($A12,2),"Lunes","Martes","Miércoles","Jueves","Viernes","Sábado","Domingo")) -> Viernes | C12: =IF($A12="","",COUNTIFS(Cálculo!$A$2:$A$1001,$B$3,Cálculo!$B$2:$B$1001,$A12)) -> 1 | D12: =IF($A12="","",SUMIFS(Cálculo!$E$2:$E$1001,Cálculo!$A$2:$A$1001,$B$3,Cálculo!$B$2:$B$1001,$A12)) -> 1650 | E12: =IF($A12="","",SUMIFS(Cálculo!$F$2:$F$1001,Cálculo!$A$2:$A$1001,$B$3,Cálculo!$B$2:$B$1001,$A12)) -> 0 | F12: =IF($A12="","",D12-E12) -> 1650 | G12: =IF($A12="","",SUMIFS(Registro!$H$2:$H$1001,Cálculo!$A$2:$A$1001,$B$3,Cálculo!$B$2:$B$1001,$A12)) -> 4060 | H12: =IF($A12="","",SUMIFS(Cálculo!$K$2:$K$1001,Cálculo!$A$2:$A$1001,$B$3,Cálculo!$B$2:$B$1001,$A12)) -> 200 | I12: =IF($A12="","",SUMIFS(Cálculo!$L$2:$L$1001,Cálculo!$A$2:$A$1001,$B$3,Cálculo!$B$2:$B$1001,$A12)) -> 0 | J12: =IF($A12="","",SUMIFS(Cálculo!$N$2:$N$1001,Cálculo!$A$2:$A$1001,$B$3,Cálculo!$B$2:$B$1001,$A12)) -> 3860
A13: =IF(ROWS($A$11:$A13)<=DAY(EOMONTH(DATE($D$3,$H$3,1),0)),DATE($D$3,$H$3,ROWS($A$11:$A13)),"") -> 46298 | B13: =IF($A13="","",CHOOSE(WEEKDAY($A13,2),"Lunes","Martes","Miércoles","Jueves","Viernes","Sábado","Domingo")) -> Sábado | C13: =IF($A13="","",COUNTIFS(Cálculo!$A$2:$A$1001,$B$3,Cálculo!$B$2:$B$1001,$A13)) -> 1 | D13: =IF($A13="","",SUMIFS(Cálculo!$E$2:$E$1001,Cálculo!$A$2:$A$1001,$B$3,Cálculo!$B$2:$B$1001,$A13)) -> 3010 | E13: =IF($A13="","",SUMIFS(Cálculo!$F$2:$F$1001,Cálculo!$A$2:$A$1001,$B$3,Cálculo!$B$2:$B$1001,$A13)) -> 0 | F13: =IF($A13="","",D13-E13) -> 3010 | G13: =IF($A13="","",SUMIFS(Registro!$H$2:$H$1001,Cálculo!$A$2:$A$1001,$B$3,Cálculo!$B$2:$B$1001,$A13)) -> 3599 | H13: =IF($A13="","",SUMIFS(Cálculo!$K$2:$K$1001,Cálculo!$A$2:$A$1001,$B$3,Cálculo!$B$2:$B$1001,$A13)) -> 100 | I13: =IF($A13="","",SUMIFS(Cálculo!$L$2:$L$1001,Cálculo!$A$2:$A$1001,$B$3,Cálculo!$B$2:$B$1001,$A13)) -> 8400 | J13: =IF($A13="","",SUMIFS(Cálculo!$N$2:$N$1001,Cálculo!$A$2:$A$1001,$B$3,Cálculo!$B$2:$B$1001,$A13)) -> -4901
A14: =IF(ROWS($A$11:$A14)<=DAY(EOMONTH(DATE($D$3,$H$3,1),0)),DATE($D$3,$H$3,ROWS($A$11:$A14)),"") -> 46299 | B14: =IF($A14="","",CHOOSE(WEEKDAY($A14,2),"Lunes","Martes","Miércoles","Jueves","Viernes","Sábado","Domingo")) -> Domingo | C14: =IF($A14="","",COUNTIFS(Cálculo!$A$2:$A$1001,$B$3,Cálculo!$B$2:$B$1001,$A14)) -> 1 | D14: =IF($A14="","",SUMIFS(Cálculo!$E$2:$E$1001,Cálculo!$A$2:$A$1001,$B$3,Cálculo!$B$2:$B$1001,$A14)) -> 2340 | E14: =IF($A14="","",SUMIFS(Cálculo!$F$2:$F$1001,Cálculo!$A$2:$A$1001,$B$3,Cálculo!$B$2:$B$1001,$A14)) -> 0 | F14: =IF($A14="","",D14-E14) -> 2340 | G14: =IF($A14="","",SUMIFS(Registro!$H$2:$H$1001,Cálculo!$A$2:$A$1001,$B$3,Cálculo!$B$2:$B$1001,$A14)) -> 2080 | H14: =IF($A14="","",SUMIFS(Cálculo!$K$2:$K$1001,Cálculo!$A$2:$A$1001,$B$3,Cálculo!$B$2:$B$1001,$A14)) -> 140 | I14: =IF($A14="","",SUMIFS(Cálculo!$L$2:$L$1001,Cálculo!$A$2:$A$1001,$B$3,Cálculo!$B$2:$B$1001,$A14)) -> 0 | J14: =IF($A14="","",SUMIFS(Cálculo!$N$2:$N$1001,Cálculo!$A$2:$A$1001,$B$3,Cálculo!$B$2:$B$1001,$A14)) -> 1940
A15: =IF(ROWS($A$11:$A15)<=DAY(EOMONTH(DATE($D$3,$H$3,1),0)),DATE($D$3,$H$3,ROWS($A$11:$A15)),"") -> 46300 | B15: =IF($A15="","",CHOOSE(WEEKDAY($A15,2),"Lunes","Martes","Miércoles","Jueves","Viernes","Sábado","Domingo")) -> Lunes | C15: =IF($A15="","",COUNTIFS(Cálculo!$A$2:$A$1001,$B$3,Cálculo!$B$2:$B$1001,$A15)) -> 1 | D15: =IF($A15="","",SUMIFS(Cálculo!$E$2:$E$1001,Cálculo!$A$2:$A$1001,$B$3,Cálculo!$B$2:$B$1001,$A15)) -> 2200 | E15: =IF($A15="","",SUMIFS(Cálculo!$F$2:$F$1001,Cálculo!$A$2:$A$1001,$B$3,Cálculo!$B$2:$B$1001,$A15)) -> 0 | F15: =IF($A15="","",D15-E15) -> 2200 | G15: =IF($A15="","",SUMIFS(Registro!$H$2:$H$1001,Cálculo!$A$2:$A$1001,$B$3,Cálculo!$B$2:$B$1001,$A15)) -> 3300 | H15: =IF($A15="","",SUMIFS(Cálculo!$K$2:$K$1001,Cálculo!$A$2:$A$1001,$B$3,Cálculo!$B$2:$B$1001,$A15)) -> 500 | I15: =IF($A15="","",SUMIFS(Cálculo!$L$2:$L$1001,Cálculo!$A$2:$A$1001,$B$3,Cálculo!$B$2:$B$1001,$A15)) -> 7500 | J15: =IF($A15="","",SUMIFS(Cálculo!$N$2:$N$1001,Cálculo!$A$2:$A$1001,$B$3,Cálculo!$B$2:$B$1001,$A15)) -> -4700
A16: =IF(ROWS($A$11:$A16)<=DAY(EOMONTH(DATE($D$3,$H$3,1),0)),DATE($D$3,$H$3,ROWS($A$11:$A16)),"") -> 46301 | B16: =IF($A16="","",CHOOSE(WEEKDAY($A16,2),"Lunes","Martes","Miércoles","Jueves","Viernes","Sábado","Domingo")) -> Martes | C16: =IF($A16="","",COUNTIFS(Cálculo!$A$2:$A$1001,$B$3,Cálculo!$B$2:$B$1001,$A16)) -> 1 | D16: =IF($A16="","",SUMIFS(Cálculo!$E$2:$E$1001,Cálculo!$A$2:$A$1001,$B$3,Cálculo!$B$2:$B$1001,$A16)) -> 2930 | E16: =IF($A16="","",SUMIFS(Cálculo!$F$2:$F$1001,Cálculo!$A$2:$A$1001,$B$3,Cálculo!$B$2:$B$1001,$A16)) -> 0 | F16: =IF($A16="","",D16-E16) -> 2930 | G16: =IF($A16="","",SUMIFS(Registro!$H$2:$H$1001,Cálculo!$A$2:$A$1001,$B$3,Cálculo!$B$2:$B$1001,$A16)) -> 2350 | H16: =IF($A16="","",SUMIFS(Cálculo!$K$2:$K$1001,Cálculo!$A$2:$A$1001,$B$3,Cálculo!$B$2:$B$1001,$A16)) -> 100 | I16: =IF($A16="","",SUMIFS(Cálculo!$L$2:$L$1001,Cálculo!$A$2:$A$1001,$B$3,Cálculo!$B$2:$B$1001,$A16)) -> 0 | J16: =IF($A16="","",SUMIFS(Cálculo!$N$2:$N$1001,Cálculo!$A$2:$A$1001,$B$3,Cálculo!$B$2:$B$1001,$A16)) -> 2250
A17: =IF(ROWS($A$11:$A17)<=DAY(EOMONTH(DATE($D$3,$H$3,1),0)),DATE($D$3,$H$3,ROWS($A$11:$A17)),"") -> 46302 | B17: =IF($A17="","",CHOOSE(WEEKDAY($A17,2),"Lunes","Martes","Miércoles","Jueves","Viernes","Sábado","Domingo")) -> Miércoles | C17: =IF($A17="","",COUNTIFS(Cálculo!$A$2:$A$1001,$B$3,Cálculo!$B$2:$B$1001,$A17)) -> 1 | D17: =IF($A17="","",SUMIFS(Cálculo!$E$2:$E$1001,Cálculo!$A$2:$A$1001,$B$3,Cálculo!$B$2:$B$1001,$A17)) -> 1450 | E17: =IF($A17="","",SUMIFS(Cálculo!$F$2:$F$1001,Cálculo!$A$2:$A$1001,$B$3,Cálculo!$B$2:$B$1001,$A17)) -> 0 | F17: =IF($A17="","",D17-E17) -> 1450 | G17: =IF($A17="","",SUMIFS(Registro!$H$2:$H$1001,Cálculo!$A$2:$A$1001,$B$3,Cálculo!$B$2:$B$1001,$A17)) -> 2455 | H17: =IF($A17="","",SUMIFS(Cálculo!$K$2:$K$1001,Cálculo!$A$2:$A$1001,$B$3,Cálculo!$B$2:$B$1001,$A17)) -> 100 | I17: =IF($A17="","",SUMIFS(Cálculo!$L$2:$L$1001,Cálculo!$A$2:$A$1001,$B$3,Cálculo!$B$2:$B$1001,$A17)) -> 0 | J17: =IF($A17="","",SUMIFS(Cálculo!$N$2:$N$1001,Cálculo!$A$2:$A$1001,$B$3,Cálculo!$B$2:$B$1001,$A17)) -> 2355
A18: =IF(ROWS($A$11:$A18)<=DAY(EOMONTH(DATE($D$3,$H$3,1),0)),DATE($D$3,$H$3,ROWS($A$11:$A18)),"") -> 46303 | B18: =IF($A18="","",CHOOSE(WEEKDAY($A18,2),"Lunes","Martes","Miércoles","Jueves","Viernes","Sábado","Domingo")) -> Jueves | C18: =IF($A18="","",COUNTIFS(Cálculo!$A$2:$A$1001,$B$3,Cálculo!$B$2:$B$1001,$A18)) -> 1 | D18: =IF($A18="","",SUMIFS(Cálculo!$E$2:$E$1001,Cálculo!$A$2:$A$1001,$B$3,Cálculo!$B$2:$B$1001,$A18)) -> 2060 | E18: =IF($A18="","",SUMIFS(Cálculo!$F$2:$F$1001,Cálculo!$A$2:$A$1001,$B$3,Cálculo!$B$2:$B$1001,$A18)) -> 0 | F18: =IF($A18="","",D18-E18) -> 2060 | G18: =IF($A18="","",SUMIFS(Registro!$H$2:$H$1001,Cálculo!$A$2:$A$1001,$B$3,Cálculo!$B$2:$B$1001,$A18)) -> 2365 | H18: =IF($A18="","",SUMIFS(Cálculo!$K$2:$K$1001,Cálculo!$A$2:$A$1001,$B$3,Cálculo!$B$2:$B$1001,$A18)) -> 50 | I18: =IF($A18="","",SUMIFS(Cálculo!$L$2:$L$1001,Cálculo!$A$2:$A$1001,$B$3,Cálculo!$B$2:$B$1001,$A18)) -> 0 | J18: =IF($A18="","",SUMIFS(Cálculo!$N$2:$N$1001,Cálculo!$A$2:$A$1001,$B$3,Cálculo!$B$2:$B$1001,$A18)) -> 2315
A19: =IF(ROWS($A$11:$A19)<=DAY(EOMONTH(DATE($D$3,$H$3,1),0)),DATE($D$3,$H$3,ROWS($A$11:$A19)),"") -> 46304 | B19: =IF($A19="","",CHOOSE(WEEKDAY($A19,2),"Lunes","Martes","Miércoles","Jueves","Viernes","Sábado","Domingo")) -> Viernes | C19: =IF($A19="","",COUNTIFS(Cálculo!$A$2:$A$1001,$B$3,Cálculo!$B$2:$B$1001,$A19)) -> 1 | D19: =IF($A19="","",SUMIFS(Cálculo!$E$2:$E$1001,Cálculo!$A$2:$A$1001,$B$3,Cálculo!$B$2:$B$1001,$A19)) -> 2870 | E19: =IF($A19="","",SUMIFS(Cálculo!$F$2:$F$1001,Cálculo!$A$2:$A$1001,$B$3,Cálculo!$B$2:$B$1001,$A19)) -> 0 | F19: =IF($A19="","",D19-E19) -> 2870 | G19: =IF($A19="","",SUMIFS(Registro!$H$2:$H$1001,Cálculo!$A$2:$A$1001,$B$3,Cálculo!$B$2:$B$1001,$A19)) -> 2395 | H19: =IF($A19="","",SUMIFS(Cálculo!$K$2:$K$1001,Cálculo!$A$2:$A$1001,$B$3,Cálculo!$B$2:$B$1001,$A19)) -> 0 | I19: =IF($A19="","",SUMIFS(Cálculo!$L$2:$L$1001,Cálculo!$A$2:$A$1001,$B$3,Cálculo!$B$2:$B$1001,$A19)) -> 0 | J19: =IF($A19="","",SUMIFS(Cálculo!$N$2:$N$1001,Cálculo!$A$2:$A$1001,$B$3,Cálculo!$B$2:$B$1001,$A19)) -> 2395
A20: =IF(ROWS($A$11:$A20)<=DAY(EOMONTH(DATE($D$3,$H$3,1),0)),DATE($D$3,$H$3,ROWS($A$11:$A20)),"") -> 46305 | B20: =IF($A20="","",CHOOSE(WEEKDAY($A20,2),"Lunes","Martes","Miércoles","Jueves","Viernes","Sábado","Domingo")) -> Sábado | C20: =IF($A20="","",COUNTIFS(Cálculo!$A$2:$A$1001,$B$3,Cálculo!$B$2:$B$1001,$A20)) -> 2 | D20: =IF($A20="","",SUMIFS(Cálculo!$E$2:$E$1001,Cálculo!$A$2:$A$1001,$B$3,Cálculo!$B$2:$B$1001,$A20)) -> 3685 | E20: =IF($A20="","",SUMIFS(Cálculo!$F$2:$F$1001,Cálculo!$A$2:$A$1001,$B$3,Cálculo!$B$2:$B$1001,$A20)) -> 0 | F20: =IF($A20="","",D20-E20) -> 3685 | G20: =IF($A20="","",SUMIFS(Registro!$H$2:$H$1001,Cálculo!$A$2:$A$1001,$B$3,Cálculo!$B$2:$B$1001,$A20)) -> 5770 | H20: =IF($A20="","",SUMIFS(Cálculo!$K$2:$K$1001,Cálculo!$A$2:$A$1001,$B$3,Cálculo!$B$2:$B$1001,$A20)) -> 100 | I20: =IF($A20="","",SUMIFS(Cálculo!$L$2:$L$1001,Cálculo!$A$2:$A$1001,$B$3,Cálculo!$B$2:$B$1001,$A20)) -> 8380 | J20: =IF($A20="","",SUMIFS(Cálculo!$N$2:$N$1001,Cálculo!$A$2:$A$1001,$B$3,Cálculo!$B$2:$B$1001,$A20)) -> -2710
A21: =IF(ROWS($A$11:$A21)<=DAY(EOMONTH(DATE($D$3,$H$3,1),0)),DATE($D$3,$H$3,ROWS($A$11:$A21)),"") -> 46306 | B21: =IF($A21="","",CHOOSE(WEEKDAY($A21,2),"Lunes","Martes","Miércoles","Jueves","Viernes","Sábado","Domingo")) -> Domingo | C21: =IF($A21="","",COUNTIFS(Cálculo!$A$2:$A$1001,$B$3,Cálculo!$B$2:$B$1001,$A21)) -> 1 | D21: =IF($A21="","",SUMIFS(Cálculo!$E$2:$E$1001,Cálculo!$A$2:$A$1001,$B$3,Cálculo!$B$2:$B$1001,$A21)) -> 2580 | E21: =IF($A21="","",SUMIFS(Cálculo!$F$2:$F$1001,Cálculo!$A$2:$A$1001,$B$3,Cálculo!$B$2:$B$1001,$A21)) -> 0 | F21: =IF($A21="","",D21-E21) -> 2580 | G21: =IF($A21="","",SUMIFS(Registro!$H$2:$H$1001,Cálculo!$A$2:$A$1001,$B$3,Cálculo!$B$2:$B$1001,$A21)) -> 5280 | H21: =IF($A21="","",SUMIFS(Cálculo!$K$2:$K$1001,Cálculo!$A$2:$A$1001,$B$3,Cálculo!$B$2:$B$1001,$A21)) -> 130 | I21: =IF($A21="","",SUMIFS(Cálculo!$L$2:$L$1001,Cálculo!$A$2:$A$1001,$B$3,Cálculo!$B$2:$B$1001,$A21)) -> 0 | J21: =IF($A21="","",SUMIFS(Cálculo!$N$2:$N$1001,Cálculo!$A$2:$A$1001,$B$3,Cálculo!$B$2:$B$1001,$A21)) -> 5150
A22: =IF(ROWS($A$11:$A22)<=DAY(EOMONTH(DATE($D$3,$H$3,1),0)),DATE($D$3,$H$3,ROWS($A$11:$A22)),"") -> 46307 | B22: =IF($A22="","",CHOOSE(WEEKDAY($A22,2),"Lunes","Martes","Miércoles","Jueves","Viernes","Sábado","Domingo")) -> Lunes | C22: =IF($A22="","",COUNTIFS(Cálculo!$A$2:$A$1001,$B$3,Cálculo!$B$2:$B$1001,$A22)) -> 1 | D22: =IF($A22="","",SUMIFS(Cálculo!$E$2:$E$1001,Cálculo!$A$2:$A$1001,$B$3,Cálculo!$B$2:$B$1001,$A22)) -> 2220 | E22: =IF($A22="","",SUMIFS(Cálculo!$F$2:$F$1001,Cálculo!$A$2:$A$1001,$B$3,Cálculo!$B$2:$B$1001,$A22)) -> 0 | F22: =IF($A22="","",D22-E22) -> 2220 | G22: =IF($A22="","",SUMIFS(Registro!$H$2:$H$1001,Cálculo!$A$2:$A$1001,$B$3,Cálculo!$B$2:$B$1001,$A22)) -> 2855 | H22: =IF($A22="","",SUMIFS(Cálculo!$K$2:$K$1001,Cálculo!$A$2:$A$1001,$B$3,Cálculo!$B$2:$B$1001,$A22)) -> 220 | I22: =IF($A22="","",SUMIFS(Cálculo!$L$2:$L$1001,Cálculo!$A$2:$A$1001,$B$3,Cálculo!$B$2:$B$1001,$A22)) -> 8190 | J22: =IF($A22="","",SUMIFS(Cálculo!$N$2:$N$1001,Cálculo!$A$2:$A$1001,$B$3,Cálculo!$B$2:$B$1001,$A22)) -> -5555
... A41: =IF(ROWS($A$11:$A41)<=DAY(EOMONTH(DATE($D$3,$H$3,1),0)),DATE($D$3,$H$3,ROWS($A$11:$A41)),"") -> 46326 | B41: =IF($A41="","",CHOOSE(WEEKDAY($A41,2),"Lunes","Martes","Miércoles","Jueves","Viernes","Sábado","Domingo")) -> Sábado | C41: =IF($A41="","",COUNTIFS(Cálculo!$A$2:$A$1001,$B$3,Cálculo!$B$2:$B$1001,$A41)) -> 0 | D41: =IF($A41="","",SUMIFS(Cálculo!$E$2:$E$1001,Cálculo!$A$2:$A$1001,$B$3,Cálculo!$B$2:$B$1001,$A41)) -> 0 | E41: =IF($A41="","",SUMIFS(Cálculo!$F$2:$F$1001,Cálculo!$A$2:$A$1001,$B$3,Cálculo!$B$2:$B$1001,$A41)) -> 0 | F41: =IF($A41="","",D41-E41) -> 0 | G41: =IF($A41="","",SUMIFS(Registro!$H$2:$H$1001,Cálculo!$A$2:$A$1001,$B$3,Cálculo!$B$2:$B$1001,$A41)) -> 0 | H41: =IF($A41="","",SUMIFS(Cálculo!$K$2:$K$1001,Cálculo!$A$2:$A$1001,$B$3,Cálculo!$B$2:$B$1001,$A41)) -> 0 | I41: =IF($A41="","",SUMIFS(Cálculo!$L$2:$L$1001,Cálculo!$A$2:$A$1001,$B$3,Cálculo!$B$2:$B$1001,$A41)) -> 0 | J41: =IF($A41="","",SUMIFS(Cálculo!$N$2:$N$1001,Cálculo!$A$2:$A$1001,$B$3,Cálculo!$B$2:$B$1001,$A41)) -> 0

Sheet Facturas
A1: ="FACTURAS E IVA — "&$D$3&" "&$B$3&" (todos los buses)" -> FACTURAS E IVA — Octubre 2026 (todos los buses)
A2: Anota abajo cada factura que conseguiste (fecha y monto). Arriba eliges año y mes: se compara el IVA de las ventas del mes (Ida neto + Llegada normal de los 3 buses) con el IVA de las facturas de ese mes.
A3: Año: | B3: 2026 | C3: Mes: | D3: Octubre | E3: Tasa IVA: | F3: 0.13 | G3: =$B$3*100+MATCH($D$3,{"Enero","Febrero","Marzo","Abril","Mayo","Junio","Julio","Agosto","Septiembre","Octubre","Noviembre","Diciembre"},0) -> 202610 | H3: ⌂ Inicio
A5: COMPARACIÓN DEL MES | G5: IVA A PAGAR
A6: Concepto | E6: Monto | F6: ="IVA ("&TEXT($F$3*100,"0")&"%)" -> IVA (13%) | G6: =MAX(F9-F10,0) -> 30896.97
A7: Ida neto del mes (3 buses) | E7: =SUMIFS(Cálculo!$G$2:$G$1001,Cálculo!$C$2:$C$1001,$G$3) -> 106655 | F7: =E7*$F$3 -> 13865.15
A8: Llegada normal del mes (3 buses) | E8: =SUMIFS(Registro!$H$2:$H$1001,Cálculo!$C$2:$C$1001,$G$3) -> 131014 | F8: =E8*$F$3 -> 17031.82
A9: TOTAL VENTAS → IVA débito | E9: =E7+E8 -> 237669 | F9: =F7+F8 -> 30896.97 | G9: SALDO A FAVOR (crédito)
A10: ="Facturas del mes ("&COUNTIFS($A$16:$A$515,">="&DATE($B$3,MOD($G$3,100),1),$A$16:$A$515,"<="&EOMONTH(DATE($B$3,MOD($G$3,100),1),0))&") → IVA crédito" -> Facturas del mes (0) → IVA crédito | E10: =SUMIFS($E$16:$E$515,$A$16:$A$515,">="&DATE($B$3,MOD($G$3,100),1),$A$16:$A$515,"<="&EOMONTH(DATE($B$3,MOD($G$3,100),1),0)) -> 0 | F10: =E10*$F$3 -> 0 | G10: =MAX(F10-F9,0) -> 0
A11: Diferencia (ventas − facturas) | E11: =E9-E10 -> 237669 | F11: =F9-F10 -> 30896.97
A14: REGISTRO DE FACTURAS — una por fila (puedes anotar las de todos los meses; ✓ marca las del mes elegido)
A15: Fecha | B15: N° factura | C15: Proveedor / NIT | D15: Concepto | E15: Monto factura | F15: IVA (crédito) | G15: ¿Del mes? | H15: Observaciones
F16: =IF(E16="","",E16*$F$3) | G16: =IF(AND(ISNUMBER(A16),E16<>""),IF(YEAR(A16)*100+MONTH(A16)=$G$3,"✓",""),"")
F17: =IF(E17="","",E17*$F$3) | G17: =IF(AND(ISNUMBER(A17),E17<>""),IF(YEAR(A17)*100+MONTH(A17)=$G$3,"✓",""),"")
F18: =IF(E18="","",E18*$F$3) | G18: =IF(AND(ISNUMBER(A18),E18<>""),IF(YEAR(A18)*100+MONTH(A18)=$G$3,"✓",""),"")
F19: =IF(E19="","",E19*$F$3) | G19: =IF(AND(ISNUMBER(A19),E19<>""),IF(YEAR(A19)*100+MONTH(A19)=$G$3,"✓",""),"")
F20: =IF(E20="","",E20*$F$3) | G20: =IF(AND(ISNUMBER(A20),E20<>""),IF(YEAR(A20)*100+MONTH(A20)=$G$3,"✓",""),"")
F21: =IF(E21="","",E21*$F$3) | G21: =IF(AND(ISNUMBER(A21),E21<>""),IF(YEAR(A21)*100+MONTH(A21)=$G$3,"✓",""),"")
F22: =IF(E22="","",E22*$F$3) | G22: =IF(AND(ISNUMBER(A22),E22<>""),IF(YEAR(A22)*100+MONTH(A22)=$G$3,"✓",""),"")
F23: =IF(E23="","",E23*$F$3) | G23: =IF(AND(ISNUMBER(A23),E23<>""),IF(YEAR(A23)*100+MONTH(A23)=$G$3,"✓",""),"")
F24: =IF(E24="","",E24*$F$3) | G24: =IF(AND(ISNUMBER(A24),E24<>""),IF(YEAR(A24)*100+MONTH(A24)=$G$3,"✓",""),"")
F25: =IF(E25="","",E25*$F$3) | G25: =IF(AND(ISNUMBER(A25),E25<>""),IF(YEAR(A25)*100+MONTH(A25)=$G$3,"✓",""),"")
F26: =IF(E26="","",E26*$F$3) | G26: =IF(AND(ISNUMBER(A26),E26<>""),IF(YEAR(A26)*100+MONTH(A26)=$G$3,"✓",""),"")
F27: =IF(E27="","",E27*$F$3) | G27: =IF(AND(ISNUMBER(A27),E27<>""),IF(YEAR(A27)*100+MONTH(A27)=$G$3,"✓",""),"")
... F515: =IF(E515="","",E515*$F$3) | G515: =IF(AND(ISNUMBER(A515),E515<>""),IF(YEAR(A515)*100+MONTH(A515)=$G$3,"✓",""),"")

Sheet Cálculo
A1: Bus | B1: Fecha | C1: Clave mes (aaaamm) | D1: Total boletos ida | E1: Monto ida | F1: Descuento ida | G1: Monto ida neto | H1: Total boletos llegada | I1: Monto calculado llegada | J1: Verificación | K1: Total gastos | L1: Total otros gastos | M1: Total menos gastos | N1: Neto final | O1: Orden (Consulta)
A2: =IF(Registro!$A2="","",Registro!$A2) -> TDS | B2: =IF(Registro!$B2="","",Registro!$B2) -> 46296 | C2: =IF(ISNUMBER(B2),YEAR(B2)*100+MONTH(B2),"") -> 202610 | D2: =IF(Registro!$E2="","",IF(ISERROR(FIND("x",LOWER(Registro!$E2))),"-",IFERROR(SUMPRODUCT(--("0"&LEFT(TRIM(MID(SUBSTITUTE(SUBSTITUTE(SUBSTITUTE(SUBSTITUTE(SUBSTITUTE(LOWER(Registro!$E2)," ",""),CHAR(10),"|"),";","|"),"+","|"),"|",REPT(" ",LEN(Registro!$E2))),({1,2,3,4,5,6,7,8,9,10,11,12,13,14,15,16,17,18,19,20,21,22,23,24,25,26,27,28,29,30}-1)*LEN(Registro!$E2)+1,LEN(Registro!$E2))),FIND("x",TRIM(MID(SUBSTITUTE(SUBSTITUTE(SUBSTITUTE(SUBSTITUTE(SUBSTITUTE(LOWER(Registro!$E2)," ",""),CHAR(10),"|"),";","|"),"+","|"),"|",REPT(" ",LEN(Registro!$E2))),({1,2,3,4,5,6,7,8,9,10,11,12,13,14,15,16,17,18,19,20,21,22,23,24,25,26,27,28,29,30}-1)*LEN(Registro!$E2)+1,LEN(Registro!$E2)))&"x")-1))),"Revisar formato"))) -> 28 | E2: =IF(Registro!$E2="","",IF(ISERROR(FIND("x",LOWER(Registro!$E2))),"-",IFERROR(SUMPRODUCT(--("0"&LEFT(TRIM(MID(SUBSTITUTE(SUBSTITUTE(SUBSTITUTE(SUBSTITUTE(SUBSTITUTE(LOWER(Registro!$E2)," ",""),CHAR(10),"|"),";","|"),"+","|"),"|",REPT(" ",LEN(Registro!$E2))),({1,2,3,4,5,6,7,8,9,10,11,12,13,14,15,16,17,18,19,20,21,22,23,24,25,26,27,28,29,30}-1)*LEN(Registro!$E2)+1,LEN(Registro!$E2))),FIND("x",TRIM(MID(SUBSTITUTE(SUBSTITUTE(SUBSTITUTE(SUBSTITUTE(SUBSTITUTE(LOWER(Registro!$E2)," ",""),CHAR(10),"|"),";","|"),"+","|"),"|",REPT(" ",LEN(Registro!$E2))),({1,2,3,4,5,6,7,8,9,10,11,12,13,14,15,16,17,18,19,20,21,22,23,24,25,26,27,28,29,30}-1)*LEN(Registro!$E2)+1,LEN(Registro!$E2)))&"x")-1)),--("0"&MID(TRIM(MID(SUBSTITUTE(SUBSTITUTE(SUBSTITUTE(SUBSTITUTE(SUBSTITUTE(LOWER(Registro!$E2)," ",""),CHAR(10),"|"),";","|"),"+","|"),"|",REPT(" ",LEN(Registro!$E2))),({1,2,3,4,5,6,7,8,9,10,11,12,13,14,15,16,17,18,19,20,21,22,23,24,25,26,27,28,29,30}-1)*LEN(Registro!$E2)+1,LEN(Registro!$E2))),FIND("x",TRIM(MID(SUBSTITUTE(SUBSTITUTE(SUBSTITUTE(SUBSTITUTE(SUBSTITUTE(LOWER(Registro!$E2)," ",""),CHAR(10),"|"),";","|"),"+","|"),"|",REPT(" ",LEN(Registro!$E2))),({1,2,3,4,5,6,7,8,9,10,11,12,13,14,15,16,17,18,19,20,21,22,23,24,25,26,27,28,29,30}-1)*LEN(Registro!$E2)+1,LEN(Registro!$E2)))&"x")+1,20))),"Revisar formato"))) -> 1150 | F2: =IF(Registro!$F2="","",N(Registro!$F2)) | G2: =IF(AND(E2="",F2=""),"",IF(OR(E2="",ISNUMBER(E2)),N(E2)-N(F2),E2)) -> 1150 | H2: =IF(Registro!$G2="","",IF(ISERROR(FIND("x",LOWER(Registro!$G2))),"-",IFERROR(SUMPRODUCT(--("0"&LEFT(TRIM(MID(SUBSTITUTE(SUBSTITUTE(SUBSTITUTE(SUBSTITUTE(SUBSTITUTE(LOWER(Registro!$G2)," ",""),CHAR(10),"|"),";","|"),"+","|"),"|",REPT(" ",LEN(Registro!$G2))),({1,2,3,4,5,6,7,8,9,10,11,12,13,14,15,16,17,18,19,20,21,22,23,24,25,26,27,28,29,30}-1)*LEN(Registro!$G2)+1,LEN(Registro!$G2))),FIND("x",TRIM(MID(SUBSTITUTE(SUBSTITUTE(SUBSTITUTE(SUBSTITUTE(SUBSTITUTE(LOWER(Registro!$G2)," ",""),CHAR(10),"|"),";","|"),"+","|"),"|",REPT(" ",LEN(Registro!$G2))),({1,2,3,4,5,6,7,8,9,10,11,12,13,14,15,16,17,18,19,20,21,22,23,24,25,26,27,28,29,30}-1)*LEN(Registro!$G2)+1,LEN(Registro!$G2)))&"x")-1))),"Revisar formato"))) -> 1 | I2: =IF(Registro!$G2="","",IF(ISERROR(FIND("x",LOWER(Registro!$G2))),N(Registro!$H2),IFERROR(SUMPRODUCT(--("0"&LEFT(TRIM(MID(SUBSTITUTE(SUBSTITUTE(SUBSTITUTE(SUBSTITUTE(SUBSTITUTE(LOWER(Registro!$G2)," ",""),CHAR(10),"|"),";","|"),"+","|"),"|",REPT(" ",LEN(Registro!$G2))),({1,2,3,4,5,6,7,8,9,10,11,12,13,14,15,16,17,18,19,20,21,22,23,24,25,26,27,28,29,30}-1)*LEN(Registro!$G2)+1,LEN(Registro!$G2))),FIND("x",TRIM(MID(SUBSTITUTE(SUBSTITUTE(SUBSTITUTE(SUBSTITUTE(SUBSTITUTE(LOWER(Registro!$G2)," ",""),CHAR(10),"|"),";","|"),"+","|"),"|",REPT(" ",LEN(Registro!$G2))),({1,2,3,4,5,6,7,8,9,10,11,12,13,14,15,16,17,18,19,20,21,22,23,24,25,26,27,28,29,30}-1)*LEN(Registro!$G2)+1,LEN(Registro!$G2)))&"x")-1)),--("0"&MID(TRIM(MID(SUBSTITUTE(SUBSTITUTE(SUBSTITUTE(SUBSTITUTE(SUBSTITUTE(LOWER(Registro!$G2)," ",""),CHAR(10),"|"),";","|"),"+","|"),"|",REPT(" ",LEN(Registro!$G2))),({1,2,3,4,5,6,7,8,9,10,11,12,13,14,15,16,17,18,19,20,21,22,23,24,25,26,27,28,29,30}-1)*LEN(Registro!$G2)+1,LEN(Registro!$G2))),FIND("x",TRIM(MID(SUBSTITUTE(SUBSTITUTE(SUBSTITUTE(SUBSTITUTE(SUBSTITUTE(LOWER(Registro!$G2)," ",""),CHAR(10),"|"),";","|"),"+","|"),"|",REPT(" ",LEN(Registro!$G2))),({1,2,3,4,5,6,7,8,9,10,11,12,13,14,15,16,17,18,19,20,21,22,23,24,25,26,27,28,29,30}-1)*LEN(Registro!$G2)+1,LEN(Registro!$G2)))&"x")+1,20))),"Revisar formato"))) -> 3300 | J2: =IF(AND(Registro!$E2="",Registro!$G2=""),"",IF(NOT(AND(ISNUMBER(I2),ISNUMBER(Registro!$H2))),"",IF(I2<Registro!$H2,"FALTA BOLETOS",IF(I2=Registro!$H2,"CONFORME","DIFERENCIA")))) -> CONFORME | K2: =IF(Registro!$I2="","",IFERROR(SUMPRODUCT(--("0"&TRIM(RIGHT(SUBSTITUTE(TRIM(MID(SUBSTITUTE(SUBSTITUTE(Registro!$I2,";",CHAR(10)),CHAR(10),REPT(" ",LEN(Registro!$I2))),({1,2,3,4,5,6,7,8,9,10,11,12,13,14,15,16,17,18,19,20,21,22,23,24,25,26,27,28,29,30}-1)*LEN(Registro!$I2)+1,LEN(Registro!$I2)))," ",REPT(" ",50)),50)))),"Revisar formato")) -> 100 | L2: =IF(Registro!$J2="","",IFERROR(SUMPRODUCT(--("0"&TRIM(RIGHT(SUBSTITUTE(TRIM(MID(SUBSTITUTE(SUBSTITUTE(Registro!$J2,";",CHAR(10)),CHAR(10),REPT(" ",LEN(Registro!$J2))),({1,2,3,4,5,6,7,8,9,10,11,12,13,14,15,16,17,18,19,20,21,22,23,24,25,26,27,28,29,30}-1)*LEN(Registro!$J2)+1,LEN(Registro!$J2)))," ",REPT(" ",50)),50)))),"Revisar formato")) | M2: =IF(AND(Registro!$H2="",Registro!$I2=""),"",IF(AND(ISTEXT(K2),K2<>""),"Revisar formato",N(Registro!$H2)-N(K2))) -> 3200 | N2: =IF(M2="","",IF(OR(M2="Revisar formato",AND(ISTEXT(L2),L2<>"")),"Revisar formato",M2-N(L2))) -> 3200 | O2: =IF(AND(A2=Consulta!$B$3,C2=Consulta!$H$3),B2*10000+ROW(),"") -> 462960002
A3: =IF(Registro!$A3="","",Registro!$A3) -> TDS | B3: =IF(Registro!$B3="","",Registro!$B3) -> 46297 | C3: =IF(ISNUMBER(B3),YEAR(B3)*100+MONTH(B3),"") -> 202610 | D3: =IF(Registro!$E3="","",IF(ISERROR(FIND("x",LOWER(Registro!$E3))),"-",IFERROR(SUMPRODUCT(--("0"&LEFT(TRIM(MID(SUBSTITUTE(SUBSTITUTE(SUBSTITUTE(SUBSTITUTE(SUBSTITUTE(LOWER(Registro!$E3)," ",""),CHAR(10),"|"),";","|"),"+","|"),"|",REPT(" ",LEN(Registro!$E3))),({1,2,3,4,5,6,7,8,9,10,11,12,13,14,15,16,17,18,19,20,21,22,23,24,25,26,27,28,29,30}-1)*LEN(Registro!$E3)+1,LEN(Registro!$E3))),FIND("x",TRIM(MID(SUBSTITUTE(SUBSTITUTE(SUBSTITUTE(SUBSTITUTE(SUBSTITUTE(LOWER(Registro!$E3)," ",""),CHAR(10),"|"),";","|"),"+","|"),"|",REPT(" ",LEN(Registro!$E3))),({1,2,3,4,5,6,7,8,9,10,11,12,13,14,15,16,17,18,19,20,21,22,23,24,25,26,27,28,29,30}-1)*LEN(Registro!$E3)+1,LEN(Registro!$E3)))&"x")-1))),"Revisar formato"))) -> 35 | E3: =IF(Registro!$E3="","",IF(ISERROR(FIND("x",LOWER(Registro!$E3))),"-",IFERROR(SUMPRODUCT(--("0"&LEFT(TRIM(MID(SUBSTITUTE(SUBSTITUTE(SUBSTITUTE(SUBSTITUTE(SUBSTITUTE(LOWER(Registro!$E3)," ",""),CHAR(10),"|"),";","|"),"+","|"),"|",REPT(" ",LEN(Registro!$E3))),({1,2,3,4,5,6,7,8,9,10,11,12,13,14,15,16,17,18,19,20,21,22,23,24,25,26,27,28,29,30}-1)*LEN(Registro!$E3)+1,LEN(Registro!$E3))),FIND("x",TRIM(MID(SUBSTITUTE(SUBSTITUTE(SUBSTITUTE(SUBSTITUTE(SUBSTITUTE(LOWER(Registro!$E3)," ",""),CHAR(10),"|"),";","|"),"+","|"),"|",REPT(" ",LEN(Registro!$E3))),({1,2,3,4,5,6,7,8,9,10,11,12,13,14,15,16,17,18,19,20,21,22,23,24,25,26,27,28,29,30}-1)*LEN(Registro!$E3)+1,LEN(Registro!$E3)))&"x")-1)),--("0"&MID(TRIM(MID(SUBSTITUTE(SUBSTITUTE(SUBSTITUTE(SUBSTITUTE(SUBSTITUTE(LOWER(Registro!$E3)," ",""),CHAR(10),"|"),";","|"),"+","|"),"|",REPT(" ",LEN(Registro!$E3))),({1,2,3,4,5,6,7,8,9,10,11,12,13,14,15,16,17,18,19,20,21,22,23,24,25,26,27,28,29,30}-1)*LEN(Registro!$E3)+1,LEN(Registro!$E3))),FIND("x",TRIM(MID(SUBSTITUTE(SUBSTITUTE(SUBSTITUTE(SUBSTITUTE(SUBSTITUTE(LOWER(Registro!$E3)," ",""),CHAR(10),"|"),";","|"),"+","|"),"|",REPT(" ",LEN(Registro!$E3))),({1,2,3,4,5,6,7,8,9,10,11,12,13,14,15,16,17,18,19,20,21,22,23,24,25,26,27,28,29,30}-1)*LEN(Registro!$E3)+1,LEN(Registro!$E3)))&"x")+1,20))),"Revisar formato"))) -> 1650 | F3: =IF(Registro!$F3="","",N(Registro!$F3)) | G3: =IF(AND(E3="",F3=""),"",IF(OR(E3="",ISNUMBER(E3)),N(E3)-N(F3),E3)) -> 1650 | H3: =IF(Registro!$G3="","",IF(ISERROR(FIND("x",LOWER(Registro!$G3))),"-",IFERROR(SUMPRODUCT(--("0"&LEFT(TRIM(MID(SUBSTITUTE(SUBSTITUTE(SUBSTITUTE(SUBSTITUTE(SUBSTITUTE(LOWER(Registro!$G3)," ",""),CHAR(10),"|"),";","|"),"+","|"),"|",REPT(" ",LEN(Registro!$G3))),({1,2,3,4,5,6,7,8,9,10,11,12,13,14,15,16,17,18,19,20,21,22,23,24,25,26,27,28,29,30}-1)*LEN(Registro!$G3)+1,LEN(Registro!$G3))),FIND("x",TRIM(MID(SUBSTITUTE(SUBSTITUTE(SUBSTITUTE(SUBSTITUTE(SUBSTITUTE(LOWER(Registro!$G3)," ",""),CHAR(10),"|"),";","|"),"+","|"),"|",REPT(" ",LEN(Registro!$G3))),({1,2,3,4,5,6,7,8,9,10,11,12,13,14,15,16,17,18,19,20,21,22,23,24,25,26,27,28,29,30}-1)*LEN(Registro!$G3)+1,LEN(Registro!$G3)))&"x")-1))),"Revisar formato"))) -> 1 | I3: =IF(Registro!$G3="","",IF(ISERROR(FIND("x",LOWER(Registro!$G3))),N(Registro!$H3),IFERROR(SUMPRODUCT(--("0"&LEFT(TRIM(MID(SUBSTITUTE(SUBSTITUTE(SUBSTITUTE(SUBSTITUTE(SUBSTITUTE(LOWER(Registro!$G3)," ",""),CHAR(10),"|"),";","|"),"+","|"),"|",REPT(" ",LEN(Registro!$G3))),({1,2,3,4,5,6,7,8,9,10,11,12,13,14,15,16,17,18,19,20,21,22,23,24,25,26,27,28,29,30}-1)*LEN(Registro!$G3)+1,LEN(Registro!$G3))),FIND("x",TRIM(MID(SUBSTITUTE(SUBSTITUTE(SUBSTITUTE(SUBSTITUTE(SUBSTITUTE(LOWER(Registro!$G3)," ",""),CHAR(10),"|"),";","|"),"+","|"),"|",REPT(" ",LEN(Registro!$G3))),({1,2,3,4,5,6,7,8,9,10,11,12,13,14,15,16,17,18,19,20,21,22,23,24,25,26,27,28,29,30}-1)*LEN(Registro!$G3)+1,LEN(Registro!$G3)))&"x")-1)),--("0"&MID(TRIM(MID(SUBSTITUTE(SUBSTITUTE(SUBSTITUTE(SUBSTITUTE(SUBSTITUTE(LOWER(Registro!$G3)," ",""),CHAR(10),"|"),";","|"),"+","|"),"|",REPT(" ",LEN(Registro!$G3))),({1,2,3,4,5,6,7,8,9,10,11,12,13,14,15,16,17,18,19,20,21,22,23,24,25,26,27,28,29,30}-1)*LEN(Registro!$G3)+1,LEN(Registro!$G3))),FIND("x",TRIM(MID(SUBSTITUTE(SUBSTITUTE(SUBSTITUTE(SUBSTITUTE(SUBSTITUTE(LOWER(Registro!$G3)," ",""),CHAR(10),"|"),";","|"),"+","|"),"|",REPT(" ",LEN(Registro!$G3))),({1,2,3,4,5,6,7,8,9,10,11,12,13,14,15,16,17,18,19,20,21,22,23,24,25,26,27,28,29,30}-1)*LEN(Registro!$G3)+1,LEN(Registro!$G3)))&"x")+1,20))),"Revisar formato"))) -> 4060 | J3: =IF(AND(Registro!$E3="",Registro!$G3=""),"",IF(NOT(AND(ISNUMBER(I3),ISNUMBER(Registro!$H3))),"",IF(I3<Registro!$H3,"FALTA BOLETOS",IF(I3=Registro!$H3,"CONFORME","DIFERENCIA")))) -> CONFORME | K3: =IF(Registro!$I3="","",IFERROR(SUMPRODUCT(--("0"&TRIM(RIGHT(SUBSTITUTE(TRIM(MID(SUBSTITUTE(SUBSTITUTE(Registro!$I3,";",CHAR(10)),CHAR(10),REPT(" ",LEN(Registro!$I3))),({1,2,3,4,5,6,7,8,9,10,11,12,13,14,15,16,17,18,19,20,21,22,23,24,25,26,27,28,29,30}-1)*LEN(Registro!$I3)+1,LEN(Registro!$I3)))," ",REPT(" ",50)),50)))),"Revisar formato")) -> 200 | L3: =IF(Registro!$J3="","",IFERROR(SUMPRODUCT(--("0"&TRIM(RIGHT(SUBSTITUTE(TRIM(MID(SUBSTITUTE(SUBSTITUTE(Registro!$J3,";",CHAR(10)),CHAR(10),REPT(" ",LEN(Registro!$J3))),({1,2,3,4,5,6,7,8,9,10,11,12,13,14,15,16,17,18,19,20,21,22,23,24,25,26,27,28,29,30}-1)*LEN(Registro!$J3)+1,LEN(Registro!$J3)))," ",REPT(" ",50)),50)))),"Revisar formato")) | M3: =IF(AND(Registro!$H3="",Registro!$I3=""),"",IF(AND(ISTEXT(K3),K3<>""),"Revisar formato",N(Registro!$H3)-N(K3))) -> 3860 | N3: =IF(M3="","",IF(OR(M3="Revisar formato",AND(ISTEXT(L3),L3<>"")),"Revisar formato",M3-N(L3))) -> 3860 | O3: =IF(AND(A3=Consulta!$B$3,C3=Consulta!$H$3),B3*10000+ROW(),"") -> 462970003
A4: =IF(Registro!$A4="","",Registro!$A4) -> TDS | B4: =IF(Registro!$B4="","",Registro!$B4) -> 46298 | C4: =IF(ISNUMBER(B4),YEAR(B4)*100+MONTH(B4),"") -> 202610 | D4: =IF(Registro!$E4="","",IF(ISERROR(FIND("x",LOWER(Registro!$E4))),"-",IFERROR(SUMPRODUCT(--("0"&LEFT(TRIM(MID(SUBSTITUTE(SUBSTITUTE(SUBSTITUTE(SUBSTITUTE(SUBSTITUTE(LOWER(Registro!$E4)," ",""),CHAR(10),"|"),";","|"),"+","|"),"|",REPT(" ",LEN(Registro!$E4))),({1,2,3,4,5,6,7,8,9,10,11,12,13,14,15,16,17,18,19,20,21,22,23,24,25,26,27,28,29,30}-1)*LEN(Registro!$E4)+1,LEN(Registro!$E4))),FIND("x",TRIM(MID(SUBSTITUTE(SUBSTITUTE(SUBSTITUTE(SUBSTITUTE(SUBSTITUTE(LOWER(Registro!$E4)," ",""),CHAR(10),"|"),";","|"),"+","|"),"|",REPT(" ",LEN(Registro!$E4))),({1,2,3,4,5,6,7,8,9,10,11,12,13,14,15,16,17,18,19,20,21,22,23,24,25,26,27,28,29,30}-1)*LEN(Registro!$E4)+1,LEN(Registro!$E4)))&"x")-1))),"Revisar formato"))) -> 55 | E4: =IF(Registro!$E4="","",IF(ISERROR(FIND("x",LOWER(Registro!$E4))),"-",IFERROR(SUMPRODUCT(--("0"&LEFT(TRIM(MID(SUBSTITUTE(SUBSTITUTE(SUBSTITUTE(SUBSTITUTE(SUBSTITUTE(LOWER(Registro!$E4)," ",""),CHAR(10),"|"),";","|"),"+","|"),"|",REPT(" ",LEN(Registro!$E4))),({1,2,3,4,5,6,7,8,9,10,11,12,13,14,15,16,17,18,19,20,21,22,23,24,25,26,27,28,29,30}-1)*LEN(Registro!$E4)+1,LEN(Registro!$E4))),FIND("x",TRIM(MID(SUBSTITUTE(SUBSTITUTE(SUBSTITUTE(SUBSTITUTE(SUBSTITUTE(LOWER(Registro!$E4)," ",""),CHAR(10),"|"),";","|"),"+","|"),"|",REPT(" ",LEN(Registro!$E4))),({1,2,3,4,5,6,7,8,9,10,11,12,13,14,15,16,17,18,19,20,21,22,23,24,25,26,27,28,29,30}-1)*LEN(Registro!$E4)+1,LEN(Registro!$E4)))&"x")-1)),--("0"&MID(TRIM(MID(SUBSTITUTE(SUBSTITUTE(SUBSTITUTE(SUBSTITUTE(SUBSTITUTE(LOWER(Registro!$E4)," ",""),CHAR(10),"|"),";","|"),"+","|"),"|",REPT(" ",LEN(Registro!$E4))),({1,2,3,4,5,6,7,8,9,10,11,12,13,14,15,16,17,18,19,20,21,22,23,24,25,26,27,28,29,30}-1)*LEN(Registro!$E4)+1,LEN(Registro!$E4))),FIND("x",TRIM(MID(SUBSTITUTE(SUBSTITUTE(SUBSTITUTE(SUBSTITUTE(SUBSTITUTE(LOWER(Registro!$E4)," ",""),CHAR(10),"|"),";","|"),"+","|"),"|",REPT(" ",LEN(Registro!$E4))),({1,2,3,4,5,6,7,8,9,10,11,12,13,14,15,16,17,18,19,20,21,22,23,24,25,26,27,28,29,30}-1)*LEN(Registro!$E4)+1,LEN(Registro!$E4)))&"x")+1,20))),"Revisar formato"))) -> 3010 | F4: =IF(Registro!$F4="","",N(Registro!$F4)) | G4: =IF(AND(E4="",F4=""),"",IF(OR(E4="",ISNUMBER(E4)),N(E4)-N(F4),E4)) -> 3010 | H4: =IF(Registro!$G4="","",IF(ISERROR(FIND("x",LOWER(Registro!$G4))),"-",IFERROR(SUMPRODUCT(--("0"&LEFT(TRIM(MID(SUBSTITUTE(SUBSTITUTE(SUBSTITUTE(SUBSTITUTE(SUBSTITUTE(LOWER(Registro!$G4)," ",""),CHAR(10),"|"),";","|"),"+","|"),"|",REPT(" ",LEN(Registro!$G4))),({1,2,3,4,5,6,7,8,9,10,11,12,13,14,15,16,17,18,19,20,21,22,23,24,25,26,27,28,29,30}-1)*LEN(Registro!$G4)+1,LEN(Registro!$G4))),FIND("x",TRIM(MID(SUBSTITUTE(SUBSTITUTE(SUBSTITUTE(SUBSTITUTE(SUBSTITUTE(LOWER(Registro!$G4)," ",""),CHAR(10),"|"),";","|"),"+","|"),"|",REPT(" ",LEN(Registro!$G4))),({1,2,3,4,5,6,7,8,9,10,11,12,13,14,15,16,17,18,19,20,21,22,23,24,25,26,27,28,29,30}-1)*LEN(Registro!$G4)+1,LEN(Registro!$G4)))&"x")-1))),"Revisar formato"))) -> 1 | I4: =IF(Registro!$G4="","",IF(ISERROR(FIND("x",LOWER(Registro!$G4))),N(Registro!$H4),IFERROR(SUMPRODUCT(--("0"&LEFT(TRIM(MID(SUBSTITUTE(SUBSTITUTE(SUBSTITUTE(SUBSTITUTE(SUBSTITUTE(LOWER(Registro!$G4)," ",""),CHAR(10),"|"),";","|"),"+","|"),"|",REPT(" ",LEN(Registro!$G4))),({1,2,3,4,5,6,7,8,9,10,11,12,13,14,15,16,17,18,19,20,21,22,23,24,25,26,27,28,29,30}-1)*LEN(Registro!$G4)+1,LEN(Registro!$G4))),FIND("x",TRIM(MID(SUBSTITUTE(SUBSTITUTE(SUBSTITUTE(SUBSTITUTE(SUBSTITUTE(LOWER(Registro!$G4)," ",""),CHAR(10),"|"),";","|"),"+","|"),"|",REPT(" ",LEN(Registro!$G4))),({1,2,3,4,5,6,7,8,9,10,11,12,13,14,15,16,17,18,19,20,21,22,23,24,25,26,27,28,29,30}-1)*LEN(Registro!$G4)+1,LEN(Registro!$G4)))&"x")-1)),--("0"&MID(TRIM(MID(SUBSTITUTE(SUBSTITUTE(SUBSTITUTE(SUBSTITUTE(SUBSTITUTE(LOWER(Registro!$G4)," ",""),CHAR(10),"|"),";","|"),"+","|"),"|",REPT(" ",LEN(Registro!$G4))),({1,2,3,4,5,6,7,8,9,10,11,12,13,14,15,16,17,18,19,20,21,22,23,24,25,26,27,28,29,30}-1)*LEN(Registro!$G4)+1,LEN(Registro!$G4))),FIND("x",TRIM(MID(SUBSTITUTE(SUBSTITUTE(SUBSTITUTE(SUBSTITUTE(SUBSTITUTE(LOWER(Registro!$G4)," ",""),CHAR(10),"|"),";","|"),"+","|"),"|",REPT(" ",LEN(Registro!$G4))),({1,2,3,4,5,6,7,8,9,10,11,12,13,14,15,16,17,18,19,20,21,22,23,24,25,26,27,28,29,30}-1)*LEN(Registro!$G4)+1,LEN(Registro!$G4)))&"x")+1,20))),"Revisar formato"))) -> 3599 | J4: =IF(AND(Registro!$E4="",Registro!$G4=""),"",IF(NOT(AND(ISNUMBER(I4),ISNUMBER(Registro!$H4))),"",IF(I4<Registro!$H4,"FALTA BOLETOS",IF(I4=Registro!$H4,"CONFORME","DIFERENCIA")))) -> CONFORME | K4: =IF(Registro!$I4="","",IFERROR(SUMPRODUCT(--("0"&TRIM(RIGHT(SUBSTITUTE(TRIM(MID(SUBSTITUTE(SUBSTITUTE(Registro!$I4,";",CHAR(10)),CHAR(10),REPT(" ",LEN(Registro!$I4))),({1,2,3,4,5,6,7,8,9,10,11,12,13,14,15,16,17,18,19,20,21,22,23,24,25,26,27,28,29,30}-1)*LEN(Registro!$I4)+1,LEN(Registro!$I4)))," ",REPT(" ",50)),50)))),"Revisar formato")) -> 100 | L4: =IF(Registro!$J4="","",IFERROR(SUMPRODUCT(--("0"&TRIM(RIGHT(SUBSTITUTE(TRIM(MID(SUBSTITUTE(SUBSTITUTE(Registro!$J4,";",CHAR(10)),CHAR(10),REPT(" ",LEN(Registro!$J4))),({1,2,3,4,5,6,7,8,9,10,11,12,13,14,15,16,17,18,19,20,21,22,23,24,25,26,27,28,29,30}-1)*LEN(Registro!$J4)+1,LEN(Registro!$J4)))," ",REPT(" ",50)),50)))),"Revisar formato")) -> 8400 | M4: =IF(AND(Registro!$H4="",Registro!$I4=""),"",IF(AND(ISTEXT(K4),K4<>""),"Revisar formato",N(Registro!$H4)-N(K4))) -> 3499 | N4: =IF(M4="","",IF(OR(M4="Revisar formato",AND(ISTEXT(L4),L4<>"")),"Revisar formato",M4-N(L4))) -> -4901 | O4: =IF(AND(A4=Consulta!$B$3,C4=Consulta!$H$3),B4*10000+ROW(),"") -> 462980004
A5: =IF(Registro!$A5="","",Registro!$A5) -> TDS | B5: =IF(Registro!$B5="","",Registro!$B5) -> 46299 | C5: =IF(ISNUMBER(B5),YEAR(B5)*100+MONTH(B5),"") -> 202610 | D5: =IF(Registro!$E5="","",IF(ISERROR(FIND("x",LOWER(Registro!$E5))),"-",IFERROR(SUMPRODUCT(--("0"&LEFT(TRIM(MID(SUBSTITUTE(SUBSTITUTE(SUBSTITUTE(SUBSTITUTE(SUBSTITUTE(LOWER(Registro!$E5)," ",""),CHAR(10),"|"),";","|"),"+","|"),"|",REPT(" ",LEN(Registro!$E5))),({1,2,3,4,5,6,7,8,9,10,11,12,13,14,15,16,17,18,19,20,21,22,23,24,25,26,27,28,29,30}-1)*LEN(Registro!$E5)+1,LEN(Registro!$E5))),FIND("x",TRIM(MID(SUBSTITUTE(SUBSTITUTE(SUBSTITUTE(SUBSTITUTE(SUBSTITUTE(LOWER(Registro!$E5)," ",""),CHAR(10),"|"),";","|"),"+","|"),"|",REPT(" ",LEN(Registro!$E5))),({1,2,3,4,5,6,7,8,9,10,11,12,13,14,15,16,17,18,19,20,21,22,23,24,25,26,27,28,29,30}-1)*LEN(Registro!$E5)+1,LEN(Registro!$E5)))&"x")-1))),"Revisar formato"))) -> 54 | E5: =IF(Registro!$E5="","",IF(ISERROR(FIND("x",LOWER(Registro!$E5))),"-",IFERROR(SUMPRODUCT(--("0"&LEFT(TRIM(MID(SUBSTITUTE(SUBSTITUTE(SUBSTITUTE(SUBSTITUTE(SUBSTITUTE(LOWER(Registro!$E5)," ",""),CHAR(10),"|"),";","|"),"+","|"),"|",REPT(" ",LEN(Registro!$E5))),({1,2,3,4,5,6,7,8,9,10,11,12,13,14,15,16,17,18,19,20,21,22,23,24,25,26,27,28,29,30}-1)*LEN(Registro!$E5)+1,LEN(Registro!$E5))),FIND("x",TRIM(MID(SUBSTITUTE(SUBSTITUTE(SUBSTITUTE(SUBSTITUTE(SUBSTITUTE(LOWER(Registro!$E5)," ",""),CHAR(10),"|"),";","|"),"+","|"),"|",REPT(" ",LEN(Registro!$E5))),({1,2,3,4,5,6,7,8,9,10,11,12,13,14,15,16,17,18,19,20,21,22,23,24,25,26,27,28,29,30}-1)*LEN(Registro!$E5)+1,LEN(Registro!$E5)))&"x")-1)),--("0"&MID(TRIM(MID(SUBSTITUTE(SUBSTITUTE(SUBSTITUTE(SUBSTITUTE(SUBSTITUTE(LOWER(Registro!$E5)," ",""),CHAR(10),"|"),";","|"),"+","|"),"|",REPT(" ",LEN(Registro!$E5))),({1,2,3,4,5,6,7,8,9,10,11,12,13,14,15,16,17,18,19,20,21,22,23,24,25,26,27,28,29,30}-1)*LEN(Registro!$E5)+1,LEN(Registro!$E5))),FIND("x",TRIM(MID(SUBSTITUTE(SUBSTITUTE(SUBSTITUTE(SUBSTITUTE(SUBSTITUTE(LOWER(Registro!$E5)," ",""),CHAR(10),"|"),";","|"),"+","|"),"|",REPT(" ",LEN(Registro!$E5))),({1,2,3,4,5,6,7,8,9,10,11,12,13,14,15,16,17,18,19,20,21,22,23,24,25,26,27,28,29,30}-1)*LEN(Registro!$E5)+1,LEN(Registro!$E5)))&"x")+1,20))),"Revisar formato"))) -> 2340 | F5: =IF(Registro!$F5="","",N(Registro!$F5)) | G5: =IF(AND(E5="",F5=""),"",IF(OR(E5="",ISNUMBER(E5)),N(E5)-N(F5),E5)) -> 2340 | H5: =IF(Registro!$G5="","",IF(ISERROR(FIND("x",LOWER(Registro!$G5))),"-",IFERROR(SUMPRODUCT(--("0"&LEFT(TRIM(MID(SUBSTITUTE(SUBSTITUTE(SUBSTITUTE(SUBSTITUTE(SUBSTITUTE(LOWER(Registro!$G5)," ",""),CHAR(10),"|"),";","|"),"+","|"),"|",REPT(" ",LEN(Registro!$G5))),({1,2,3,4,5,6,7,8,9,10,11,12,13,14,15,16,17,18,19,20,21,22,23,24,25,26,27,28,29,30}-1)*LEN(Registro!$G5)+1,LEN(Registro!$G5))),FIND("x",TRIM(MID(SUBSTITUTE(SUBSTITUTE(SUBSTITUTE(SUBSTITUTE(SUBSTITUTE(LOWER(Registro!$G5)," ",""),CHAR(10),"|"),";","|"),"+","|"),"|",REPT(" ",LEN(Registro!$G5))),({1,2,3,4,5,6,7,8,9,10,11,12,13,14,15,16,17,18,19,20,21,22,23,24,25,26,27,28,29,30}-1)*LEN(Registro!$G5)+1,LEN(Registro!$G5)))&"x")-1))),"Revisar formato"))) -> 1 | I5: =IF(Registro!$G5="","",IF(ISERROR(FIND("x",LOWER(Registro!$G5))),N(Registro!$H5),IFERROR(SUMPRODUCT(--("0"&LEFT(TRIM(MID(SUBSTITUTE(SUBSTITUTE(SUBSTITUTE(SUBSTITUTE(SUBSTITUTE(LOWER(Registro!$G5)," ",""),CHAR(10),"|"),";","|"),"+","|"),"|",REPT(" ",LEN(Registro!$G5))),({1,2,3,4,5,6,7,8,9,10,11,12,13,14,15,16,17,18,19,20,21,22,23,24,25,26,27,28,29,30}-1)*LEN(Registro!$G5)+1,LEN(Registro!$G5))),FIND("x",TRIM(MID(SUBSTITUTE(SUBSTITUTE(SUBSTITUTE(SUBSTITUTE(SUBSTITUTE(LOWER(Registro!$G5)," ",""),CHAR(10),"|"),";","|"),"+","|"),"|",REPT(" ",LEN(Registro!$G5))),({1,2,3,4,5,6,7,8,9,10,11,12,13,14,15,16,17,18,19,20,21,22,23,24,25,26,27,28,29,30}-1)*LEN(Registro!$G5)+1,LEN(Registro!$G5)))&"x")-1)),--("0"&MID(TRIM(MID(SUBSTITUTE(SUBSTITUTE(SUBSTITUTE(SUBSTITUTE(SUBSTITUTE(LOWER(Registro!$G5)," ",""),CHAR(10),"|"),";","|"),"+","|"),"|",REPT(" ",LEN(Registro!$G5))),({1,2,3,4,5,6,7,8,9,10,11,12,13,14,15,16,17,18,19,20,21,22,23,24,25,26,27,28,29,30}-1)*LEN(Registro!$G5)+1,LEN(Registro!$G5))),FIND("x",TRIM(MID(SUBSTITUTE(SUBSTITUTE(SUBSTITUTE(SUBSTITUTE(SUBSTITUTE(LOWER(Registro!$G5)," ",""),CHAR(10),"|"),";","|"),"+","|"),"|",REPT(" ",LEN(Registro!$G5))),({1,2,3,4,5,6,7,8,9,10,11,12,13,14,15,16,17,18,19,20,21,22,23,24,25,26,27,28,29,30}-1)*LEN(Registro!$G5)+1,LEN(Registro!$G5)))&"x")+1,20))),"Revisar formato"))) -> 2080 | J5: =IF(AND(Registro!$E5="",Registro!$G5=""),"",IF(NOT(AND(ISNUMBER(I5),ISNUMBER(Registro!$H5))),"",IF(I5<Registro!$H5,"FALTA BOLETOS",IF(I5=Registro!$H5,"CONFORME","DIFERENCIA")))) -> CONFORME | K5: =IF(Registro!$I5="","",IFERROR(SUMPRODUCT(--("0"&TRIM(RIGHT(SUBSTITUTE(TRIM(MID(SUBSTITUTE(SUBSTITUTE(Registro!$I5,";",CHAR(10)),CHAR(10),REPT(" ",LEN(Registro!$I5))),({1,2,3,4,5,6,7,8,9,10,11,12,13,14,15,16,17,18,19,20,21,22,23,24,25,26,27,28,29,30}-1)*LEN(Registro!$I5)+1,LEN(Registro!$I5)))," ",REPT(" ",50)),50)))),"Revisar formato")) -> 140 | L5: =IF(Registro!$J5="","",IFERROR(SUMPRODUCT(--("0"&TRIM(RIGHT(SUBSTITUTE(TRIM(MID(SUBSTITUTE(SUBSTITUTE(Registro!$J5,";",CHAR(10)),CHAR(10),REPT(" ",LEN(Registro!$J5))),({1,2,3,4,5,6,7,8,9,10,11,12,13,14,15,16,17,18,19,20,21,22,23,24,25,26,27,28,29,30}-1)*LEN(Registro!$J5)+1,LEN(Registro!$J5)))," ",REPT(" ",50)),50)))),"Revisar formato")) | M5: =IF(AND(Registro!$H5="",Registro!$I5=""),"",IF(AND(ISTEXT(K5),K5<>""),"Revisar formato",N(Registro!$H5)-N(K5))) -> 1940 | N5: =IF(M5="","",IF(OR(M5="Revisar formato",AND(ISTEXT(L5),L5<>"")),"Revisar formato",M5-N(L5))) -> 1940 | O5: =IF(AND(A5=Consulta!$B$3,C5=Consulta!$H$3),B5*10000+ROW(),"") -> 462990005
A6: =IF(Registro!$A6="","",Registro!$A6) -> TDS | B6: =IF(Registro!$B6="","",Registro!$B6) -> 46300 | C6: =IF(ISNUMBER(B6),YEAR(B6)*100+MONTH(B6),"") -> 202610 | D6: =IF(Registro!$E6="","",IF(ISERROR(FIND("x",LOWER(Registro!$E6))),"-",IFERROR(SUMPRODUCT(--("0"&LEFT(TRIM(MID(SUBSTITUTE(SUBSTITUTE(SUBSTITUTE(SUBSTITUTE(SUBSTITUTE(LOWER(Registro!$E6)," ",""),CHAR(10),"|"),";","|"),"+","|"),"|",REPT(" ",LEN(Registro!$E6))),({1,2,3,4,5,6,7,8,9,10,11,12,13,14,15,16,17,18,19,20,21,22,23,24,25,26,27,28,29,30}-1)*LEN(Registro!$E6)+1,LEN(Registro!$E6))),FIND("x",TRIM(MID(SUBSTITUTE(SUBSTITUTE(SUBSTITUTE(SUBSTITUTE(SUBSTITUTE(LOWER(Registro!$E6)," ",""),CHAR(10),"|"),";","|"),"+","|"),"|",REPT(" ",LEN(Registro!$E6))),({1,2,3,4,5,6,7,8,9,10,11,12,13,14,15,16,17,18,19,20,21,22,23,24,25,26,27,28,29,30}-1)*LEN(Registro!$E6)+1,LEN(Registro!$E6)))&"x")-1))),"Revisar formato"))) -> 49 | E6: =IF(Registro!$E6="","",IF(ISERROR(FIND("x",LOWER(Registro!$E6))),"-",IFERROR(SUMPRODUCT(--("0"&LEFT(TRIM(MID(SUBSTITUTE(SUBSTITUTE(SUBSTITUTE(SUBSTITUTE(SUBSTITUTE(LOWER(Registro!$E6)," ",""),CHAR(10),"|"),";","|"),"+","|"),"|",REPT(" ",LEN(Registro!$E6))),({1,2,3,4,5,6,7,8,9,10,11,12,13,14,15,16,17,18,19,20,21,22,23,24,25,26,27,28,29,30}-1)*LEN(Registro!$E6)+1,LEN(Registro!$E6))),FIND("x",TRIM(MID(SUBSTITUTE(SUBSTITUTE(SUBSTITUTE(SUBSTITUTE(SUBSTITUTE(LOWER(Registro!$E6)," ",""),CHAR(10),"|"),";","|"),"+","|"),"|",REPT(" ",LEN(Registro!$E6))),({1,2,3,4,5,6,7,8,9,10,11,12,13,14,15,16,17,18,19,20,21,22,23,24,25,26,27,28,29,30}-1)*LEN(Registro!$E6)+1,LEN(Registro!$E6)))&"x")-1)),--("0"&MID(TRIM(MID(SUBSTITUTE(SUBSTITUTE(SUBSTITUTE(SUBSTITUTE(SUBSTITUTE(LOWER(Registro!$E6)," ",""),CHAR(10),"|"),";","|"),"+","|"),"|",REPT(" ",LEN(Registro!$E6))),({1,2,3,4,5,6,7,8,9,10,11,12,13,14,15,16,17,18,19,20,21,22,23,24,25,26,27,28,29,30}-1)*LEN(Registro!$E6)+1,LEN(Registro!$E6))),FIND("x",TRIM(MID(SUBSTITUTE(SUBSTITUTE(SUBSTITUTE(SUBSTITUTE(SUBSTITUTE(LOWER(Registro!$E6)," ",""),CHAR(10),"|"),";","|"),"+","|"),"|",REPT(" ",LEN(Registro!$E6))),({1,2,3,4,5,6,7,8,9,10,11,12,13,14,15,16,17,18,19,20,21,22,23,24,25,26,27,28,29,30}-1)*LEN(Registro!$E6)+1,LEN(Registro!$E6)))&"x")+1,20))),"Revisar formato"))) -> 2200 | F6: =IF(Registro!$F6="","",N(Registro!$F6)) | G6: =IF(AND(E6="",F6=""),"",IF(OR(E6="",ISNUMBER(E6)),N(E6)-N(F6),E6)) -> 2200 | H6: =IF(Registro!$G6="","",IF(ISERROR(FIND("x",LOWER(Registro!$G6))),"-",IFERROR(SUMPRODUCT(--("0"&LEFT(TRIM(MID(SUBSTITUTE(SUBSTITUTE(SUBSTITUTE(SUBSTITUTE(SUBSTITUTE(LOWER(Registro!$G6)," ",""),CHAR(10),"|"),";","|"),"+","|"),"|",REPT(" ",LEN(Registro!$G6))),({1,2,3,4,5,6,7,8,9,10,11,12,13,14,15,16,17,18,19,20,21,22,23,24,25,26,27,28,29,30}-1)*LEN(Registro!$G6)+1,LEN(Registro!$G6))),FIND("x",TRIM(MID(SUBSTITUTE(SUBSTITUTE(SUBSTITUTE(SUBSTITUTE(SUBSTITUTE(LOWER(Registro!$G6)," ",""),CHAR(10),"|"),";","|"),"+","|"),"|",REPT(" ",LEN(Registro!$G6))),({1,2,3,4,5,6,7,8,9,10,11,12,13,14,15,16,17,18,19,20,21,22,23,24,25,26,27,28,29,30}-1)*LEN(Registro!$G6)+1,LEN(Registro!$G6)))&"x")-1))),"Revisar formato"))) -> 1 | I6: =IF(Registro!$G6="","",IF(ISERROR(FIND("x",LOWER(Registro!$G6))),N(Registro!$H6),IFERROR(SUMPRODUCT(--("0"&LEFT(TRIM(MID(SUBSTITUTE(SUBSTITUTE(SUBSTITUTE(SUBSTITUTE(SUBSTITUTE(LOWER(Registro!$G6)," ",""),CHAR(10),"|"),";","|"),"+","|"),"|",REPT(" ",LEN(Registro!$G6))),({1,2,3,4,5,6,7,8,9,10,11,12,13,14,15,16,17,18,19,20,21,22,23,24,25,26,27,28,29,30}-1)*LEN(Registro!$G6)+1,LEN(Registro!$G6))),FIND("x",TRIM(MID(SUBSTITUTE(SUBSTITUTE(SUBSTITUTE(SUBSTITUTE(SUBSTITUTE(LOWER(Registro!$G6)," ",""),CHAR(10),"|"),";","|"),"+","|"),"|",REPT(" ",LEN(Registro!$G6))),({1,2,3,4,5,6,7,8,9,10,11,12,13,14,15,16,17,18,19,20,21,22,23,24,25,26,27,28,29,30}-1)*LEN(Registro!$G6)+1,LEN(Registro!$G6)))&"x")-1)),--("0"&MID(TRIM(MID(SUBSTITUTE(SUBSTITUTE(SUBSTITUTE(SUBSTITUTE(SUBSTITUTE(LOWER(Registro!$G6)," ",""),CHAR(10),"|"),";","|"),"+","|"),"|",REPT(" ",LEN(Registro!$G6))),({1,2,3,4,5,6,7,8,9,10,11,12,13,14,15,16,17,18,19,20,21,22,23,24,25,26,27,28,29,30}-1)*LEN(Registro!$G6)+1,LEN(Registro!$G6))),FIND("x",TRIM(MID(SUBSTITUTE(SUBSTITUTE(SUBSTITUTE(SUBSTITUTE(SUBSTITUTE(LOWER(Registro!$G6)," ",""),CHAR(10),"|"),";","|"),"+","|"),"|",REPT(" ",LEN(Registro!$G6))),({1,2,3,4,5,6,7,8,9,10,11,12,13,14,15,16,17,18,19,20,21,22,23,24,25,26,27,28,29,30}-1)*LEN(Registro!$G6)+1,LEN(Registro!$G6)))&"x")+1,20))),"Revisar formato"))) -> 3300 | J6: =IF(AND(Registro!$E6="",Registro!$G6=""),"",IF(NOT(AND(ISNUMBER(I6),ISNUMBER(Registro!$H6))),"",IF(I6<Registro!$H6,"FALTA BOLETOS",IF(I6=Registro!$H6,"CONFORME","DIFERENCIA")))) -> CONFORME | K6: =IF(Registro!$I6="","",IFERROR(SUMPRODUCT(--("0"&TRIM(RIGHT(SUBSTITUTE(TRIM(MID(SUBSTITUTE(SUBSTITUTE(Registro!$I6,";",CHAR(10)),CHAR(10),REPT(" ",LEN(Registro!$I6))),({1,2,3,4,5,6,7,8,9,10,11,12,13,14,15,16,17,18,19,20,21,22,23,24,25,26,27,28,29,30}-1)*LEN(Registro!$I6)+1,LEN(Registro!$I6)))," ",REPT(" ",50)),50)))),"Revisar formato")) -> 500 | L6: =IF(Registro!$J6="","",IFERROR(SUMPRODUCT(--("0"&TRIM(RIGHT(SUBSTITUTE(TRIM(MID(SUBSTITUTE(SUBSTITUTE(Registro!$J6,";",CHAR(10)),CHAR(10),REPT(" ",LEN(Registro!$J6))),({1,2,3,4,5,6,7,8,9,10,11,12,13,14,15,16,17,18,19,20,21,22,23,24,25,26,27,28,29,30}-1)*LEN(Registro!$J6)+1,LEN(Registro!$J6)))," ",REPT(" ",50)),50)))),"Revisar formato")) -> 7500 | M6: =IF(AND(Registro!$H6="",Registro!$I6=""),"",IF(AND(ISTEXT(K6),K6<>""),"Revisar formato",N(Registro!$H6)-N(K6))) -> 2800 | N6: =IF(M6="","",IF(OR(M6="Revisar formato",AND(ISTEXT(L6),L6<>"")),"Revisar formato",M6-N(L6))) -> -4700 | O6: =IF(AND(A6=Consulta!$B$3,C6=Consulta!$H$3),B6*10000+ROW(),"") -> 463000006
A7: =IF(Registro!$A7="","",Registro!$A7) -> TDS | B7: =IF(Registro!$B7="","",Registro!$B7) -> 46301 | C7: =IF(ISNUMBER(B7),YEAR(B7)*100+MONTH(B7),"") -> 202610 | D7: =IF(Registro!$E7="","",IF(ISERROR(FIND("x",LOWER(Registro!$E7))),"-",IFERROR(SUMPRODUCT(--("0"&LEFT(TRIM(MID(SUBSTITUTE(SUBSTITUTE(SUBSTITUTE(SUBSTITUTE(SUBSTITUTE(LOWER(Registro!$E7)," ",""),CHAR(10),"|"),";","|"),"+","|"),"|",REPT(" ",LEN(Registro!$E7))),({1,2,3,4,5,6,7,8,9,10,11,12,13,14,15,16,17,18,19,20,21,22,23,24,25,26,27,28,29,30}-1)*LEN(Registro!$E7)+1,LEN(Registro!$E7))),FIND("x",TRIM(MID(SUBSTITUTE(SUBSTITUTE(SUBSTITUTE(SUBSTITUTE(SUBSTITUTE(LOWER(Registro!$E7)," ",""),CHAR(10),"|"),";","|"),"+","|"),"|",REPT(" ",LEN(Registro!$E7))),({1,2,3,4,5,6,7,8,9,10,11,12,13,14,15,16,17,18,19,20,21,22,23,24,25,26,27,28,29,30}-1)*LEN(Registro!$E7)+1,LEN(Registro!$E7)))&"x")-1))),"Revisar formato"))) -> 56 | E7: =IF(Registro!$E7="","",IF(ISERROR(FIND("x",LOWER(Registro!$E7))),"-",IFERROR(SUMPRODUCT(--("0"&LEFT(TRIM(MID(SUBSTITUTE(SUBSTITUTE(SUBSTITUTE(SUBSTITUTE(SUBSTITUTE(LOWER(Registro!$E7)," ",""),CHAR(10),"|"),";","|"),"+","|"),"|",REPT(" ",LEN(Registro!$E7))),({1,2,3,4,5,6,7,8,9,10,11,12,13,14,15,16,17,18,19,20,21,22,23,24,25,26,27,28,29,30}-1)*LEN(Registro!$E7)+1,LEN(Registro!$E7))),FIND("x",TRIM(MID(SUBSTITUTE(SUBSTITUTE(SUBSTITUTE(SUBSTITUTE(SUBSTITUTE(LOWER(Registro!$E7)," ",""),CHAR(10),"|"),";","|"),"+","|"),"|",REPT(" ",LEN(Registro!$E7))),({1,2,3,4,5,6,7,8,9,10,11,12,13,14,15,16,17,18,19,20,21,22,23,24,25,26,27,28,29,30}-1)*LEN(Registro!$E7)+1,LEN(Registro!$E7)))&"x")-1)),--("0"&MID(TRIM(MID(SUBSTITUTE(SUBSTITUTE(SUBSTITUTE(SUBSTITUTE(SUBSTITUTE(LOWER(Registro!$E7)," ",""),CHAR(10),"|"),";","|"),"+","|"),"|",REPT(" ",LEN(Registro!$E7))),({1,2,3,4,5,6,7,8,9,10,11,12,13,14,15,16,17,18,19,20,21,22,23,24,25,26,27,28,29,30}-1)*LEN(Registro!$E7)+1,LEN(Registro!$E7))),FIND("x",TRIM(MID(SUBSTITUTE(SUBSTITUTE(SUBSTITUTE(SUBSTITUTE(SUBSTITUTE(LOWER(Registro!$E7)," ",""),CHAR(10),"|"),";","|"),"+","|"),"|",REPT(" ",LEN(Registro!$E7))),({1,2,3,4,5,6,7,8,9,10,11,12,13,14,15,16,17,18,19,20,21,22,23,24,25,26,27,28,29,30}-1)*LEN(Registro!$E7)+1,LEN(Registro!$E7)))&"x")+1,20))),"Revisar formato"))) -> 2930 | F7: =IF(Registro!$F7="","",N(Registro!$F7)) | G7: =IF(AND(E7="",F7=""),"",IF(OR(E7="",ISNUMBER(E7)),N(E7)-N(F7),E7)) -> 2930 | H7: =IF(Registro!$G7="","",IF(ISERROR(FIND("x",LOWER(Registro!$G7))),"-",IFERROR(SUMPRODUCT(--("0"&LEFT(TRIM(MID(SUBSTITUTE(SUBSTITUTE(SUBSTITUTE(SUBSTITUTE(SUBSTITUTE(LOWER(Registro!$G7)," ",""),CHAR(10),"|"),";","|"),"+","|"),"|",REPT(" ",LEN(Registro!$G7))),({1,2,3,4,5,6,7,8,9,10,11,12,13,14,15,16,17,18,19,20,21,22,23,24,25,26,27,28,29,30}-1)*LEN(Registro!$G7)+1,LEN(Registro!$G7))),FIND("x",TRIM(MID(SUBSTITUTE(SUBSTITUTE(SUBSTITUTE(SUBSTITUTE(SUBSTITUTE(LOWER(Registro!$G7)," ",""),CHAR(10),"|"),";","|"),"+","|"),"|",REPT(" ",LEN(Registro!$G7))),({1,2,3,4,5,6,7,8,9,10,11,12,13,14,15,16,17,18,19,20,21,22,23,24,25,26,27,28,29,30}-1)*LEN(Registro!$G7)+1,LEN(Registro!$G7)))&"x")-1))),"Revisar formato"))) -> 1 | I7: =IF(Registro!$G7="","",IF(ISERROR(FIND("x",LOWER(Registro!$G7))),N(Registro!$H7),IFERROR(SUMPRODUCT(--("0"&LEFT(TRIM(MID(SUBSTITUTE(SUBSTITUTE(SUBSTITUTE(SUBSTITUTE(SUBSTITUTE(LOWER(Registro!$G7)," ",""),CHAR(10),"|"),";","|"),"+","|"),"|",REPT(" ",LEN(Registro!$G7))),({1,2,3,4,5,6,7,8,9,10,11,12,13,14,15,16,17,18,19,20,21,22,23,24,25,26,27,28,29,30}-1)*LEN(Registro!$G7)+1,LEN(Registro!$G7))),FIND("x",TRIM(MID(SUBSTITUTE(SUBSTITUTE(SUBSTITUTE(SUBSTITUTE(SUBSTITUTE(LOWER(Registro!$G7)," ",""),CHAR(10),"|"),";","|"),"+","|"),"|",REPT(" ",LEN(Registro!$G7))),({1,2,3,4,5,6,7,8,9,10,11,12,13,14,15,16,17,18,19,20,21,22,23,24,25,26,27,28,29,30}-1)*LEN(Registro!$G7)+1,LEN(Registro!$G7)))&"x")-1)),--("0"&MID(TRIM(MID(SUBSTITUTE(SUBSTITUTE(SUBSTITUTE(SUBSTITUTE(SUBSTITUTE(LOWER(Registro!$G7)," ",""),CHAR(10),"|"),";","|"),"+","|"),"|",REPT(" ",LEN(Registro!$G7))),({1,2,3,4,5,6,7,8,9,10,11,12,13,14,15,16,17,18,19,20,21,22,23,24,25,26,27,28,29,30}-1)*LEN(Registro!$G7)+1,LEN(Registro!$G7))),FIND("x",TRIM(MID(SUBSTITUTE(SUBSTITUTE(SUBSTITUTE(SUBSTITUTE(SUBSTITUTE(LOWER(Registro!$G7)," ",""),CHAR(10),"|"),";","|"),"+","|"),"|",REPT(" ",LEN(Registro!$G7))),({1,2,3,4,5,6,7,8,9,10,11,12,13,14,15,16,17,18,19,20,21,22,23,24,25,26,27,28,29,30}-1)*LEN(Registro!$G7)+1,LEN(Registro!$G7)))&"x")+1,20))),"Revisar formato"))) -> 2350 | J7: =IF(AND(Registro!$E7="",Registro!$G7=""),"",IF(NOT(AND(ISNUMBER(I7),ISNUMBER(Registro!$H7))),"",IF(I7<Registro!$H7,"FALTA BOLETOS",IF(I7=Registro!$H7,"CONFORME","DIFERENCIA")))) -> CONFORME | K7: =IF(Registro!$I7="","",IFERROR(SUMPRODUCT(--("0"&TRIM(RIGHT(SUBSTITUTE(TRIM(MID(SUBSTITUTE(SUBSTITUTE(Registro!$I7,";",CHAR(10)),CHAR(10),REPT(" ",LEN(Registro!$I7))),({1,2,3,4,5,6,7,8,9,10,11,12,13,14,15,16,17,18,19,20,21,22,23,24,25,26,27,28,29,30}-1)*LEN(Registro!$I7)+1,LEN(Registro!$I7)))," ",REPT(" ",50)),50)))),"Revisar formato")) -> 100 | L7: =IF(Registro!$J7="","",IFERROR(SUMPRODUCT(--("0"&TRIM(RIGHT(SUBSTITUTE(TRIM(MID(SUBSTITUTE(SUBSTITUTE(Registro!$J7,";",CHAR(10)),CHAR(10),REPT(" ",LEN(Registro!$J7))),({1,2,3,4,5,6,7,8,9,10,11,12,13,14,15,16,17,18,19,20,21,22,23,24,25,26,27,28,29,30}-1)*LEN(Registro!$J7)+1,LEN(Registro!$J7)))," ",REPT(" ",50)),50)))),"Revisar formato")) | M7: =IF(AND(Registro!$H7="",Registro!$I7=""),"",IF(AND(ISTEXT(K7),K7<>""),"Revisar formato",N(Registro!$H7)-N(K7))) -> 2250 | N7: =IF(M7="","",IF(OR(M7="Revisar formato",AND(ISTEXT(L7),L7<>"")),"Revisar formato",M7-N(L7))) -> 2250 | O7: =IF(AND(A7=Consulta!$B$3,C7=Consulta!$H$3),B7*10000+ROW(),"") -> 463010007
A8: =IF(Registro!$A8="","",Registro!$A8) -> TDS | B8: =IF(Registro!$B8="","",Registro!$B8) -> 46302 | C8: =IF(ISNUMBER(B8),YEAR(B8)*100+MONTH(B8),"") -> 202610 | D8: =IF(Registro!$E8="","",IF(ISERROR(FIND("x",LOWER(Registro!$E8))),"-",IFERROR(SUMPRODUCT(--("0"&LEFT(TRIM(MID(SUBSTITUTE(SUBSTITUTE(SUBSTITUTE(SUBSTITUTE(SUBSTITUTE(LOWER(Registro!$E8)," ",""),CHAR(10),"|"),";","|"),"+","|"),"|",REPT(" ",LEN(Registro!$E8))),({1,2,3,4,5,6,7,8,9,10,11,12,13,14,15,16,17,18,19,20,21,22,23,24,25,26,27,28,29,30}-1)*LEN(Registro!$E8)+1,LEN(Registro!$E8))),FIND("x",TRIM(MID(SUBSTITUTE(SUBSTITUTE(SUBSTITUTE(SUBSTITUTE(SUBSTITUTE(LOWER(Registro!$E8)," ",""),CHAR(10),"|"),";","|"),"+","|"),"|",REPT(" ",LEN(Registro!$E8))),({1,2,3,4,5,6,7,8,9,10,11,12,13,14,15,16,17,18,19,20,21,22,23,24,25,26,27,28,29,30}-1)*LEN(Registro!$E8)+1,LEN(Registro!$E8)))&"x")-1))),"Revisar formato"))) -> 33 | E8: =IF(Registro!$E8="","",IF(ISERROR(FIND("x",LOWER(Registro!$E8))),"-",IFERROR(SUMPRODUCT(--("0"&LEFT(TRIM(MID(SUBSTITUTE(SUBSTITUTE(SUBSTITUTE(SUBSTITUTE(SUBSTITUTE(LOWER(Registro!$E8)," ",""),CHAR(10),"|"),";","|"),"+","|"),"|",REPT(" ",LEN(Registro!$E8))),({1,2,3,4,5,6,7,8,9,10,11,12,13,14,15,16,17,18,19,20,21,22,23,24,25,26,27,28,29,30}-1)*LEN(Registro!$E8)+1,LEN(Registro!$E8))),FIND("x",TRIM(MID(SUBSTITUTE(SUBSTITUTE(SUBSTITUTE(SUBSTITUTE(SUBSTITUTE(LOWER(Registro!$E8)," ",""),CHAR(10),"|"),";","|"),"+","|"),"|",REPT(" ",LEN(Registro!$E8))),({1,2,3,4,5,6,7,8,9,10,11,12,13,14,15,16,17,18,19,20,21,22,23,24,25,26,27,28,29,30}-1)*LEN(Registro!$E8)+1,LEN(Registro!$E8)))&"x")-1)),--("0"&MID(TRIM(MID(SUBSTITUTE(SUBSTITUTE(SUBSTITUTE(SUBSTITUTE(SUBSTITUTE(LOWER(Registro!$E8)," ",""),CHAR(10),"|"),";","|"),"+","|"),"|",REPT(" ",LEN(Registro!$E8))),({1,2,3,4,5,6,7,8,9,10,11,12,13,14,15,16,17,18,19,20,21,22,23,24,25,26,27,28,29,30}-1)*LEN(Registro!$E8)+1,LEN(Registro!$E8))),FIND("x",TRIM(MID(SUBSTITUTE(SUBSTITUTE(SUBSTITUTE(SUBSTITUTE(SUBSTITUTE(LOWER(Registro!$E8)," ",""),CHAR(10),"|"),";","|"),"+","|"),"|",REPT(" ",LEN(Registro!$E8))),({1,2,3,4,5,6,7,8,9,10,11,12,13,14,15,16,17,18,19,20,21,22,23,24,25,26,27,28,29,30}-1)*LEN(Registro!$E8)+1,LEN(Registro!$E8)))&"x")+1,20))),"Revisar formato"))) -> 1450 | F8: =IF(Registro!$F8="","",N(Registro!$F8)) | G8: =IF(AND(E8="",F8=""),"",IF(OR(E8="",ISNUMBER(E8)),N(E8)-N(F8),E8)) -> 1450 | H8: =IF(Registro!$G8="","",IF(ISERROR(FIND("x",LOWER(Registro!$G8))),"-",IFERROR(SUMPRODUCT(--("0"&LEFT(TRIM(MID(SUBSTITUTE(SUBSTITUTE(SUBSTITUTE(SUBSTITUTE(SUBSTITUTE(LOWER(Registro!$G8)," ",""),CHAR(10),"|"),";","|"),"+","|"),"|",REPT(" ",LEN(Registro!$G8))),({1,2,3,4,5,6,7,8,9,10,11,12,13,14,15,16,17,18,19,20,21,22,23,24,25,26,27,28,29,30}-1)*LEN(Registro!$G8)+1,LEN(Registro!$G8))),FIND("x",TRIM(MID(SUBSTITUTE(SUBSTITUTE(SUBSTITUTE(SUBSTITUTE(SUBSTITUTE(LOWER(Registro!$G8)," ",""),CHAR(10),"|"),";","|"),"+","|"),"|",REPT(" ",LEN(Registro!$G8))),({1,2,3,4,5,6,7,8,9,10,11,12,13,14,15,16,17,18,19,20,21,22,23,24,25,26,27,28,29,30}-1)*LEN(Registro!$G8)+1,LEN(Registro!$G8)))&"x")-1))),"Revisar formato"))) -> 1 | I8: =IF(Registro!$G8="","",IF(ISERROR(FIND("x",LOWER(Registro!$G8))),N(Registro!$H8),IFERROR(SUMPRODUCT(--("0"&LEFT(TRIM(MID(SUBSTITUTE(SUBSTITUTE(SUBSTITUTE(SUBSTITUTE(SUBSTITUTE(LOWER(Registro!$G8)," ",""),CHAR(10),"|"),";","|"),"+","|"),"|",REPT(" ",LEN(Registro!$G8))),({1,2,3,4,5,6,7,8,9,10,11,12,13,14,15,16,17,18,19,20,21,22,23,24,25,26,27,28,29,30}-1)*LEN(Registro!$G8)+1,LEN(Registro!$G8))),FIND("x",TRIM(MID(SUBSTITUTE(SUBSTITUTE(SUBSTITUTE(SUBSTITUTE(SUBSTITUTE(LOWER(Registro!$G8)," ",""),CHAR(10),"|"),";","|"),"+","|"),"|",REPT(" ",LEN(Registro!$G8))),({1,2,3,4,5,6,7,8,9,10,11,12,13,14,15,16,17,18,19,20,21,22,23,24,25,26,27,28,29,30}-1)*LEN(Registro!$G8)+1,LEN(Registro!$G8)))&"x")-1)),--("0"&MID(TRIM(MID(SUBSTITUTE(SUBSTITUTE(SUBSTITUTE(SUBSTITUTE(SUBSTITUTE(LOWER(Registro!$G8)," ",""),CHAR(10),"|"),";","|"),"+","|"),"|",REPT(" ",LEN(Registro!$G8))),({1,2,3,4,5,6,7,8,9,10,11,12,13,14,15,16,17,18,19,20,21,22,23,24,25,26,27,28,29,30}-1)*LEN(Registro!$G8)+1,LEN(Registro!$G8))),FIND("x",TRIM(MID(SUBSTITUTE(SUBSTITUTE(SUBSTITUTE(SUBSTITUTE(SUBSTITUTE(LOWER(Registro!$G8)," ",""),CHAR(10),"|"),";","|"),"+","|"),"|",REPT(" ",LEN(Registro!$G8))),({1,2,3,4,5,6,7,8,9,10,11,12,13,14,15,16,17,18,19,20,21,22,23,24,25,26,27,28,29,30}-1)*LEN(Registro!$G8)+1,LEN(Registro!$G8)))&"x")+1,20))),"Revisar formato"))) -> 2455 | J8: =IF(AND(Registro!$E8="",Registro!$G8=""),"",IF(NOT(AND(ISNUMBER(I8),ISNUMBER(Registro!$H8))),"",IF(I8<Registro!$H8,"FALTA BOLETOS",IF(I8=Registro!$H8,"CONFORME","DIFERENCIA")))) -> CONFORME | K8: =IF(Registro!$I8="","",IFERROR(SUMPRODUCT(--("0"&TRIM(RIGHT(SUBSTITUTE(TRIM(MID(SUBSTITUTE(SUBSTITUTE(Registro!$I8,";",CHAR(10)),CHAR(10),REPT(" ",LEN(Registro!$I8))),({1,2,3,4,5,6,7,8,9,10,11,12,13,14,15,16,17,18,19,20,21,22,23,24,25,26,27,28,29,30}-1)*LEN(Registro!$I8)+1,LEN(Registro!$I8)))," ",REPT(" ",50)),50)))),"Revisar formato")) -> 100 | L8: =IF(Registro!$J8="","",IFERROR(SUMPRODUCT(--("0"&TRIM(RIGHT(SUBSTITUTE(TRIM(MID(SUBSTITUTE(SUBSTITUTE(Registro!$J8,";",CHAR(10)),CHAR(10),REPT(" ",LEN(Registro!$J8))),({1,2,3,4,5,6,7,8,9,10,11,12,13,14,15,16,17,18,19,20,21,22,23,24,25,26,27,28,29,30}-1)*LEN(Registro!$J8)+1,LEN(Registro!$J8)))," ",REPT(" ",50)),50)))),"Revisar formato")) | M8: =IF(AND(Registro!$H8="",Registro!$I8=""),"",IF(AND(ISTEXT(K8),K8<>""),"Revisar formato",N(Registro!$H8)-N(K8))) -> 2355 | N8: =IF(M8="","",IF(OR(M8="Revisar formato",AND(ISTEXT(L8),L8<>"")),"Revisar formato",M8-N(L8))) -> 2355 | O8: =IF(AND(A8=Consulta!$B$3,C8=Consulta!$H$3),B8*10000+ROW(),"") -> 463020008
A9: =IF(Registro!$A9="","",Registro!$A9) -> TDS | B9: =IF(Registro!$B9="","",Registro!$B9) -> 46303 | C9: =IF(ISNUMBER(B9),YEAR(B9)*100+MONTH(B9),"") -> 202610 | D9: =IF(Registro!$E9="","",IF(ISERROR(FIND("x",LOWER(Registro!$E9))),"-",IFERROR(SUMPRODUCT(--("0"&LEFT(TRIM(MID(SUBSTITUTE(SUBSTITUTE(SUBSTITUTE(SUBSTITUTE(SUBSTITUTE(LOWER(Registro!$E9)," ",""),CHAR(10),"|"),";","|"),"+","|"),"|",REPT(" ",LEN(Registro!$E9))),({1,2,3,4,5,6,7,8,9,10,11,12,13,14,15,16,17,18,19,20,21,22,23,24,25,26,27,28,29,30}-1)*LEN(Registro!$E9)+1,LEN(Registro!$E9))),FIND("x",TRIM(MID(SUBSTITUTE(SUBSTITUTE(SUBSTITUTE(SUBSTITUTE(SUBSTITUTE(LOWER(Registro!$E9)," ",""),CHAR(10),"|"),";","|"),"+","|"),"|",REPT(" ",LEN(Registro!$E9))),({1,2,3,4,5,6,7,8,9,10,11,12,13,14,15,16,17,18,19,20,21,22,23,24,25,26,27,28,29,30}-1)*LEN(Registro!$E9)+1,LEN(Registro!$E9)))&"x")-1))),"Revisar formato"))) -> 46 | E9: =IF(Registro!$E9="","",IF(ISERROR(FIND("x",LOWER(Registro!$E9))),"-",IFERROR(SUMPRODUCT(--("0"&LEFT(TRIM(MID(SUBSTITUTE(SUBSTITUTE(SUBSTITUTE(SUBSTITUTE(SUBSTITUTE(LOWER(Registro!$E9)," ",""),CHAR(10),"|"),";","|"),"+","|"),"|",REPT(" ",LEN(Registro!$E9))),({1,2,3,4,5,6,7,8,9,10,11,12,13,14,15,16,17,18,19,20,21,22,23,24,25,26,27,28,29,30}-1)*LEN(Registro!$E9)+1,LEN(Registro!$E9))),FIND("x",TRIM(MID(SUBSTITUTE(SUBSTITUTE(SUBSTITUTE(SUBSTITUTE(SUBSTITUTE(LOWER(Registro!$E9)," ",""),CHAR(10),"|"),";","|"),"+","|"),"|",REPT(" ",LEN(Registro!$E9))),({1,2,3,4,5,6,7,8,9,10,11,12,13,14,15,16,17,18,19,20,21,22,23,24,25,26,27,28,29,30}-1)*LEN(Registro!$E9)+1,LEN(Registro!$E9)))&"x")-1)),--("0"&MID(TRIM(MID(SUBSTITUTE(SUBSTITUTE(SUBSTITUTE(SUBSTITUTE(SUBSTITUTE(LOWER(Registro!$E9)," ",""),CHAR(10),"|"),";","|"),"+","|"),"|",REPT(" ",LEN(Registro!$E9))),({1,2,3,4,5,6,7,8,9,10,11,12,13,14,15,16,17,18,19,20,21,22,23,24,25,26,27,28,29,30}-1)*LEN(Registro!$E9)+1,LEN(Registro!$E9))),FIND("x",TRIM(MID(SUBSTITUTE(SUBSTITUTE(SUBSTITUTE(SUBSTITUTE(SUBSTITUTE(LOWER(Registro!$E9)," ",""),CHAR(10),"|"),";","|"),"+","|"),"|",REPT(" ",LEN(Registro!$E9))),({1,2,3,4,5,6,7,8,9,10,11,12,13,14,15,16,17,18,19,20,21,22,23,24,25,26,27,28,29,30}-1)*LEN(Registro!$E9)+1,LEN(Registro!$E9)))&"x")+1,20))),"Revisar formato"))) -> 2060 | F9: =IF(Registro!$F9="","",N(Registro!$F9)) | G9: =IF(AND(E9="",F9=""),"",IF(OR(E9="",ISNUMBER(E9)),N(E9)-N(F9),E9)) -> 2060 | H9: =IF(Registro!$G9="","",IF(ISERROR(FIND("x",LOWER(Registro!$G9))),"-",IFERROR(SUMPRODUCT(--("0"&LEFT(TRIM(MID(SUBSTITUTE(SUBSTITUTE(SUBSTITUTE(SUBSTITUTE(SUBSTITUTE(LOWER(Registro!$G9)," ",""),CHAR(10),"|"),";","|"),"+","|"),"|",REPT(" ",LEN(Registro!$G9))),({1,2,3,4,5,6,7,8,9,10,11,12,13,14,15,16,17,18,19,20,21,22,23,24,25,26,27,28,29,30}-1)*LEN(Registro!$G9)+1,LEN(Registro!$G9))),FIND("x",TRIM(MID(SUBSTITUTE(SUBSTITUTE(SUBSTITUTE(SUBSTITUTE(SUBSTITUTE(LOWER(Registro!$G9)," ",""),CHAR(10),"|"),";","|"),"+","|"),"|",REPT(" ",LEN(Registro!$G9))),({1,2,3,4,5,6,7,8,9,10,11,12,13,14,15,16,17,18,19,20,21,22,23,24,25,26,27,28,29,30}-1)*LEN(Registro!$G9)+1,LEN(Registro!$G9)))&"x")-1))),"Revisar formato"))) -> 1 | I9: =IF(Registro!$G9="","",IF(ISERROR(FIND("x",LOWER(Registro!$G9))),N(Registro!$H9),IFERROR(SUMPRODUCT(--("0"&LEFT(TRIM(MID(SUBSTITUTE(SUBSTITUTE(SUBSTITUTE(SUBSTITUTE(SUBSTITUTE(LOWER(Registro!$G9)," ",""),CHAR(10),"|"),";","|"),"+","|"),"|",REPT(" ",LEN(Registro!$G9))),({1,2,3,4,5,6,7,8,9,10,11,12,13,14,15,16,17,18,19,20,21,22,23,24,25,26,27,28,29,30}-1)*LEN(Registro!$G9)+1,LEN(Registro!$G9))),FIND("x",TRIM(MID(SUBSTITUTE(SUBSTITUTE(SUBSTITUTE(SUBSTITUTE(SUBSTITUTE(LOWER(Registro!$G9)," ",""),CHAR(10),"|"),";","|"),"+","|"),"|",REPT(" ",LEN(Registro!$G9))),({1,2,3,4,5,6,7,8,9,10,11,12,13,14,15,16,17,18,19,20,21,22,23,24,25,26,27,28,29,30}-1)*LEN(Registro!$G9)+1,LEN(Registro!$G9)))&"x")-1)),--("0"&MID(TRIM(MID(SUBSTITUTE(SUBSTITUTE(SUBSTITUTE(SUBSTITUTE(SUBSTITUTE(LOWER(Registro!$G9)," ",""),CHAR(10),"|"),";","|"),"+","|"),"|",REPT(" ",LEN(Registro!$G9))),({1,2,3,4,5,6,7,8,9,10,11,12,13,14,15,16,17,18,19,20,21,22,23,24,25,26,27,28,29,30}-1)*LEN(Registro!$G9)+1,LEN(Registro!$G9))),FIND("x",TRIM(MID(SUBSTITUTE(SUBSTITUTE(SUBSTITUTE(SUBSTITUTE(SUBSTITUTE(LOWER(Registro!$G9)," ",""),CHAR(10),"|"),";","|"),"+","|"),"|",REPT(" ",LEN(Registro!$G9))),({1,2,3,4,5,6,7,8,9,10,11,12,13,14,15,16,17,18,19,20,21,22,23,24,25,26,27,28,29,30}-1)*LEN(Registro!$G9)+1,LEN(Registro!$G9)))&"x")+1,20))),"Revisar formato"))) -> 2365 | J9: =IF(AND(Registro!$E9="",Registro!$G9=""),"",IF(NOT(AND(ISNUMBER(I9),ISNUMBER(Registro!$H9))),"",IF(I9<Registro!$H9,"FALTA BOLETOS",IF(I9=Registro!$H9,"CONFORME","DIFERENCIA")))) -> CONFORME | K9: =IF(Registro!$I9="","",IFERROR(SUMPRODUCT(--("0"&TRIM(RIGHT(SUBSTITUTE(TRIM(MID(SUBSTITUTE(SUBSTITUTE(Registro!$I9,";",CHAR(10)),CHAR(10),REPT(" ",LEN(Registro!$I9))),({1,2,3,4,5,6,7,8,9,10,11,12,13,14,15,16,17,18,19,20,21,22,23,24,25,26,27,28,29,30}-1)*LEN(Registro!$I9)+1,LEN(Registro!$I9)))," ",REPT(" ",50)),50)))),"Revisar formato")) -> 50 | L9: =IF(Registro!$J9="","",IFERROR(SUMPRODUCT(--("0"&TRIM(RIGHT(SUBSTITUTE(TRIM(MID(SUBSTITUTE(SUBSTITUTE(Registro!$J9,";",CHAR(10)),CHAR(10),REPT(" ",LEN(Registro!$J9))),({1,2,3,4,5,6,7,8,9,10,11,12,13,14,15,16,17,18,19,20,21,22,23,24,25,26,27,28,29,30}-1)*LEN(Registro!$J9)+1,LEN(Registro!$J9)))," ",REPT(" ",50)),50)))),"Revisar formato")) | M9: =IF(AND(Registro!$H9="",Registro!$I9=""),"",IF(AND(ISTEXT(K9),K9<>""),"Revisar formato",N(Registro!$H9)-N(K9))) -> 2315 | N9: =IF(M9="","",IF(OR(M9="Revisar formato",AND(ISTEXT(L9),L9<>"")),"Revisar formato",M9-N(L9))) -> 2315 | O9: =IF(AND(A9=Consulta!$B$3,C9=Consulta!$H$3),B9*10000+ROW(),"") -> 463030009
A10: =IF(Registro!$A10="","",Registro!$A10) -> TDS | B10: =IF(Registro!$B10="","",Registro!$B10) -> 46304 | C10: =IF(ISNUMBER(B10),YEAR(B10)*100+MONTH(B10),"") -> 202610 | D10: =IF(Registro!$E10="","",IF(ISERROR(FIND("x",LOWER(Registro!$E10))),"-",IFERROR(SUMPRODUCT(--("0"&LEFT(TRIM(MID(SUBSTITUTE(SUBSTITUTE(SUBSTITUTE(SUBSTITUTE(SUBSTITUTE(LOWER(Registro!$E10)," ",""),CHAR(10),"|"),";","|"),"+","|"),"|",REPT(" ",LEN(Registro!$E10))),({1,2,3,4,5,6,7,8,9,10,11,12,13,14,15,16,17,18,19,20,21,22,23,24,25,26,27,28,29,30}-1)*LEN(Registro!$E10)+1,LEN(Registro!$E10))),FIND("x",TRIM(MID(SUBSTITUTE(SUBSTITUTE(SUBSTITUTE(SUBSTITUTE(SUBSTITUTE(LOWER(Registro!$E10)," ",""),CHAR(10),"|"),";","|"),"+","|"),"|",REPT(" ",LEN(Registro!$E10))),({1,2,3,4,5,6,7,8,9,10,11,12,13,14,15,16,17,18,19,20,21,22,23,24,25,26,27,28,29,30}-1)*LEN(Registro!$E10)+1,LEN(Registro!$E10)))&"x")-1))),"Revisar formato"))) -> 57 | E10: =IF(Registro!$E10="","",IF(ISERROR(FIND("x",LOWER(Registro!$E10))),"-",IFERROR(SUMPRODUCT(--("0"&LEFT(TRIM(MID(SUBSTITUTE(SUBSTITUTE(SUBSTITUTE(SUBSTITUTE(SUBSTITUTE(LOWER(Registro!$E10)," ",""),CHAR(10),"|"),";","|"),"+","|"),"|",REPT(" ",LEN(Registro!$E10))),({1,2,3,4,5,6,7,8,9,10,11,12,13,14,15,16,17,18,19,20,21,22,23,24,25,26,27,28,29,30}-1)*LEN(Registro!$E10)+1,LEN(Registro!$E10))),FIND("x",TRIM(MID(SUBSTITUTE(SUBSTITUTE(SUBSTITUTE(SUBSTITUTE(SUBSTITUTE(LOWER(Registro!$E10)," ",""),CHAR(10),"|"),";","|"),"+","|"),"|",REPT(" ",LEN(Registro!$E10))),({1,2,3,4,5,6,7,8,9,10,11,12,13,14,15,16,17,18,19,20,21,22,23,24,25,26,27,28,29,30}-1)*LEN(Registro!$E10)+1,LEN(Registro!$E10)))&"x")-1)),--("0"&MID(TRIM(MID(SUBSTITUTE(SUBSTITUTE(SUBSTITUTE(SUBSTITUTE(SUBSTITUTE(LOWER(Registro!$E10)," ",""),CHAR(10),"|"),";","|"),"+","|"),"|",REPT(" ",LEN(Registro!$E10))),({1,2,3,4,5,6,7,8,9,10,11,12,13,14,15,16,17,18,19,20,21,22,23,24,25,26,27,28,29,30}-1)*LEN(Registro!$E10)+1,LEN(Registro!$E10))),FIND("x",TRIM(MID(SUBSTITUTE(SUBSTITUTE(SUBSTITUTE(SUBSTITUTE(SUBSTITUTE(LOWER(Registro!$E10)," ",""),CHAR(10),"|"),";","|"),"+","|"),"|",REPT(" ",LEN(Registro!$E10))),({1,2,3,4,5,6,7,8,9,10,11,12,13,14,15,16,17,18,19,20,21,22,23,24,25,26,27,28,29,30}-1)*LEN(Registro!$E10)+1,LEN(Registro!$E10)))&"x")+1,20))),"Revisar formato"))) -> 2870 | F10: =IF(Registro!$F10="","",N(Registro!$F10)) | G10: =IF(AND(E10="",F10=""),"",IF(OR(E10="",ISNUMBER(E10)),N(E10)-N(F10),E10)) -> 2870 | H10: =IF(Registro!$G10="","",IF(ISERROR(FIND("x",LOWER(Registro!$G10))),"-",IFERROR(SUMPRODUCT(--("0"&LEFT(TRIM(MID(SUBSTITUTE(SUBSTITUTE(SUBSTITUTE(SUBSTITUTE(SUBSTITUTE(LOWER(Registro!$G10)," ",""),CHAR(10),"|"),";","|"),"+","|"),"|",REPT(" ",LEN(Registro!$G10))),({1,2,3,4,5,6,7,8,9,10,11,12,13,14,15,16,17,18,19,20,21,22,23,24,25,26,27,28,29,30}-1)*LEN(Registro!$G10)+1,LEN(Registro!$G10))),FIND("x",TRIM(MID(SUBSTITUTE(SUBSTITUTE(SUBSTITUTE(SUBSTITUTE(SUBSTITUTE(LOWER(Registro!$G10)," ",""),CHAR(10),"|"),";","|"),"+","|"),"|",REPT(" ",LEN(Registro!$G10))),({1,2,3,4,5,6,7,8,9,10,11,12,13,14,15,16,17,18,19,20,21,22,23,24,25,26,27,28,29,30}-1)*LEN(Registro!$G10)+1,LEN(Registro!$G10)))&"x")-1))),"Revisar formato"))) -> 1 | I10: =IF(Registro!$G10="","",IF(ISERROR(FIND("x",LOWER(Registro!$G10))),N(Registro!$H10),IFERROR(SUMPRODUCT(--("0"&LEFT(TRIM(MID(SUBSTITUTE(SUBSTITUTE(SUBSTITUTE(SUBSTITUTE(SUBSTITUTE(LOWER(Registro!$G10)," ",""),CHAR(10),"|"),";","|"),"+","|"),"|",REPT(" ",LEN(Registro!$G10))),({1,2,3,4,5,6,7,8,9,10,11,12,13,14,15,16,17,18,19,20,21,22,23,24,25,26,27,28,29,30}-1)*LEN(Registro!$G10)+1,LEN(Registro!$G10))),FIND("x",TRIM(MID(SUBSTITUTE(SUBSTITUTE(SUBSTITUTE(SUBSTITUTE(SUBSTITUTE(LOWER(Registro!$G10)," ",""),CHAR(10),"|"),";","|"),"+","|"),"|",REPT(" ",LEN(Registro!$G10))),({1,2,3,4,5,6,7,8,9,10,11,12,13,14,15,16,17,18,19,20,21,22,23,24,25,26,27,28,29,30}-1)*LEN(Registro!$G10)+1,LEN(Registro!$G10)))&"x")-1)),--("0"&MID(TRIM(MID(SUBSTITUTE(SUBSTITUTE(SUBSTITUTE(SUBSTITUTE(SUBSTITUTE(LOWER(Registro!$G10)," ",""),CHAR(10),"|"),";","|"),"+","|"),"|",REPT(" ",LEN(Registro!$G10))),({1,2,3,4,5,6,7,8,9,10,11,12,13,14,15,16,17,18,19,20,21,22,23,24,25,26,27,28,29,30}-1)*LEN(Registro!$G10)+1,LEN(Registro!$G10))),FIND("x",TRIM(MID(SUBSTITUTE(SUBSTITUTE(SUBSTITUTE(SUBSTITUTE(SUBSTITUTE(LOWER(Registro!$G10)," ",""),CHAR(10),"|"),";","|"),"+","|"),"|",REPT(" ",LEN(Registro!$G10))),({1,2,3,4,5,6,7,8,9,10,11,12,13,14,15,16,17,18,19,20,21,22,23,24,25,26,27,28,29,30}-1)*LEN(Registro!$G10)+1,LEN(Registro!$G10)))&"x")+1,20))),"Revisar formato"))) -> 2395 | J10: =IF(AND(Registro!$E10="",Registro!$G10=""),"",IF(NOT(AND(ISNUMBER(I10),ISNUMBER(Registro!$H10))),"",IF(I10<Registro!$H10,"FALTA BOLETOS",IF(I10=Registro!$H10,"CONFORME","DIFERENCIA")))) -> CONFORME | K10: =IF(Registro!$I10="","",IFERROR(SUMPRODUCT(--("0"&TRIM(RIGHT(SUBSTITUTE(TRIM(MID(SUBSTITUTE(SUBSTITUTE(Registro!$I10,";",CHAR(10)),CHAR(10),REPT(" ",LEN(Registro!$I10))),({1,2,3,4,5,6,7,8,9,10,11,12,13,14,15,16,17,18,19,20,21,22,23,24,25,26,27,28,29,30}-1)*LEN(Registro!$I10)+1,LEN(Registro!$I10)))," ",REPT(" ",50)),50)))),"Revisar formato")) | L10: =IF(Registro!$J10="","",IFERROR(SUMPRODUCT(--("0"&TRIM(RIGHT(SUBSTITUTE(TRIM(MID(SUBSTITUTE(SUBSTITUTE(Registro!$J10,";",CHAR(10)),CHAR(10),REPT(" ",LEN(Registro!$J10))),({1,2,3,4,5,6,7,8,9,10,11,12,13,14,15,16,17,18,19,20,21,22,23,24,25,26,27,28,29,30}-1)*LEN(Registro!$J10)+1,LEN(Registro!$J10)))," ",REPT(" ",50)),50)))),"Revisar formato")) | M10: =IF(AND(Registro!$H10="",Registro!$I10=""),"",IF(AND(ISTEXT(K10),K10<>""),"Revisar formato",N(Registro!$H10)-N(K10))) -> 2395 | N10: =IF(M10="","",IF(OR(M10="Revisar formato",AND(ISTEXT(L10),L10<>"")),"Revisar formato",M10-N(L10))) -> 2395 | O10: =IF(AND(A10=Consulta!$B$3,C10=Consulta!$H$3),B10*10000+ROW(),"") -> 463040010
A11: =IF(Registro!$A11="","",Registro!$A11) -> TDS | B11: =IF(Registro!$B11="","",Registro!$B11) -> 46305 | C11: =IF(ISNUMBER(B11),YEAR(B11)*100+MONTH(B11),"") -> 202610 | D11: =IF(Registro!$E11="","",IF(ISERROR(FIND("x",LOWER(Registro!$E11))),"-",IFERROR(SUMPRODUCT(--("0"&LEFT(TRIM(MID(SUBSTITUTE(SUBSTITUTE(SUBSTITUTE(SUBSTITUTE(SUBSTITUTE(LOWER(Registro!$E11)," ",""),CHAR(10),"|"),";","|"),"+","|"),"|",REPT(" ",LEN(Registro!$E11))),({1,2,3,4,5,6,7,8,9,10,11,12,13,14,15,16,17,18,19,20,21,22,23,24,25,26,27,28,29,30}-1)*LEN(Registro!$E11)+1,LEN(Registro!$E11))),FIND("x",TRIM(MID(SUBSTITUTE(SUBSTITUTE(SUBSTITUTE(SUBSTITUTE(SUBSTITUTE(LOWER(Registro!$E11)," ",""),CHAR(10),"|"),";","|"),"+","|"),"|",REPT(" ",LEN(Registro!$E11))),({1,2,3,4,5,6,7,8,9,10,11,12,13,14,15,16,17,18,19,20,21,22,23,24,25,26,27,28,29,30}-1)*LEN(Registro!$E11)+1,LEN(Registro!$E11)))&"x")-1))),"Revisar formato"))) -> 43 | E11: =IF(Registro!$E11="","",IF(ISERROR(FIND("x",LOWER(Registro!$E11))),"-",IFERROR(SUMPRODUCT(--("0"&LEFT(TRIM(MID(SUBSTITUTE(SUBSTITUTE(SUBSTITUTE(SUBSTITUTE(SUBSTITUTE(LOWER(Registro!$E11)," ",""),CHAR(10),"|"),";","|"),"+","|"),"|",REPT(" ",LEN(Registro!$E11))),({1,2,3,4,5,6,7,8,9,10,11,12,13,14,15,16,17,18,19,20,21,22,23,24,25,26,27,28,29,30}-1)*LEN(Registro!$E11)+1,LEN(Registro!$E11))),FIND("x",TRIM(MID(SUBSTITUTE(SUBSTITUTE(SUBSTITUTE(SUBSTITUTE(SUBSTITUTE(LOWER(Registro!$E11)," ",""),CHAR(10),"|"),";","|"),"+","|"),"|",REPT(" ",LEN(Registro!$E11))),({1,2,3,4,5,6,7,8,9,10,11,12,13,14,15,16,17,18,19,20,21,22,23,24,25,26,27,28,29,30}-1)*LEN(Registro!$E11)+1,LEN(Registro!$E11)))&"x")-1)),--("0"&MID(TRIM(MID(SUBSTITUTE(SUBSTITUTE(SUBSTITUTE(SUBSTITUTE(SUBSTITUTE(LOWER(Registro!$E11)," ",""),CHAR(10),"|"),";","|"),"+","|"),"|",REPT(" ",LEN(Registro!$E11))),({1,2,3,4,5,6,7,8,9,10,11,12,13,14,15,16,17,18,19,20,21,22,23,24,25,26,27,28,29,30}-1)*LEN(Registro!$E11)+1,LEN(Registro!$E11))),FIND("x",TRIM(MID(SUBSTITUTE(SUBSTITUTE(SUBSTITUTE(SUBSTITUTE(SUBSTITUTE(LOWER(Registro!$E11)," ",""),CHAR(10),"|"),";","|"),"+","|"),"|",REPT(" ",LEN(Registro!$E11))),({1,2,3,4,5,6,7,8,9,10,11,12,13,14,15,16,17,18,19,20,21,22,23,24,25,26,27,28,29,30}-1)*LEN(Registro!$E11)+1,LEN(Registro!$E11)))&"x")+1,20))),"Revisar formato"))) -> 1690 | F11: =IF(Registro!$F11="","",N(Registro!$F11)) | G11: =IF(AND(E11="",F11=""),"",IF(OR(E11="",ISNUMBER(E11)),N(E11)-N(F11),E11)) -> 1690 | H11: =IF(Registro!$G11="","",IF(ISERROR(FIND("x",LOWER(Registro!$G11))),"-",IFERROR(SUMPRODUCT(--("0"&LEFT(TRIM(MID(SUBSTITUTE(SUBSTITUTE(SUBSTITUTE(SUBSTITUTE(SUBSTITUTE(LOWER(Registro!$G11)," ",""),CHAR(10),"|"),";","|"),"+","|"),"|",REPT(" ",LEN(Registro!$G11))),({1,2,3,4,5,6,7,8,9,10,11,12,13,14,15,16,17,18,19,20,21,22,23,24,25,26,27,28,29,30}-1)*LEN(Registro!$G11)+1,LEN(Registro!$G11))),FIND("x",TRIM(MID(SUBSTITUTE(SUBSTITUTE(SUBSTITUTE(SUBSTITUTE(SUBSTITUTE(LOWER(Registro!$G11)," ",""),CHAR(10),"|"),";","|"),"+","|"),"|",REPT(" ",LEN(Registro!$G11))),({1,2,3,4,5,6,7,8,9,10,11,12,13,14,15,16,17,18,19,20,21,22,23,24,25,26,27,28,29,30}-1)*LEN(Registro!$G11)+1,LEN(Registro!$G11)))&"x")-1))),"Revisar formato"))) -> 1 | I11: =IF(Registro!$G11="","",IF(ISERROR(FIND("x",LOWER(Registro!$G11))),N(Registro!$H11),IFERROR(SUMPRODUCT(--("0"&LEFT(TRIM(MID(SUBSTITUTE(SUBSTITUTE(SUBSTITUTE(SUBSTITUTE(SUBSTITUTE(LOWER(Registro!$G11)," ",""),CHAR(10),"|"),";","|"),"+","|"),"|",REPT(" ",LEN(Registro!$G11))),({1,2,3,4,5,6,7,8,9,10,11,12,13,14,15,16,17,18,19,20,21,22,23,24,25,26,27,28,29,30}-1)*LEN(Registro!$G11)+1,LEN(Registro!$G11))),FIND("x",TRIM(MID(SUBSTITUTE(SUBSTITUTE(SUBSTITUTE(SUBSTITUTE(SUBSTITUTE(LOWER(Registro!$G11)," ",""),CHAR(10),"|"),";","|"),"+","|"),"|",REPT(" ",LEN(Registro!$G11))),({1,2,3,4,5,6,7,8,9,10,11,12,13,14,15,16,17,18,19,20,21,22,23,24,25,26,27,28,29,30}-1)*LEN(Registro!$G11)+1,LEN(Registro!$G11)))&"x")-1)),--("0"&MID(TRIM(MID(SUBSTITUTE(SUBSTITUTE(SUBSTITUTE(SUBSTITUTE(SUBSTITUTE(LOWER(Registro!$G11)," ",""),CHAR(10),"|"),";","|"),"+","|"),"|",REPT(" ",LEN(Registro!$G11))),({1,2,3,4,5,6,7,8,9,10,11,12,13,14,15,16,17,18,19,20,21,22,23,24,25,26,27,28,29,30}-1)*LEN(Registro!$G11)+1,LEN(Registro!$G11))),FIND("x",TRIM(MID(SUBSTITUTE(SUBSTITUTE(SUBSTITUTE(SUBSTITUTE(SUBSTITUTE(LOWER(Registro!$G11)," ",""),CHAR(10),"|"),";","|"),"+","|"),"|",REPT(" ",LEN(Registro!$G11))),({1,2,3,4,5,6,7,8,9,10,11,12,13,14,15,16,17,18,19,20,21,22,23,24,25,26,27,28,29,30}-1)*LEN(Registro!$G11)+1,LEN(Registro!$G11)))&"x")+1,20))),"Revisar formato"))) -> 3670 | J11: =IF(AND(Registro!$E11="",Registro!$G11=""),"",IF(NOT(AND(ISNUMBER(I11),ISNUMBER(Registro!$H11))),"",IF(I11<Registro!$H11,"FALTA BOLETOS",IF(I11=Registro!$H11,"CONFORME","DIFERENCIA")))) -> CONFORME | K11: =IF(Registro!$I11="","",IFERROR(SUMPRODUCT(--("0"&TRIM(RIGHT(SUBSTITUTE(TRIM(MID(SUBSTITUTE(SUBSTITUTE(Registro!$I11,";",CHAR(10)),CHAR(10),REPT(" ",LEN(Registro!$I11))),({1,2,3,4,5,6,7,8,9,10,11,12,13,14,15,16,17,18,19,20,21,22,23,24,25,26,27,28,29,30}-1)*LEN(Registro!$I11)+1,LEN(Registro!$I11)))," ",REPT(" ",50)),50)))),"Revisar formato")) -> 100 | L11: =IF(Registro!$J11="","",IFERROR(SUMPRODUCT(--("0"&TRIM(RIGHT(SUBSTITUTE(TRIM(MID(SUBSTITUTE(SUBSTITUTE(Registro!$J11,";",CHAR(10)),CHAR(10),REPT(" ",LEN(Registro!$J11))),({1,2,3,4,5,6,7,8,9,10,11,12,13,14,15,16,17,18,19,20,21,22,23,24,25,26,27,28,29,30}-1)*LEN(Registro!$J11)+1,LEN(Registro!$J11)))," ",REPT(" ",50)),50)))),"Revisar formato")) -> 8380 | M11: =IF(AND(Registro!$H11="",Registro!$I11=""),"",IF(AND(ISTEXT(K11),K11<>""),"Revisar formato",N(Registro!$H11)-N(K11))) -> 3570 | N11: =IF(M11="","",IF(OR(M11="Revisar formato",AND(ISTEXT(L11),L11<>"")),"Revisar formato",M11-N(L11))) -> -4810 | O11: =IF(AND(A11=Consulta!$B$3,C11=Consulta!$H$3),B11*10000+ROW(),"") -> 463050011
A12: =IF(Registro!$A12="","",Registro!$A12) -> TDS | B12: =IF(Registro!$B12="","",Registro!$B12) -> 46305 | C12: =IF(ISNUMBER(B12),YEAR(B12)*100+MONTH(B12),"") -> 202610 | D12: =IF(Registro!$E12="","",IF(ISERROR(FIND("x",LOWER(Registro!$E12))),"-",IFERROR(SUMPRODUCT(--("0"&LEFT(TRIM(MID(SUBSTITUTE(SUBSTITUTE(SUBSTITUTE(SUBSTITUTE(SUBSTITUTE(LOWER(Registro!$E12)," ",""),CHAR(10),"|"),";","|"),"+","|"),"|",REPT(" ",LEN(Registro!$E12))),({1,2,3,4,5,6,7,8,9,10,11,12,13,14,15,16,17,18,19,20,21,22,23,24,25,26,27,28,29,30}-1)*LEN(Registro!$E12)+1,LEN(Registro!$E12))),FIND("x",TRIM(MID(SUBSTITUTE(SUBSTITUTE(SUBSTITUTE(SUBSTITUTE(SUBSTITUTE(LOWER(Registro!$E12)," ",""),CHAR(10),"|"),";","|"),"+","|"),"|",REPT(" ",LEN(Registro!$E12))),({1,2,3,4,5,6,7,8,9,10,11,12,13,14,15,16,17,18,19,20,21,22,23,24,25,26,27,28,29,30}-1)*LEN(Registro!$E12)+1,LEN(Registro!$E12)))&"x")-1))),"Revisar formato"))) -> 45 | E12: =IF(Registro!$E12="","",IF(ISERROR(FIND("x",LOWER(Registro!$E12))),"-",IFERROR(SUMPRODUCT(--("0"&LEFT(TRIM(MID(SUBSTITUTE(SUBSTITUTE(SUBSTITUTE(SUBSTITUTE(SUBSTITUTE(LOWER(Registro!$E12)," ",""),CHAR(10),"|"),";","|"),"+","|"),"|",REPT(" ",LEN(Registro!$E12))),({1,2,3,4,5,6,7,8,9,10,11,12,13,14,15,16,17,18,19,20,21,22,23,24,25,26,27,28,29,30}-1)*LEN(Registro!$E12)+1,LEN(Registro!$E12))),FIND("x",TRIM(MID(SUBSTITUTE(SUBSTITUTE(SUBSTITUTE(SUBSTITUTE(SUBSTITUTE(LOWER(Registro!$E12)," ",""),CHAR(10),"|"),";","|"),"+","|"),"|",REPT(" ",LEN(Registro!$E12))),({1,2,3,4,5,6,7,8,9,10,11,12,13,14,15,16,17,18,19,20,21,22,23,24,25,26,27,28,29,30}-1)*LEN(Registro!$E12)+1,LEN(Registro!$E12)))&"x")-1)),--("0"&MID(TRIM(MID(SUBSTITUTE(SUBSTITUTE(SUBSTITUTE(SUBSTITUTE(SUBSTITUTE(LOWER(Registro!$E12)," ",""),CHAR(10),"|"),";","|"),"+","|"),"|",REPT(" ",LEN(Registro!$E12))),({1,2,3,4,5,6,7,8,9,10,11,12,13,14,15,16,17,18,19,20,21,22,23,24,25,26,27,28,29,30}-1)*LEN(Registro!$E12)+1,LEN(Registro!$E12))),FIND("x",TRIM(MID(SUBSTITUTE(SUBSTITUTE(SUBSTITUTE(SUBSTITUTE(SUBSTITUTE(LOWER(Registro!$E12)," ",""),CHAR(10),"|"),";","|"),"+","|"),"|",REPT(" ",LEN(Registro!$E12))),({1,2,3,4,5,6,7,8,9,10,11,12,13,14,15,16,17,18,19,20,21,22,23,24,25,26,27,28,29,30}-1)*LEN(Registro!$E12)+1,LEN(Registro!$E12)))&"x")+1,20))),"Revisar formato"))) -> 1995 | F12: =IF(Registro!$F12="","",N(Registro!$F12)) | G12: =IF(AND(E12="",F12=""),"",IF(OR(E12="",ISNUMBER(E12)),N(E12)-N(F12),E12)) -> 1995 | H12: =IF(Registro!$G12="","",IF(ISERROR(FIND("x",LOWER(Registro!$G12))),"-",IFERROR(SUMPRODUCT(--("0"&LEFT(TRIM(MID(SUBSTITUTE(SUBSTITUTE(SUBSTITUTE(SUBSTITUTE(SUBSTITUTE(LOWER(Registro!$G12)," ",""),CHAR(10),"|"),";","|"),"+","|"),"|",REPT(" ",LEN(Registro!$G12))),({1,2,3,4,5,6,7,8,9,10,11,12,13,14,15,16,17,18,19,20,21,22,23,24,25,26,27,28,29,30}-1)*LEN(Registro!$G12)+1,LEN(Registro!$G12))),FIND("x",TRIM(MID(SUBSTITUTE(SUBSTITUTE(SUBSTITUTE(SUBSTITUTE(SUBSTITUTE(LOWER(Registro!$G12)," ",""),CHAR(10),"|"),";","|"),"+","|"),"|",REPT(" ",LEN(Registro!$G12))),({1,2,3,4,5,6,7,8,9,10,11,12,13,14,15,16,17,18,19,20,21,22,23,24,25,26,27,28,29,30}-1)*LEN(Registro!$G12)+1,LEN(Registro!$G12)))&"x")-1))),"Revisar formato"))) -> 1 | I12: =IF(Registro!$G12="","",IF(ISERROR(FIND("x",LOWER(Registro!$G12))),N(Registro!$H12),IFERROR(SUMPRODUCT(--("0"&LEFT(TRIM(MID(SUBSTITUTE(SUBSTITUTE(SUBSTITUTE(SUBSTITUTE(SUBSTITUTE(LOWER(Registro!$G12)," ",""),CHAR(10),"|"),";","|"),"+","|"),"|",REPT(" ",LEN(Registro!$G12))),({1,2,3,4,5,6,7,8,9,10,11,12,13,14,15,16,17,18,19,20,21,22,23,24,25,26,27,28,29,30}-1)*LEN(Registro!$G12)+1,LEN(Registro!$G12))),FIND("x",TRIM(MID(SUBSTITUTE(SUBSTITUTE(SUBSTITUTE(SUBSTITUTE(SUBSTITUTE(LOWER(Registro!$G12)," ",""),CHAR(10),"|"),";","|"),"+","|"),"|",REPT(" ",LEN(Registro!$G12))),({1,2,3,4,5,6,7,8,9,10,11,12,13,14,15,16,17,18,19,20,21,22,23,24,25,26,27,28,29,30}-1)*LEN(Registro!$G12)+1,LEN(Registro!$G12)))&"x")-1)),--("0"&MID(TRIM(MID(SUBSTITUTE(SUBSTITUTE(SUBSTITUTE(SUBSTITUTE(SUBSTITUTE(LOWER(Registro!$G12)," ",""),CHAR(10),"|"),";","|"),"+","|"),"|",REPT(" ",LEN(Registro!$G12))),({1,2,3,4,5,6,7,8,9,10,11,12,13,14,15,16,17,18,19,20,21,22,23,24,25,26,27,28,29,30}-1)*LEN(Registro!$G12)+1,LEN(Registro!$G12))),FIND("x",TRIM(MID(SUBSTITUTE(SUBSTITUTE(SUBSTITUTE(SUBSTITUTE(SUBSTITUTE(LOWER(Registro!$G12)," ",""),CHAR(10),"|"),";","|"),"+","|"),"|",REPT(" ",LEN(Registro!$G12))),({1,2,3,4,5,6,7,8,9,10,11,12,13,14,15,16,17,18,19,20,21,22,23,24,25,26,27,28,29,30}-1)*LEN(Registro!$G12)+1,LEN(Registro!$G12)))&"x")+1,20))),"Revisar formato"))) -> 2100 | J12: =IF(AND(Registro!$E12="",Registro!$G12=""),"",IF(NOT(AND(ISNUMBER(I12),ISNUMBER(Registro!$H12))),"",IF(I12<Registro!$H12,"FALTA BOLETOS",IF(I12=Registro!$H12,"CONFORME","DIFERENCIA")))) -> CONFORME | K12: =IF(Registro!$I12="","",IFERROR(SUMPRODUCT(--("0"&TRIM(RIGHT(SUBSTITUTE(TRIM(MID(SUBSTITUTE(SUBSTITUTE(Registro!$I12,";",CHAR(10)),CHAR(10),REPT(" ",LEN(Registro!$I12))),({1,2,3,4,5,6,7,8,9,10,11,12,13,14,15,16,17,18,19,20,21,22,23,24,25,26,27,28,29,30}-1)*LEN(Registro!$I12)+1,LEN(Registro!$I12)))," ",REPT(" ",50)),50)))),"Revisar formato")) | L12: =IF(Registro!$J12="","",IFERROR(SUMPRODUCT(--("0"&TRIM(RIGHT(SUBSTITUTE(TRIM(MID(SUBSTITUTE(SUBSTITUTE(Registro!$J12,";",CHAR(10)),CHAR(10),REPT(" ",LEN(Registro!$J12))),({1,2,3,4,5,6,7,8,9,10,11,12,13,14,15,16,17,18,19,20,21,22,23,24,25,26,27,28,29,30}-1)*LEN(Registro!$J12)+1,LEN(Registro!$J12)))," ",REPT(" ",50)),50)))),"Revisar formato")) | M12: =IF(AND(Registro!$H12="",Registro!$I12=""),"",IF(AND(ISTEXT(K12),K12<>""),"Revisar formato",N(Registro!$H12)-N(K12))) -> 2100 | N12: =IF(M12="","",IF(OR(M12="Revisar formato",AND(ISTEXT(L12),L12<>"")),"Revisar formato",M12-N(L12))) -> 2100 | O12: =IF(AND(A12=Consulta!$B$3,C12=Consulta!$H$3),B12*10000+ROW(),"") -> 463050012
A13: =IF(Registro!$A13="","",Registro!$A13) -> TDS | B13: =IF(Registro!$B13="","",Registro!$B13) -> 46306 | C13: =IF(ISNUMBER(B13),YEAR(B13)*100+MONTH(B13),"") -> 202610 | D13: =IF(Registro!$E13="","",IF(ISERROR(FIND("x",LOWER(Registro!$E13))),"-",IFERROR(SUMPRODUCT(--("0"&LEFT(TRIM(MID(SUBSTITUTE(SUBSTITUTE(SUBSTITUTE(SUBSTITUTE(SUBSTITUTE(LOWER(Registro!$E13)," ",""),CHAR(10),"|"),";","|"),"+","|"),"|",REPT(" ",LEN(Registro!$E13))),({1,2,3,4,5,6,7,8,9,10,11,12,13,14,15,16,17,18,19,20,21,22,23,24,25,26,27,28,29,30}-1)*LEN(Registro!$E13)+1,LEN(Registro!$E13))),FIND("x",TRIM(MID(SUBSTITUTE(SUBSTITUTE(SUBSTITUTE(SUBSTITUTE(SUBSTITUTE(LOWER(Registro!$E13)," ",""),CHAR(10),"|"),";","|"),"+","|"),"|",REPT(" ",LEN(Registro!$E13))),({1,2,3,4,5,6,7,8,9,10,11,12,13,14,15,16,17,18,19,20,21,22,23,24,25,26,27,28,29,30}-1)*LEN(Registro!$E13)+1,LEN(Registro!$E13)))&"x")-1))),"Revisar formato"))) -> 50 | E13: =IF(Registro!$E13="","",IF(ISERROR(FIND("x",LOWER(Registro!$E13))),"-",IFERROR(SUMPRODUCT(--("0"&LEFT(TRIM(MID(SUBSTITUTE(SUBSTITUTE(SUBSTITUTE(SUBSTITUTE(SUBSTITUTE(LOWER(Registro!$E13)," ",""),CHAR(10),"|"),";","|"),"+","|"),"|",REPT(" ",LEN(Registro!$E13))),({1,2,3,4,5,6,7,8,9,10,11,12,13,14,15,16,17,18,19,20,21,22,23,24,25,26,27,28,29,30}-1)*LEN(Registro!$E13)+1,LEN(Registro!$E13))),FIND("x",TRIM(MID(SUBSTITUTE(SUBSTITUTE(SUBSTITUTE(SUBSTITUTE(SUBSTITUTE(LOWER(Registro!$E13)," ",""),CHAR(10),"|"),";","|"),"+","|"),"|",REPT(" ",LEN(Registro!$E13))),({1,2,3,4,5,6,7,8,9,10,11,12,13,14,15,16,17,18,19,20,21,22,23,24,25,26,27,28,29,30}-1)*LEN(Registro!$E13)+1,LEN(Registro!$E13)))&"x")-1)),--("0"&MID(TRIM(MID(SUBSTITUTE(SUBSTITUTE(SUBSTITUTE(SUBSTITUTE(SUBSTITUTE(LOWER(Registro!$E13)," ",""),CHAR(10),"|"),";","|"),"+","|"),"|",REPT(" ",LEN(Registro!$E13))),({1,2,3,4,5,6,7,8,9,10,11,12,13,14,15,16,17,18,19,20,21,22,23,24,25,26,27,28,29,30}-1)*LEN(Registro!$E13)+1,LEN(Registro!$E13))),FIND("x",TRIM(MID(SUBSTITUTE(SUBSTITUTE(SUBSTITUTE(SUBSTITUTE(SUBSTITUTE(LOWER(Registro!$E13)," ",""),CHAR(10),"|"),";","|"),"+","|"),"|",REPT(" ",LEN(Registro!$E13))),({1,2,3,4,5,6,7,8,9,10,11,12,13,14,15,16,17,18,19,20,21,22,23,24,25,26,27,28,29,30}-1)*LEN(Registro!$E13)+1,LEN(Registro!$E13)))&"x")+1,20))),"Revisar formato"))) -> 2580 | F13: =IF(Registro!$F13="","",N(Registro!$F13)) | G13: =IF(AND(E13="",F13=""),"",IF(OR(E13="",ISNUMBER(E13)),N(E13)-N(F13),E13)) -> 2580 | H13: =IF(Registro!$G13="","",IF(ISERROR(FIND("x",LOWER(Registro!$G13))),"-",IFERROR(SUMPRODUCT(--("0"&LEFT(TRIM(MID(SUBSTITUTE(SUBSTITUTE(SUBSTITUTE(SUBSTITUTE(SUBSTITUTE(LOWER(Registro!$G13)," ",""),CHAR(10),"|"),";","|"),"+","|"),"|",REPT(" ",LEN(Registro!$G13))),({1,2,3,4,5,6,7,8,9,10,11,12,13,14,15,16,17,18,19,20,21,22,23,24,25,26,27,28,29,30}-1)*LEN(Registro!$G13)+1,LEN(Registro!$G13))),FIND("x",TRIM(MID(SUBSTITUTE(SUBSTITUTE(SUBSTITUTE(SUBSTITUTE(SUBSTITUTE(LOWER(Registro!$G13)," ",""),CHAR(10),"|"),";","|"),"+","|"),"|",REPT(" ",LEN(Registro!$G13))),({1,2,3,4,5,6,7,8,9,10,11,12,13,14,15,16,17,18,19,20,21,22,23,24,25,26,27,28,29,30}-1)*LEN(Registro!$G13)+1,LEN(Registro!$G13)))&"x")-1))),"Revisar formato"))) -> 1 | I13: =IF(Registro!$G13="","",IF(ISERROR(FIND("x",LOWER(Registro!$G13))),N(Registro!$H13),IFERROR(SUMPRODUCT(--("0"&LEFT(TRIM(MID(SUBSTITUTE(SUBSTITUTE(SUBSTITUTE(SUBSTITUTE(SUBSTITUTE(LOWER(Registro!$G13)," ",""),CHAR(10),"|"),";","|"),"+","|"),"|",REPT(" ",LEN(Registro!$G13))),({1,2,3,4,5,6,7,8,9,10,11,12,13,14,15,16,17,18,19,20,21,22,23,24,25,26,27,28,29,30}-1)*LEN(Registro!$G13)+1,LEN(Registro!$G13))),FIND("x",TRIM(MID(SUBSTITUTE(SUBSTITUTE(SUBSTITUTE(SUBSTITUTE(SUBSTITUTE(LOWER(Registro!$G13)," ",""),CHAR(10),"|"),";","|"),"+","|"),"|",REPT(" ",LEN(Registro!$G13))),({1,2,3,4,5,6,7,8,9,10,11,12,13,14,15,16,17,18,19,20,21,22,23,24,25,26,27,28,29,30}-1)*LEN(Registro!$G13)+1,LEN(Registro!$G13)))&"x")-1)),--("0"&MID(TRIM(MID(SUBSTITUTE(SUBSTITUTE(SUBSTITUTE(SUBSTITUTE(SUBSTITUTE(LOWER(Registro!$G13)," ",""),CHAR(10),"|"),";","|"),"+","|"),"|",REPT(" ",LEN(Registro!$G13))),({1,2,3,4,5,6,7,8,9,10,11,12,13,14,15,16,17,18,19,20,21,22,23,24,25,26,27,28,29,30}-1)*LEN(Registro!$G13)+1,LEN(Registro!$G13))),FIND("x",TRIM(MID(SUBSTITUTE(SUBSTITUTE(SUBSTITUTE(SUBSTITUTE(SUBSTITUTE(LOWER(Registro!$G13)," ",""),CHAR(10),"|"),";","|"),"+","|"),"|",REPT(" ",LEN(Registro!$G13))),({1,2,3,4,5,6,7,8,9,10,11,12,13,14,15,16,17,18,19,20,21,22,23,24,25,26,27,28,29,30}-1)*LEN(Registro!$G13)+1,LEN(Registro!$G13)))&"x")+1,20))),"Revisar formato"))) -> 5280 | J13: =IF(AND(Registro!$E13="",Registro!$G13=""),"",IF(NOT(AND(ISNUMBER(I13),ISNUMBER(Registro!$H13))),"",IF(I13<Registro!$H13,"FALTA BOLETOS",IF(I13=Registro!$H13,"CONFORME","DIFERENCIA")))) -> CONFORME | K13: =IF(Registro!$I13="","",IFERROR(SUMPRODUCT(--("0"&TRIM(RIGHT(SUBSTITUTE(TRIM(MID(SUBSTITUTE(SUBSTITUTE(Registro!$I13,";",CHAR(10)),CHAR(10),REPT(" ",LEN(Registro!$I13))),({1,2,3,4,5,6,7,8,9,10,11,12,13,14,15,16,17,18,19,20,21,22,23,24,25,26,27,28,29,30}-1)*LEN(Registro!$I13)+1,LEN(Registro!$I13)))," ",REPT(" ",50)),50)))),"Revisar formato")) -> 130 | L13: =IF(Registro!$J13="","",IFERROR(SUMPRODUCT(--("0"&TRIM(RIGHT(SUBSTITUTE(TRIM(MID(SUBSTITUTE(SUBSTITUTE(Registro!$J13,";",CHAR(10)),CHAR(10),REPT(" ",LEN(Registro!$J13))),({1,2,3,4,5,6,7,8,9,10,11,12,13,14,15,16,17,18,19,20,21,22,23,24,25,26,27,28,29,30}-1)*LEN(Registro!$J13)+1,LEN(Registro!$J13)))," ",REPT(" ",50)),50)))),"Revisar formato")) | M13: =IF(AND(Registro!$H13="",Registro!$I13=""),"",IF(AND(ISTEXT(K13),K13<>""),"Revisar formato",N(Registro!$H13)-N(K13))) -> 5150 | N13: =IF(M13="","",IF(OR(M13="Revisar formato",AND(ISTEXT(L13),L13<>"")),"Revisar formato",M13-N(L13))) -> 5150 | O13: =IF(AND(A13=Consulta!$B$3,C13=Consulta!$H$3),B13*10000+ROW(),"") -> 463060013
... A1001: =IF(Registro!$A1001="","",Registro!$A1001) | B1001: =IF(Registro!$B1001="","",Registro!$B1001) | C1001: =IF(ISNUMBER(B1001),YEAR(B1001)*100+MONTH(B1001),"") | D1001: =IF(Registro!$E1001="","",IF(ISERROR(FIND("x",LOWER(Registro!$E1001))),"-",IFERROR(SUMPRODUCT(--("0"&LEFT(TRIM(MID(SUBSTITUTE(SUBSTITUTE(SUBSTITUTE(SUBSTITUTE(SUBSTITUTE(LOWER(Registro!$E1001)," ",""),CHAR(10),"|"),";","|"),"+","|"),"|",REPT(" ",LEN(Registro!$E1001))),({1,2,3,4,5,6,7,8,9,10,11,12,13,14,15,16,17,18,19,20,21,22,23,24,25,26,27,28,29,30}-1)*LEN(Registro!$E1001)+1,LEN(Registro!$E1001))),FIND("x",TRIM(MID(SUBSTITUTE(SUBSTITUTE(SUBSTITUTE(SUBSTITUTE(SUBSTITUTE(LOWER(Registro!$E1001)," ",""),CHAR(10),"|"),";","|"),"+","|"),"|",REPT(" ",LEN(Registro!$E1001))),({1,2,3,4,5,6,7,8,9,10,11,12,13,14,15,16,17,18,19,20,21,22,23,24,25,26,27,28,29,30}-1)*LEN(Registro!$E1001)+1,LEN(Registro!$E1001)))&"x")-1))),"Revisar formato"))) | E1001: =IF(Registro!$E1001="","",IF(ISERROR(FIND("x",LOWER(Registro!$E1001))),"-",IFERROR(SUMPRODUCT(--("0"&LEFT(TRIM(MID(SUBSTITUTE(SUBSTITUTE(SUBSTITUTE(SUBSTITUTE(SUBSTITUTE(LOWER(Registro!$E1001)," ",""),CHAR(10),"|"),";","|"),"+","|"),"|",REPT(" ",LEN(Registro!$E1001))),({1,2,3,4,5,6,7,8,9,10,11,12,13,14,15,16,17,18,19,20,21,22,23,24,25,26,27,28,29,30}-1)*LEN(Registro!$E1001)+1,LEN(Registro!$E1001))),FIND("x",TRIM(MID(SUBSTITUTE(SUBSTITUTE(SUBSTITUTE(SUBSTITUTE(SUBSTITUTE(LOWER(Registro!$E1001)," ",""),CHAR(10),"|"),";","|"),"+","|"),"|",REPT(" ",LEN(Registro!$E1001))),({1,2,3,4,5,6,7,8,9,10,11,12,13,14,15,16,17,18,19,20,21,22,23,24,25,26,27,28,29,30}-1)*LEN(Registro!$E1001)+1,LEN(Registro!$E1001)))&"x")-1)),--("0"&MID(TRIM(MID(SUBSTITUTE(SUBSTITUTE(SUBSTITUTE(SUBSTITUTE(SUBSTITUTE(LOWER(Registro!$E1001)," ",""),CHAR(10),"|"),";","|"),"+","|"),"|",REPT(" ",LEN(Registro!$E1001))),({1,2,3,4,5,6,7,8,9,10,11,12,13,14,15,16,17,18,19,20,21,22,23,24,25,26,27,28,29,30}-1)*LEN(Registro!$E1001)+1,LEN(Registro!$E1001))),FIND("x",TRIM(MID(SUBSTITUTE(SUBSTITUTE(SUBSTITUTE(SUBSTITUTE(SUBSTITUTE(LOWER(Registro!$E1001)," ",""),CHAR(10),"|"),";","|"),"+","|"),"|",REPT(" ",LEN(Registro!$E1001))),({1,2,3,4,5,6,7,8,9,10,11,12,13,14,15,16,17,18,19,20,21,22,23,24,25,26,27,28,29,30}-1)*LEN(Registro!$E1001)+1,LEN(Registro!$E1001)))&"x")+1,20))),"Revisar formato"))) | F1001: =IF(Registro!$F1001="","",N(Registro!$F1001)) | G1001: =IF(AND(E1001="",F1001=""),"",IF(OR(E1001="",ISNUMBER(E1001)),N(E1001)-N(F1001),E1001)) | H1001: =IF(Registro!$G1001="","",IF(ISERROR(FIND("x",LOWER(Registro!$G1001))),"-",IFERROR(SUMPRODUCT(--("0"&LEFT(TRIM(MID(SUBSTITUTE(SUBSTITUTE(SUBSTITUTE(SUBSTITUTE(SUBSTITUTE(LOWER(Registro!$G1001)," ",""),CHAR(10),"|"),";","|"),"+","|"),"|",REPT(" ",LEN(Registro!$G1001))),({1,2,3,4,5,6,7,8,9,10,11,12,13,14,15,16,17,18,19,20,21,22,23,24,25,26,27,28,29,30}-1)*LEN(Registro!$G1001)+1,LEN(Registro!$G1001))),FIND("x",TRIM(MID(SUBSTITUTE(SUBSTITUTE(SUBSTITUTE(SUBSTITUTE(SUBSTITUTE(LOWER(Registro!$G1001)," ",""),CHAR(10),"|"),";","|"),"+","|"),"|",REPT(" ",LEN(Registro!$G1001))),({1,2,3,4,5,6,7,8,9,10,11,12,13,14,15,16,17,18,19,20,21,22,23,24,25,26,27,28,29,30}-1)*LEN(Registro!$G1001)+1,LEN(Registro!$G1001)))&"x")-1))),"Revisar formato"))) | I1001: =IF(Registro!$G1001="","",IF(ISERROR(FIND("x",LOWER(Registro!$G1001))),N(Registro!$H1001),IFERROR(SUMPRODUCT(--("0"&LEFT(TRIM(MID(SUBSTITUTE(SUBSTITUTE(SUBSTITUTE(SUBSTITUTE(SUBSTITUTE(LOWER(Registro!$G1001)," ",""),CHAR(10),"|"),";","|"),"+","|"),"|",REPT(" ",LEN(Registro!$G1001))),({1,2,3,4,5,6,7,8,9,10,11,12,13,14,15,16,17,18,19,20,21,22,23,24,25,26,27,28,29,30}-1)*LEN(Registro!$G1001)+1,LEN(Registro!$G1001))),FIND("x",TRIM(MID(SUBSTITUTE(SUBSTITUTE(SUBSTITUTE(SUBSTITUTE(SUBSTITUTE(LOWER(Registro!$G1001)," ",""),CHAR(10),"|"),";","|"),"+","|"),"|",REPT(" ",LEN(Registro!$G1001))),({1,2,3,4,5,6,7,8,9,10,11,12,13,14,15,16,17,18,19,20,21,22,23,24,25,26,27,28,29,30}-1)*LEN(Registro!$G1001)+1,LEN(Registro!$G1001)))&"x")-1)),--("0"&MID(TRIM(MID(SUBSTITUTE(SUBSTITUTE(SUBSTITUTE(SUBSTITUTE(SUBSTITUTE(LOWER(Registro!$G1001)," ",""),CHAR(10),"|"),";","|"),"+","|"),"|",REPT(" ",LEN(Registro!$G1001))),({1,2,3,4,5,6,7,8,9,10,11,12,13,14,15,16,17,18,19,20,21,22,23,24,25,26,27,28,29,30}-1)*LEN(Registro!$G1001)+1,LEN(Registro!$G1001))),FIND("x",TRIM(MID(SUBSTITUTE(SUBSTITUTE(SUBSTITUTE(SUBSTITUTE(SUBSTITUTE(LOWER(Registro!$G1001)," ",""),CHAR(10),"|"),";","|"),"+","|"),"|",REPT(" ",LEN(Registro!$G1001))),({1,2,3,4,5,6,7,8,9,10,11,12,13,14,15,16,17,18,19,20,21,22,23,24,25,26,27,28,29,30}-1)*LEN(Registro!$G1001)+1,LEN(Registro!$G1001)))&"x")+1,20))),"Revisar formato"))) | J1001: =IF(AND(Registro!$E1001="",Registro!$G1001=""),"",IF(NOT(AND(ISNUMBER(I1001),ISNUMBER(Registro!$H1001))),"",IF(I1001<Registro!$H1001,"FALTA BOLETOS",IF(I1001=Registro!$H1001,"CONFORME","DIFERENCIA")))) | K1001: =IF(Registro!$I1001="","",IFERROR(SUMPRODUCT(--("0"&TRIM(RIGHT(SUBSTITUTE(TRIM(MID(SUBSTITUTE(SUBSTITUTE(Registro!$I1001,";",CHAR(10)),CHAR(10),REPT(" ",LEN(Registro!$I1001))),({1,2,3,4,5,6,7,8,9,10,11,12,13,14,15,16,17,18,19,20,21,22,23,24,25,26,27,28,29,30}-1)*LEN(Registro!$I1001)+1,LEN(Registro!$I1001)))," ",REPT(" ",50)),50)))),"Revisar formato")) | L1001: =IF(Registro!$J1001="","",IFERROR(SUMPRODUCT(--("0"&TRIM(RIGHT(SUBSTITUTE(TRIM(MID(SUBSTITUTE(SUBSTITUTE(Registro!$J1001,";",CHAR(10)),CHAR(10),REPT(" ",LEN(Registro!$J1001))),({1,2,3,4,5,6,7,8,9,10,11,12,13,14,15,16,17,18,19,20,21,22,23,24,25,26,27,28,29,30}-1)*LEN(Registro!$J1001)+1,LEN(Registro!$J1001)))," ",REPT(" ",50)),50)))),"Revisar formato")) | M1001: =IF(AND(Registro!$H1001="",Registro!$I1001=""),"",IF(AND(ISTEXT(K1001),K1001<>""),"Revisar formato",N(Registro!$H1001)-N(K1001))) | N1001: =IF(M1001="","",IF(OR(M1001="Revisar formato",AND(ISTEXT(L1001),L1001<>"")),"Revisar formato",M1001-N(L1001))) | O1001: =IF(AND(A1001=Consulta!$B$3,C1001=Consulta!$H$3),B1001*10000+ROW(),"")
